Workbook
Name Business: BaseData!$G$2:$G$6
Name CustomerExtern: BaseData!$H$2:$H$49
Name Customers: BaseData!$B$2:$B$69
Name Duparec: Depot!$C$2:$C$13
Name HRAdria: Depot!$D$2:$D$13
Name HRBulgaria: Depot!$E$2:$E$13
Name HRCZ: Depot!$M$2:$M$13
Name HREns: Depot!$F$2:$F$13
Name HRGroup: Depot!$G$2:$G$13
Name HRNZ: Depot!$H$2:$H$13
Name HRPolska: Depot!$I$2:$I$13
Name HRRomania: Depot!$J$2:$J$13
Name HRTurkey: Depot!$K$2:$K$13
Name MA200_: DropDownLists!$L$2:$L$101
Name MA210_: DropDownLists!$M$2:$M$101
Name MA215_: DropDownLists!$N$2:$N$101
Name MA230_: DropDownLists!$O$2:$O$101
Name MA240_: DropDownLists!$P$2:$P$101
Name MA250_: DropDownLists!$Q$2:$Q$101
Name MA260_: DropDownLists!$R$2:$R$101
Name MA300_: DropDownLists!$S$2
Name NewCompany: Depot!$B$2:$B$13
Name SCHOzon: Depot!$L$2:$L$13
Name Source: BaseData!$F$2:$F$252
Name Supplier: BaseData!$I$2:$I$119
Name TehnopapirBG: Depot!$N$2:$N$13
Name TehnopapirZV: Depot!$O$2:$O$13

Sheet START
B2: Investment form
B4: =IF(C6="","1. Please select the company!","Selected company:") -> Selected company: | G4: Legend/ color guide
C6: 1661 HR Turkey | E6: =VLOOKUP(C6,Depot!$R$2:$S$30,2,0) -> HRTurkey | H6: field with calculated data - no entry!
B8: =IF(C10="","2. Please select the location!","Selected location:") -> Selected location: | H8: field with drop down selection
C10: 166101 Bornova | H10: field for manual data input
B12: =IF(C14="","2. Please select the actual year!","Selected year:") -> Selected year: | H12: field with calculated data from Sales Report - no entry!
C14: 2021 | H14: field to be filled in by Holding
B16: =IF(OR(C18="",E18=""),"4. Please select the local currency and define the exchange rate!","Selected local currency and exchange rate:") -> Selected local currency and exchange rate:
C18: TRY | D18: 1,00 EUR = | E18: 7.5 | F18: =IF(C18="","","(Proposal from Budget 2019 FX rates: "&ROUND(VLOOKUP(START!C18,FXRates2019!$C$10:$D$50,2,0),5)&")") -> (Proposal from Budget 2019 FX rates: 9,67)
C21: The company calculation shall contain
C22: INFOR data | E22: OR | F22: INFOR data | H22: PLUS | I22: Business plan location | K22: RESULTS IN | L22: Business plan company
C23: from Prev year | F23: from FC
C24: 190100 Sveta Helena | F24: 190100 Sveta Helena | L24: 190100 Sveta Helena
F25: 190101 Split | L25: 190101 Split
F26: 190102 Osijek | L26: 190102 Osijek
I27: 190103 Zagreb | L27: 190103 Zagreb
B37: General guide line: Enter P&L values according to INFOR logic:
B38: Revenue values are positive, expense values are negative!
B39: Please consider the investment information below.
B41: INFOR Input
B43: INFOR-PreviousYearEURO
B44: INFOR OneGroup BI PROD - Recycling Actual:
B47: Open the Report "ACT Rep - P&L All Depots"
B48: Select your profit center and the previous year
B49: and Month: "12 YTD", "in thousands" and "Euro"
B74: Open the Report in Excel and copy in following way:
B75: Press "CTRL" and "pos1" (will mark the cell C2)
B76: Hold "Shift" + "CTRL" and press "End" (will mark relevant area)
... B145: business.
C147: A1 Stabilizing or Replacement Investments with positive return
C148: Investments for replacements with additional benefits, e.g. cost saving – stabilizing in the meaning of “modernization”.
C150: A2 Stabilizing or Replacement Investments with no return
C151: e.g. investments and replacements of existing assets, all company cars, investments in office rooms, social rooms, etc.
C153: A3 Investments for Safety, Health, Environmental or other aspects
C154: Legal requirements independent from positive or no return. Investments which secure legal compliance (e.g. fire protection),
C155: safety at work or environmental directives.
B157: (B) Investments with payback
B158: Investment to increase production capacity and/or profitability (low complexity and implementation time within 1 year).
B160: (C) Major Projects
B161: Investment to secure or increase production capacity and/or profitability (high complexity and implementation time longer than 1 year).
B162: These investments relate to large-scale projects such as revitalisations of Profit Centers, plant enlargement projects with payback.
B164: (D) Financial Investments
B165: Share deals, Mergers and Acquisitions.
B166: (D) cannot be handled within this file - you need a separate master file!
B168: (E) Major Repair
B169: No investment but expenses therefore no further treatment within this guideline.
B171: PRINZHORN GROUP GUIDELINES | J171: Version: 1.5 | Issued: Sept. 10th, 2014
B173: General
B174: These principles are the basis for the future investment planning & approval process.The target is to create a common understanding
B175: on the unified investment process and to simplify and speed up the approval process.
B177: Requirements
B178: O | C178: Once a year (budgeting) the investment plans are presented and explained
B179: O | C179: During the business year the overall investment plans needs to be on a monthly basis
B180: O | C180: The general status on Investments (Reporting) should be an integrated part of the monthly Controlling
B181: O | C181: All investments have to be categorized
B182: O | C182: Categorized Investments have to be further prioritized based on its liquidity effect (e.g. urgency / benefit for the business)
C183: into Priority 1 or Priority 2.
B185: Proposals on Major Repairs (“Großreparaturen”) are treated from a process perspective similar to investments but are not covered within
B186: the investment guideline.
B188: Prioritization
B189: All categorized projects have to be ranked based on their priority – Priority 1 or Priority 2. The main characteristic of the PRIO 2 projects
B190: is the possibility to postpone them at least for 1 year. For that reason they will also not have a liquidity effect in our cash flow; while all
B191: PRIO 1 investments are part of the Investment Cash-Flow.
C193: Realisation in the next year - Priority 1
C194: Time critical investments which need to be done within the next business year (<1 year) in order to fulfil legal requirements,
C195: secure current business and level of EBITDA or have an increased payback.
C197: Realisation between 1 year and 3 years - Priority 1 or Priority 2
C198: Less time critical investments which need to be done within the next 2-3 business years (>1 and <3 year) in order to fulfil
C199: legal requirements, secure current business or increase payback. Those investments need to be discussed in the budgeting process
C200: with the Management Board in order to define correct prioritisation in Prio 1 or Prio 2 (total liquidity will decide if Prio 1 is feasible).
C202: Realisation > 3 years - Priority 2
C203: Non time critical investments which are proposed by business in a timeframe > 3 years. These investments should be considered
C204: as Priority 2.
B206: Prioritization has an impact on the treatment of the investments in the budgeting process:
C208: Priority 1
C209: Investments under Priority 1 are cash relevant investments in the complete planning process. These investments will be considered
C210: with all effects on P&L, Balance Sheet and on yearly Cash-Flow.
C212: Priority 2
C213: Investments under Priority 2 will only be listed under our investment projects without any impact on our P&L, Balance Sheet or yearly
C214: Cash-Flow. Only in case of immediate need, cash availability and management decision, will these investments be initiated.
C215: Investments which were approved as Priority 1 in the yearly budgeting process, but the corresponding investment proposal was not
C216: submitted/approved, need to be re-presented in the following budgeting year (the old investment number will be closed and a new
C217: one needs to be opened).
B219: Carry Over
B220: All investments with full proposal approval which are still in progress result in a carry over. No new approval will be needed in the
B221: investment process. These carry overs are tracked by investment tracking and Cash Flow. All investments which are not fully approved
B222: have to be reconsidered in the following years’ budget approval. All investments which have been approved during the budget process
B223: but the corresponding investment proposal is not signed within the according year of planning until Oct. 31 have to be represented
B224: during the budget process in the following year.
B226: Investment approval process
B227: Regardless of prioritisation and categorization of investments in the budgeting process, each investment has to be approved
B228: (Investment Proposal) before the realization is started. At this point financing will be clarified. All Investment Proposals are entered in
B229: functional currency and submitted in Group Currency (Euro) by Infor BI. Based on current Division specific approval processes an
B230: approval hierarchy is defined and supported by the automatic workflow.

Sheet PP_Form
K3: Division | M3: 04
K4: PC | L4: =START!C6 -> 1661 HR Turkey
K5: Project No. | L5: P-12007
C6: Category | D6: [C] Major Project
C8: Priority | D8: NO
C10: Project | D10: Logistic Service Provider For Bornova Counting Center
C12: Project Costs in 1 Euro | D12: ='INVESTMENT per Year'!H21 -> 3013333.3 | F12: thereof Leasing | I12: Budgeted approved
C14: Project Description | D14: Mandatory Deposite System for some beverage packagings will come into force at 2021 depending on the new Environmental Law. 3.business type is expected to be available for this sytem • System Operator • Logistic Company • Counting Center Operator (Antalya and İzmir) The IP is prepared for being a logistic company that delivers packagings to the counting center in Bornova.
C16: Benefit | D16: The new law will give us opportunity to participate the deposite system. That will help us to reach the sources which we can't reach because of the municipality collection contracts. We will have more option to reach the commercial companies.
C18: Remarks
C20: Documentation
C26: Planned start | D26: 44197
C28: Total property an required assets | I28: Efficiency Calculation
C30: MA200 Expend. for setting up & expanding a business | G30: =SUMIF('INVESTMENT per Year'!$E$4:$E$18,C30,'INVESTMENT per Year'!$N$4:$N$18) -> 0 | I30: 11. Additional incomes | M30: =(BusPlanLocation!I42+BusPlanLocation!K42+BusPlanLocation!M42+BusPlanLocation!O42+BusPlanLocation!Q42+BusPlanLocation!S42)/IF(BusPlanLocation!C9="EUR",1,START!$E$18)*1000/D51 -> #REF!
C31: MA210 Concessions, commercial property | G31: =SUMIF('INVESTMENT per Year'!$E$4:$E$18,C31,'INVESTMENT per Year'!$N$4:$N$18) -> 0 | I31: 12. Cost reduction
C32: MA215 Goodwill | G32: =SUMIF('INVESTMENT per Year'!$E$4:$E$18,C32,'INVESTMENT per Year'!$N$4:$N$18) -> 0 | I32: 13. Additional cost (without depr. and financing cost) | M32: =+(M30*D51-(SUM(BusPlanLocation!I92+BusPlanLocation!K92+BusPlanLocation!M92+BusPlanLocation!O92+BusPlanLocation!Q92+BusPlanLocation!S92)/IF(BusPlanLocation!C9="EUR",1,START!$E$18))*1000)/D51 -> #REF!
C33: MA230 Land and similar rights | G33: =SUMIF('INVESTMENT per Year'!$E$4:$E$18,C33,'INVESTMENT per Year'!$N$4:$N$18) -> 0 | I33: 14. Additional EBITDA Contribution | M33: =SUM(M30:M31)-M32 -> #REF!
C34: MA240 Buildings including buildings on third party land | G34: =SUMIF('INVESTMENT per Year'!$E$4:$E$18,C34,'INVESTMENT per Year'!$N$4:$N$18) -> 0
C35: MA250 Technical equipment and machinery | G35: =SUMIF('INVESTMENT per Year'!$E$4:$E$20,C35,'INVESTMENT per Year'!$N$4:$N$20) -> 3640000 | I35: 15. Calc. depr. | M35: =IF(OR(G41="",D52=""),0,G41/D52) -> 1040000
C36: MA260 Other equipment, factory and office equipment | G36: =SUMIF('INVESTMENT per Year'!$E$4:$E$18,C36,'INVESTMENT per Year'!$N$4:$N$18) -> 0 | I36: 16. Additional EBIT Contribution | M36: =M33-M35 -> #REF!
C37: MA300 Shares in affil. companies | G37: =SUMIF('INVESTMENT per Year'!$E$4:$E$18,C37,'INVESTMENT per Year'!$N$4:$N$18) -> 0
C38: 1. Gross Total Property (incl. own services) | G38: =SUM(G30:G37) -> 3640000 | I38: 17. Depreciated lifetime (weighted avg.) in years | M38: ='INVESTMENT per Year'!O21 -> 3.5
I39: 18. Pay back period in years | M39: =IF(M33=0,"",G46/M33) -> #REF!
C40: 2. Residual value of the old equipment | I40: 19. Return on capital employed | M40: =IF(M36=" / ","/",M36/((G41-G34)*0.5+G34+G42)) -> #REF!
C41: 3. Net Total Property | G41: =G38-G40 -> 3640000
C42: 4. Current assets | G42: 0 | I42: Cash Out
C43: 5. Leasing | G43: =G12 -> 0
C44: 6. Expense | G44: 0 | I44: =" Quarter 1 "&START!$C$14 -> Quarter 1 2021 | M44: ='Cashflow per quarter'!G20 -> 3013333.3
C45: 7. Major Repair Expense | G45: 0 | I45: =" Quarter 2 "&START!$C$14 -> Quarter 2 2021 | M45: ='Cashflow per quarter'!H20 -> 0
C46: 8. Invested Capital | G46: =SUM(G41:G45) -> 3640000 | I46: =" Quarter 3 "&START!$C$14 -> Quarter 3 2021 | M46: ='Cashflow per quarter'!I20 -> 0
I47: =" Quarter 4 "&START!$C$14 -> Quarter 4 2021 | M47: ='Cashflow per quarter'!J20 -> 0
C48: 9. Own services | I48: =START!$C$14 -> 2021 | M48: =SUM(M44:M47) -> 3013333.3
C49: 10. Additionally Needed Assets | G49: =G46-G48 -> 3640000 | I49: =" Quarter 1 "&START!$C$14+1 -> Quarter 1 2022 | M49: ='Cashflow per quarter'!M20 -> 0
I50: =" Quarter 2 "&START!$C$14+1 -> Quarter 2 2022 | M50: ='Cashflow per quarter'!N20 -> 0
C51: Planning periods in years | D51: ='EBITDA-Tracking'!M8 -> #REF! | I51: =" Quarter 3 "&START!$C$14+1 -> Quarter 3 2022 | M51: ='Cashflow per quarter'!O20 -> 0
C52: Depreciation in years: | D52: =+'INVESTMENT per Year'!O21 -> 3.5 | I52: =" Quarter 4 "&START!$C$14+1 -> Quarter 4 2022 | M52: ='Cashflow per quarter'!P20 -> 0
I53: =START!$C$14+1 -> 2022 | M53: =SUM(M49:M52) -> 0
I54: =" >= "&START!$C$14+1 -> >= 2022 | M54: =SUM('INVESTMENT per Year'!J21:M21) -> 0
I55: Total Cash Out | M55: =M54+M53+M48 -> 3013333.3
C57: to be filled | E57: Postcalculation on Payback / Benfits needed
C58: by Holding | E58: Date of postcalculation
C60: Level | D60: Group | E60: User | G60: Date | I60: Signature | K60: Comment
C61: Submitted by
C62: PC | D62: Controlling
C63: PC | D63: General Manager
C64: Division | D64: Finance Director
C65: Division | D65: Managing Director
C66: Holding | D66: CFO/CEO

Sheet INF_PrevYearEUR
C2: Quicklink | J2: ACT Rep - unconsolidated P&L All Depots
J3: 2018-12 YTD | Actual | 190 HR Ens | in 1.000 | unconsolidated
C5: Menu | J5: Status: Approved by Div
C8: Profit Center | M8: 2018-12 YTD | O8: 2018-12 YTD | Q8: Dev. | S8: Total excl. Coll. | U8: 1901 HR Ens | W8: Dev. | Y8: 190100 Sveta Helena | AA8: Dev. | AC8: 190101 Split | AE8: Dev. | AG8: 190102 Osijek | AI8: Dev. | AK8: 190103 Zagreb | AM8: Dev.
M9: Actual | O9: Actual | Q9: in % | S9: Actual | U9: Actual | W9: in % | Y9: Actual | AA9: in % | AC9: Actual | AE9: in % | AG9: Actual | AI9: in % | AK9: Actual | AM9: in %
C10: Year | J10: Acc | K10: Name | M10: in 1.000 EUR | O10: in 1.000 EUR | S10: in 1.000 EUR | U10: in 1.000 EUR | Y10: in 1.000 EUR | AC10: in 1.000 EUR | AG10: in 1.000 EUR | AK10: in 1.000 EUR
J11: M105 | K11: Sales (gross) - Core Business ext.
C12: Month | J12: M106 | K12: Sales (gross) - Core Business affil.
J13: M109 | K13: Total Sales (gross) - Core Business
C14: Currency | J14: M115 | K14: Customer Bonus
J15: M116 | K15: Customer Bonus affil.
C16: Scaling | J16: M120 | K16: Claims
J17: M121 | K17: Claims affil.
J18: M125 | K18: Discount
C19: Comp Column 1 | J19: M126 | K19: Discount affil.
J20: M130 | K20: Freight refund
J21: M131 | K21: Freight refund affil.
J22: M139 | K22: Reduction in Sales - Core Business
J23: M145 | K23: Revenues from trade goods ext.
J24: M146 | K24: Revenues from trade goods affil.
J25: M149 | K25: Sales from trade goods (net)
J26: M155 | K26: Other Sales (net) ext.
J27: M156 | K27: Other Sales (net) affil.
J28: M159 | K28: Other Sales (net)
J29: M179 | K29: TOTAL SALES (net)
J30: M189 | K30: Change in inventory
J31: M199 | K31: OPERATING INCOME
... J143: S | K143: Secondary costs
K144: NET INCOME After Allocation
J146: All Business Types
J147: Papers
J148: Plastics
J149: Refuse Derived Fuels
J150: Metals
J151: Glass
J152: Wood
J153: Final Goods
J154: Compound
J155: Waste
J156: Collection
J157: Papers
... J326: EBT % Net revenue

Sheet Calc_INF_PrevYearEUR
B2: =INF_PrevYearEUR!J2 -> ACT Rep - unconsolidated P&L All Depots
B3: =INF_PrevYearEUR!J3 -> 2018-12 YTD | Actual | 190 HR Ens | in 1.000 | unconsolidated
B5: =INF_PrevYearEUR!J5 -> Status: Approved by Div | E5: =E8 -> 2018-12 YTD | F5: =F8 -> 0 | G5: =G8 -> 2018-12 YTD | H5: =H8 -> 0 | I5: =I8 -> Dev. | J5: =J8 -> 0 | K5: =K8 -> Total excl. Coll. | L5: =L8 -> 0 | ... BQ5: =BQ8 -> 0
E6: =IF(E5=0,"",COLUMN()) -> 5 | F6: =IF(F5=0,"",COLUMN()) | G6: =IF(G5=0,"",COLUMN()) -> 7 | H6: =IF(H5=0,"",COLUMN()) | I6: =IF(I5=0,"",COLUMN()) -> 9 | J6: =IF(J5=0,"",COLUMN()) | K6: =IF(K5=0,"",COLUMN()) -> 11 | L6: =IF(L5=0,"",COLUMN()) | ... BQ6: =IF(BQ5=0,"",COLUMN())
B8: =INF_PrevYearEUR!J8 -> 0 | C8: =INF_PrevYearEUR!K8 -> 0 | D8: =INF_PrevYearEUR!L8 -> 0 | E8: =INF_PrevYearEUR!M8 -> 2018-12 YTD | F8: =INF_PrevYearEUR!N8 -> 0 | G8: =INF_PrevYearEUR!O8 -> 2018-12 YTD | H8: =INF_PrevYearEUR!P8 -> 0 | I8: =INF_PrevYearEUR!Q8 -> Dev. | ... BQ8: =INF_PrevYearEUR!BY8 -> 0
B9: =INF_PrevYearEUR!J9 -> 0 | C9: =INF_PrevYearEUR!K9 -> 0 | D9: =INF_PrevYearEUR!L9 -> 0 | E9: =INF_PrevYearEUR!M9 -> Actual | F9: =INF_PrevYearEUR!N9 -> 0 | G9: =INF_PrevYearEUR!O9 -> Actual | H9: =INF_PrevYearEUR!P9 -> 0 | I9: =INF_PrevYearEUR!Q9 -> in % | ... BQ9: =INF_PrevYearEUR!BY9 -> 0
A10: Acc | B10: =INF_PrevYearEUR!J10 -> Acc | C10: =INF_PrevYearEUR!K10 -> Name | D10: =INF_PrevYearEUR!L10 -> 0 | E10: =INF_PrevYearEUR!M10 -> in 1.000 EUR | F10: =INF_PrevYearEUR!N10 -> 0 | G10: =INF_PrevYearEUR!O10 -> in 1.000 EUR | H10: =INF_PrevYearEUR!P10 -> 0 | I10: =INF_PrevYearEUR!Q10 -> 0 | ... BQ10: =INF_PrevYearEUR!BY10 -> 0
A11: =IF(OR(B11=0,B11=""),"",B11&IF(COUNTIF(B11:$B$11,B11)>1,COUNTIF(B11:$B$11,B11),"")) -> M105 | B11: =INF_PrevYearEUR!J11 -> M105 | C11: =INF_PrevYearEUR!K11 -> Sales (gross) - Core Business ext. | D11: =INF_PrevYearEUR!L11 -> 0 | E11: =INF_PrevYearEUR!M11 -> 0 | F11: =INF_PrevYearEUR!N11 -> 0 | G11: =INF_PrevYearEUR!O11 -> 0 | H11: =INF_PrevYearEUR!P11 -> 0 | I11: =INF_PrevYearEUR!Q11 -> 0 | ... BQ11: =INF_PrevYearEUR!BY11 -> 0
A12: =IF(OR(B12=0,B12=""),"",B12&IF(COUNTIF(B$11:$B12,B12)>1,COUNTIF(B$11:$B12,B12),"")) -> M106 | B12: =INF_PrevYearEUR!J12 -> M106 | C12: =INF_PrevYearEUR!K12 -> Sales (gross) - Core Business affil. | D12: =INF_PrevYearEUR!L12 -> 0 | E12: =INF_PrevYearEUR!M12 -> 0 | F12: =INF_PrevYearEUR!N12 -> 0 | G12: =INF_PrevYearEUR!O12 -> 0 | H12: =INF_PrevYearEUR!P12 -> 0 | I12: =INF_PrevYearEUR!Q12 -> 0 | ... BQ12: =INF_PrevYearEUR!BY12 -> 0
A13: =IF(OR(B13=0,B13=""),"",B13&IF(COUNTIF(B$11:$B13,B13)>1,COUNTIF(B$11:$B13,B13),"")) -> M109 | B13: =INF_PrevYearEUR!J13 -> M109 | C13: =INF_PrevYearEUR!K13 -> Total Sales (gross) - Core Business | D13: =INF_PrevYearEUR!L13 -> 0 | E13: =INF_PrevYearEUR!M13 -> 0 | F13: =INF_PrevYearEUR!N13 -> 0 | G13: =INF_PrevYearEUR!O13 -> 0 | H13: =INF_PrevYearEUR!P13 -> 0 | I13: =INF_PrevYearEUR!Q13 -> 0 | ... BQ13: =INF_PrevYearEUR!BY13 -> 0
A14: =IF(OR(B14=0,B14=""),"",B14&IF(COUNTIF(B$11:$B14,B14)>1,COUNTIF(B$11:$B14,B14),"")) -> M115 | B14: =INF_PrevYearEUR!J14 -> M115 | C14: =INF_PrevYearEUR!K14 -> Customer Bonus | D14: =INF_PrevYearEUR!L14 -> 0 | E14: =INF_PrevYearEUR!M14 -> 0 | F14: =INF_PrevYearEUR!N14 -> 0 | G14: =INF_PrevYearEUR!O14 -> 0 | H14: =INF_PrevYearEUR!P14 -> 0 | I14: =INF_PrevYearEUR!Q14 -> 0 | ... BQ14: =INF_PrevYearEUR!BY14 -> 0
A15: =IF(OR(B15=0,B15=""),"",B15&IF(COUNTIF(B$11:$B15,B15)>1,COUNTIF(B$11:$B15,B15),"")) -> M116 | B15: =INF_PrevYearEUR!J15 -> M116 | C15: =INF_PrevYearEUR!K15 -> Customer Bonus affil. | D15: =INF_PrevYearEUR!L15 -> 0 | E15: =INF_PrevYearEUR!M15 -> 0 | F15: =INF_PrevYearEUR!N15 -> 0 | G15: =INF_PrevYearEUR!O15 -> 0 | H15: =INF_PrevYearEUR!P15 -> 0 | I15: =INF_PrevYearEUR!Q15 -> 0 | ... BQ15: =INF_PrevYearEUR!BY15 -> 0
A16: =IF(OR(B16=0,B16=""),"",B16&IF(COUNTIF(B$11:$B16,B16)>1,COUNTIF(B$11:$B16,B16),"")) -> M120 | B16: =INF_PrevYearEUR!J16 -> M120 | C16: =INF_PrevYearEUR!K16 -> Claims | D16: =INF_PrevYearEUR!L16 -> 0 | E16: =INF_PrevYearEUR!M16 -> 0 | F16: =INF_PrevYearEUR!N16 -> 0 | G16: =INF_PrevYearEUR!O16 -> 0 | H16: =INF_PrevYearEUR!P16 -> 0 | I16: =INF_PrevYearEUR!Q16 -> 0 | ... BQ16: =INF_PrevYearEUR!BY16 -> 0
A17: =IF(OR(B17=0,B17=""),"",B17&IF(COUNTIF(B$11:$B17,B17)>1,COUNTIF(B$11:$B17,B17),"")) -> M121 | B17: =INF_PrevYearEUR!J17 -> M121 | C17: =INF_PrevYearEUR!K17 -> Claims affil. | D17: =INF_PrevYearEUR!L17 -> 0 | E17: =INF_PrevYearEUR!M17 -> 0 | F17: =INF_PrevYearEUR!N17 -> 0 | G17: =INF_PrevYearEUR!O17 -> 0 | H17: =INF_PrevYearEUR!P17 -> 0 | I17: =INF_PrevYearEUR!Q17 -> 0 | ... BQ17: =INF_PrevYearEUR!BY17 -> 0
A18: =IF(OR(B18=0,B18=""),"",B18&IF(COUNTIF(B$11:$B18,B18)>1,COUNTIF(B$11:$B18,B18),"")) -> M125 | B18: =INF_PrevYearEUR!J18 -> M125 | C18: =INF_PrevYearEUR!K18 -> Discount | D18: =INF_PrevYearEUR!L18 -> 0 | E18: =INF_PrevYearEUR!M18 -> 0 | F18: =INF_PrevYearEUR!N18 -> 0 | G18: =INF_PrevYearEUR!O18 -> 0 | H18: =INF_PrevYearEUR!P18 -> 0 | I18: =INF_PrevYearEUR!Q18 -> 0 | ... BQ18: =INF_PrevYearEUR!BY18 -> 0
A19: =IF(OR(B19=0,B19=""),"",B19&IF(COUNTIF(B$11:$B19,B19)>1,COUNTIF(B$11:$B19,B19),"")) -> M126 | B19: =INF_PrevYearEUR!J19 -> M126 | C19: =INF_PrevYearEUR!K19 -> Discount affil. | D19: =INF_PrevYearEUR!L19 -> 0 | E19: =INF_PrevYearEUR!M19 -> 0 | F19: =INF_PrevYearEUR!N19 -> 0 | G19: =INF_PrevYearEUR!O19 -> 0 | H19: =INF_PrevYearEUR!P19 -> 0 | I19: =INF_PrevYearEUR!Q19 -> 0 | ... BQ19: =INF_PrevYearEUR!BY19 -> 0
A20: =IF(OR(B20=0,B20=""),"",B20&IF(COUNTIF(B$11:$B20,B20)>1,COUNTIF(B$11:$B20,B20),"")) -> M130 | B20: =INF_PrevYearEUR!J20 -> M130 | C20: =INF_PrevYearEUR!K20 -> Freight refund | D20: =INF_PrevYearEUR!L20 -> 0 | E20: =INF_PrevYearEUR!M20 -> 0 | F20: =INF_PrevYearEUR!N20 -> 0 | G20: =INF_PrevYearEUR!O20 -> 0 | H20: =INF_PrevYearEUR!P20 -> 0 | I20: =INF_PrevYearEUR!Q20 -> 0 | ... BQ20: =INF_PrevYearEUR!BY20 -> 0
A21: =IF(OR(B21=0,B21=""),"",B21&IF(COUNTIF(B$11:$B21,B21)>1,COUNTIF(B$11:$B21,B21),"")) -> M131 | B21: =INF_PrevYearEUR!J21 -> M131 | C21: =INF_PrevYearEUR!K21 -> Freight refund affil. | D21: =INF_PrevYearEUR!L21 -> 0 | E21: =INF_PrevYearEUR!M21 -> 0 | F21: =INF_PrevYearEUR!N21 -> 0 | G21: =INF_PrevYearEUR!O21 -> 0 | H21: =INF_PrevYearEUR!P21 -> 0 | I21: =INF_PrevYearEUR!Q21 -> 0 | ... BQ21: =INF_PrevYearEUR!BY21 -> 0
A22: =IF(OR(B22=0,B22=""),"",B22&IF(COUNTIF(B$11:$B22,B22)>1,COUNTIF(B$11:$B22,B22),"")) -> M139 | B22: =INF_PrevYearEUR!J22 -> M139 | C22: =INF_PrevYearEUR!K22 -> Reduction in Sales - Core Business | D22: =INF_PrevYearEUR!L22 -> 0 | E22: =INF_PrevYearEUR!M22 -> 0 | F22: =INF_PrevYearEUR!N22 -> 0 | G22: =INF_PrevYearEUR!O22 -> 0 | H22: =INF_PrevYearEUR!P22 -> 0 | I22: =INF_PrevYearEUR!Q22 -> 0 | ... BQ22: =INF_PrevYearEUR!BY22 -> 0
A23: =IF(OR(B23=0,B23=""),"",B23&IF(COUNTIF(B$11:$B23,B23)>1,COUNTIF(B$11:$B23,B23),"")) -> M145 | B23: =INF_PrevYearEUR!J23 -> M145 | C23: =INF_PrevYearEUR!K23 -> Revenues from trade goods ext. | D23: =INF_PrevYearEUR!L23 -> 0 | E23: =INF_PrevYearEUR!M23 -> 0 | F23: =INF_PrevYearEUR!N23 -> 0 | G23: =INF_PrevYearEUR!O23 -> 0 | H23: =INF_PrevYearEUR!P23 -> 0 | I23: =INF_PrevYearEUR!Q23 -> 0 | ... BQ23: =INF_PrevYearEUR!BY23 -> 0
... A143: =IF(OR(B143=0,B143=""),"",B143&IF(COUNTIF(B$11:$B143,B143)>1,COUNTIF(B$11:$B143,B143),"")) -> S | B143: =INF_PrevYearEUR!J143 -> S | C143: =INF_PrevYearEUR!K143 -> Secondary costs | D143: =INF_PrevYearEUR!L143 -> 0 | E143: =INF_PrevYearEUR!M143 -> 0 | F143: =INF_PrevYearEUR!N143 -> 0 | G143: =INF_PrevYearEUR!O143 -> 0 | H143: =INF_PrevYearEUR!P143 -> 0 | I143: =INF_PrevYearEUR!Q143 -> 0 | ... BQ143: =INF_PrevYearEUR!BY143 -> 0
A144: =IF(OR(B144=0,B144=""),"",B144&IF(COUNTIF(B$11:$B144,B144)>1,COUNTIF(B$11:$B144,B144),"")) | B144: =INF_PrevYearEUR!J145 -> 0 | D144: =INF_PrevYearEUR!L145 -> 0 | E144: =INF_PrevYearEUR!M145 -> 0 | F144: =INF_PrevYearEUR!N145 -> 0 | G144: =INF_PrevYearEUR!O145 -> 0 | H144: =INF_PrevYearEUR!P145 -> 0 | I144: =INF_PrevYearEUR!Q145 -> 0 | J144: =INF_PrevYearEUR!R145 -> 0 | K144: =INF_PrevYearEUR!S145 -> 0 | ... BQ144: =INF_PrevYearEUR!BY145 -> 0
A145: =IF(OR(B145=0,B145=""),"",B145&IF(COUNTIF(B$11:$B145,B145)>1,COUNTIF(B$11:$B145,B145),"")) -> All Business Types | B145: =INF_PrevYearEUR!J146 -> All Business Types | D145: =INF_PrevYearEUR!L146 -> 0 | E145: =INF_PrevYearEUR!M146 -> 0 | F145: =INF_PrevYearEUR!N146 -> 0 | G145: =INF_PrevYearEUR!O146 -> 0 | H145: =INF_PrevYearEUR!P146 -> 0 | I145: =INF_PrevYearEUR!Q146 -> 0 | J145: =INF_PrevYearEUR!R146 -> 0 | K145: =INF_PrevYearEUR!S146 -> 0 | ... BQ145: =INF_PrevYearEUR!BY146 -> 0
A146: =IF(OR(B146=0,B146=""),"",B146&IF(COUNTIF(B$11:$B146,B146)>1,COUNTIF(B$11:$B146,B146),"")) -> Papers | B146: =INF_PrevYearEUR!J147 -> Papers | D146: =INF_PrevYearEUR!L147 -> 0 | E146: =INF_PrevYearEUR!M147 -> 0 | F146: =INF_PrevYearEUR!N147 -> 0 | G146: =INF_PrevYearEUR!O147 -> 0 | H146: =INF_PrevYearEUR!P147 -> 0 | I146: =INF_PrevYearEUR!Q147 -> 0 | J146: =INF_PrevYearEUR!R147 -> 0 | K146: =INF_PrevYearEUR!S147 -> 0 | ... BQ146: =INF_PrevYearEUR!BY147 -> 0
A147: =IF(OR(B147=0,B147=""),"",B147&IF(COUNTIF(B$11:$B147,B147)>1,COUNTIF(B$11:$B147,B147),"")) -> Plastics | B147: =INF_PrevYearEUR!J148 -> Plastics | D147: =INF_PrevYearEUR!L148 -> 0 | E147: =INF_PrevYearEUR!M148 -> 0 | F147: =INF_PrevYearEUR!N148 -> 0 | G147: =INF_PrevYearEUR!O148 -> 0 | H147: =INF_PrevYearEUR!P148 -> 0 | I147: =INF_PrevYearEUR!Q148 -> 0 | J147: =INF_PrevYearEUR!R148 -> 0 | K147: =INF_PrevYearEUR!S148 -> 0 | ... BQ147: =INF_PrevYearEUR!BY148 -> 0
A148: =IF(OR(B148=0,B148=""),"",B148&IF(COUNTIF(B$11:$B148,B148)>1,COUNTIF(B$11:$B148,B148),"")) -> Refuse Derived Fuels | B148: =INF_PrevYearEUR!J149 -> Refuse Derived Fuels | D148: =INF_PrevYearEUR!L149 -> 0 | E148: =INF_PrevYearEUR!M149 -> 0 | F148: =INF_PrevYearEUR!N149 -> 0 | G148: =INF_PrevYearEUR!O149 -> 0 | H148: =INF_PrevYearEUR!P149 -> 0 | I148: =INF_PrevYearEUR!Q149 -> 0 | J148: =INF_PrevYearEUR!R149 -> 0 | K148: =INF_PrevYearEUR!S149 -> 0 | ... BQ148: =INF_PrevYearEUR!BY149 -> 0
A149: =IF(OR(B149=0,B149=""),"",B149&IF(COUNTIF(B$11:$B149,B149)>1,COUNTIF(B$11:$B149,B149),"")) -> Metals | B149: =INF_PrevYearEUR!J150 -> Metals | D149: =INF_PrevYearEUR!L150 -> 0 | E149: =INF_PrevYearEUR!M150 -> 0 | F149: =INF_PrevYearEUR!N150 -> 0 | G149: =INF_PrevYearEUR!O150 -> 0 | H149: =INF_PrevYearEUR!P150 -> 0 | I149: =INF_PrevYearEUR!Q150 -> 0 | J149: =INF_PrevYearEUR!R150 -> 0 | K149: =INF_PrevYearEUR!S150 -> 0 | ... BQ149: =INF_PrevYearEUR!BY150 -> 0
A150: =IF(OR(B150=0,B150=""),"",B150&IF(COUNTIF(B$11:$B150,B150)>1,COUNTIF(B$11:$B150,B150),"")) -> Glass | B150: =INF_PrevYearEUR!J151 -> Glass | D150: =INF_PrevYearEUR!L151 -> 0 | E150: =INF_PrevYearEUR!M151 -> 0 | F150: =INF_PrevYearEUR!N151 -> 0 | G150: =INF_PrevYearEUR!O151 -> 0 | H150: =INF_PrevYearEUR!P151 -> 0 | I150: =INF_PrevYearEUR!Q151 -> 0 | J150: =INF_PrevYearEUR!R151 -> 0 | K150: =INF_PrevYearEUR!S151 -> 0 | ... BQ150: =INF_PrevYearEUR!BY151 -> 0
A151: =IF(OR(B151=0,B151=""),"",B151&IF(COUNTIF(B$11:$B151,B151)>1,COUNTIF(B$11:$B151,B151),"")) -> Wood | B151: =INF_PrevYearEUR!J152 -> Wood | D151: =INF_PrevYearEUR!L152 -> 0 | E151: =INF_PrevYearEUR!M152 -> 0 | F151: =INF_PrevYearEUR!N152 -> 0 | G151: =INF_PrevYearEUR!O152 -> 0 | H151: =INF_PrevYearEUR!P152 -> 0 | I151: =INF_PrevYearEUR!Q152 -> 0 | J151: =INF_PrevYearEUR!R152 -> 0 | K151: =INF_PrevYearEUR!S152 -> 0 | ... BQ151: =INF_PrevYearEUR!BY152 -> 0
A152: =IF(OR(B152=0,B152=""),"",B152&IF(COUNTIF(B$11:$B152,B152)>1,COUNTIF(B$11:$B152,B152),"")) -> Final Goods | B152: =INF_PrevYearEUR!J153 -> Final Goods | D152: =INF_PrevYearEUR!L153 -> 0 | E152: =INF_PrevYearEUR!M153 -> 0 | F152: =INF_PrevYearEUR!N153 -> 0 | G152: =INF_PrevYearEUR!O153 -> 0 | H152: =INF_PrevYearEUR!P153 -> 0 | I152: =INF_PrevYearEUR!Q153 -> 0 | J152: =INF_PrevYearEUR!R153 -> 0 | K152: =INF_PrevYearEUR!S153 -> 0 | ... BQ152: =INF_PrevYearEUR!BY153 -> 0
A153: =IF(OR(B153=0,B153=""),"",B153&IF(COUNTIF(B$11:$B153,B153)>1,COUNTIF(B$11:$B153,B153),"")) -> Compound | B153: =INF_PrevYearEUR!J154 -> Compound | D153: =INF_PrevYearEUR!L154 -> 0 | E153: =INF_PrevYearEUR!M154 -> 0 | F153: =INF_PrevYearEUR!N154 -> 0 | G153: =INF_PrevYearEUR!O154 -> 0 | H153: =INF_PrevYearEUR!P154 -> 0 | I153: =INF_PrevYearEUR!Q154 -> 0 | J153: =INF_PrevYearEUR!R154 -> 0 | K153: =INF_PrevYearEUR!S154 -> 0 | ... BQ153: =INF_PrevYearEUR!BY154 -> 0
A154: =IF(OR(B154=0,B154=""),"",B154&IF(COUNTIF(B$11:$B154,B154)>1,COUNTIF(B$11:$B154,B154),"")) -> Waste | B154: =INF_PrevYearEUR!J155 -> Waste | D154: =INF_PrevYearEUR!L155 -> 0 | E154: =INF_PrevYearEUR!M155 -> 0 | F154: =INF_PrevYearEUR!N155 -> 0 | G154: =INF_PrevYearEUR!O155 -> 0 | H154: =INF_PrevYearEUR!P155 -> 0 | I154: =INF_PrevYearEUR!Q155 -> 0 | J154: =INF_PrevYearEUR!R155 -> 0 | K154: =INF_PrevYearEUR!S155 -> 0 | ... BQ154: =INF_PrevYearEUR!BY155 -> 0
A155: =IF(OR(B155=0,B155=""),"",B155&IF(COUNTIF(B$11:$B155,B155)>1,COUNTIF(B$11:$B155,B155),"")) -> Collection | B155: =INF_PrevYearEUR!J156 -> Collection | D155: =INF_PrevYearEUR!L156 -> 0 | E155: =INF_PrevYearEUR!M156 -> 0 | F155: =INF_PrevYearEUR!N156 -> 0 | G155: =INF_PrevYearEUR!O156 -> 0 | H155: =INF_PrevYearEUR!P156 -> 0 | I155: =INF_PrevYearEUR!Q156 -> 0 | J155: =INF_PrevYearEUR!R156 -> 0 | K155: =INF_PrevYearEUR!S156 -> 0 | ... BQ155: =INF_PrevYearEUR!BY156 -> 0
... A330: =IF(OR(B330=0,B330=""),"",B330&IF(COUNTIF(B$11:$B330,B330)>1,COUNTIF(B$11:$B330,B330),"")) | B330: =INF_PrevYearEUR!J331 -> 0 | D330: =INF_PrevYearEUR!L331 -> 0 | E330: =INF_PrevYearEUR!M331 -> 0 | F330: =INF_PrevYearEUR!N331 -> 0 | G330: =INF_PrevYearEUR!O331 -> 0 | H330: =INF_PrevYearEUR!P331 -> 0 | I330: =INF_PrevYearEUR!Q331 -> 0 | J330: =INF_PrevYearEUR!R331 -> 0 | K330: =INF_PrevYearEUR!S331 -> 0 | ... BQ330: =INF_PrevYearEUR!BY331 -> 0

Sheet INF_FC_EUR
C2: Quicklink | J2: FC Rep - unconsolidated P&L All Depots
J3: FC 2019-03 | 190 HR Ens | in 1.000
C5: Menu | J5: Status: Finished
C8: Profit Center | M8: 2013-12 YTD | O8: 2019-12 YTD | Q8: Dev. | S8: Total excl. Coll. | U8: 1901 HR Ens | W8: Dev. | Y8: 190100 Sveta Helena | AA8: Dev. | AC8: 190101 Split | AE8: Dev. | AG8: 190102 Osijek | AI8: Dev. | AK8: 190103 Zagreb | AM8: Dev.
M9: Actual | O9: FC 2019-01 | Q9: in % | S9: FC 2019-01 | U9: FC 2019-01 | W9: in % | Y9: FC 2019-01 | AA9: in % | AC9: FC 2019-01 | AE9: in % | AG9: FC 2019-01 | AI9: in % | AK9: FC 2019-01 | AM9: in %
C10: Forecast Scenario (Planning) | J10: Acc | K10: Name | M10: in 1.000 EUR | O10: in 1.000 EUR | S10: in 1.000 EUR | U10: in 1.000 EUR | Y10: in 1.000 EUR | AC10: in 1.000 EUR | AG10: in 1.000 EUR | AK10: in 1.000 EUR
J11: M105 | K11: Sales (gross) - Core Business ext.
C12: MTP-Year | J12: M106 | K12: Sales (gross) - Core Business affil.
J13: M109 | K13: Total Sales (gross) - Core Business
C14: Currency | J14: M115 | K14: Customer Bonus
J15: M116 | K15: Customer Bonus affil.
C16: Scaling | J16: M120 | K16: Claims
J17: M121 | K17: Claims affil.
J18: M125 | K18: Discount
C19: Comp Column 1 | J19: M126 | K19: Discount affil.
J20: M130 | K20: Freight refund
J21: M131 | K21: Freight refund affil.
J22: M139 | K22: Reduction in Sales - Core Business
J23: M145 | K23: Revenues from trade goods ext.
J24: M146 | K24: Revenues from trade goods affil.
J25: M149 | K25: Sales from trade goods (net)
J26: M155 | K26: Other Sales (net) ext.
J27: M156 | K27: Other Sales (net) affil.
J28: M159 | K28: Other Sales (net)
J29: M179 | K29: TOTAL SALES (net)
J30: M189 | K30: Change in inventory
J31: M199 | K31: OPERATING INCOME
... J140: M999 | K140: NET INCOME
K142: Exchange Rate ....
J144: S | K144: Secondary costs
K145: NET INCOME After Allocation
J147: All Business Types
J148: Papers
J149: Plastics
J150: Refuse Derived Fuels
J151: Metals
J152: Glass
J153: Wood
J154: Final Goods
J155: Compound
J156: Waste
J157: Collection
J158: Papers
... J327: EBT % Net revenue

Sheet Calc_INF_FC_EUR
B2: =INF_FC_EUR!J2 -> FC Rep - unconsolidated P&L All Depots
B3: =INF_FC_EUR!J3 -> FC 2019-03 | 190 HR Ens | in 1.000
B5: =INF_FC_EUR!J5 -> Status: Finished | E5: =E8 -> 2013-12 YTD | F5: =F8 -> 0 | G5: =G8 -> 2019-12 YTD | H5: =H8 -> 0 | I5: =I8 -> Dev. | J5: =J8 -> 0 | K5: =K8 -> Total excl. Coll. | L5: =L8 -> 0 | ... BQ5: =BQ8 -> 0
E6: =IF(E5=0,"",COLUMN()) -> 5 | F6: =IF(F5=0,"",COLUMN()) | G6: =IF(G5=0,"",COLUMN()) -> 7 | H6: =IF(H5=0,"",COLUMN()) | I6: =IF(I5=0,"",COLUMN()) -> 9 | J6: =IF(J5=0,"",COLUMN()) | K6: =IF(K5=0,"",COLUMN()) -> 11 | L6: =IF(L5=0,"",COLUMN()) | ... BQ6: =IF(BQ5=0,"",COLUMN())
B8: =INF_FC_EUR!J8 -> 0 | C8: =INF_FC_EUR!K8 -> 0 | D8: =INF_FC_EUR!L8 -> 0 | E8: =INF_FC_EUR!M8 -> 2013-12 YTD | F8: =INF_FC_EUR!N8 -> 0 | G8: =INF_FC_EUR!O8 -> 2019-12 YTD | H8: =INF_FC_EUR!P8 -> 0 | I8: =INF_FC_EUR!Q8 -> Dev. | ... BQ8: =INF_FC_EUR!BY8 -> 0
B9: =INF_FC_EUR!J9 -> 0 | C9: =INF_FC_EUR!K9 -> 0 | D9: =INF_FC_EUR!L9 -> 0 | E9: =INF_FC_EUR!M9 -> Actual | F9: =INF_FC_EUR!N9 -> 0 | G9: =INF_FC_EUR!O9 -> FC 2019-01 | H9: =INF_FC_EUR!P9 -> 0 | I9: =INF_FC_EUR!Q9 -> in % | ... BQ9: =INF_FC_EUR!BY9 -> 0
A10: Acc | B10: =INF_FC_EUR!J10 -> Acc | C10: =INF_FC_EUR!K10 -> Name | D10: =INF_FC_EUR!L10 -> 0 | E10: =INF_FC_EUR!M10 -> in 1.000 EUR | F10: =INF_FC_EUR!N10 -> 0 | G10: =INF_FC_EUR!O10 -> in 1.000 EUR | H10: =INF_FC_EUR!P10 -> 0 | I10: =INF_FC_EUR!Q10 -> 0 | ... BQ10: =INF_FC_EUR!BY10 -> 0
A11: =IF(OR(B11=0,B11=""),"",B11&IF(COUNTIF(B11:$B$11,B11)>1,COUNTIF(B11:$B$11,B11),"")) -> M105 | B11: =INF_FC_EUR!J11 -> M105 | C11: =INF_FC_EUR!K11 -> Sales (gross) - Core Business ext. | D11: =INF_FC_EUR!L11 -> 0 | E11: =INF_FC_EUR!M11 -> 0 | F11: =INF_FC_EUR!N11 -> 0 | G11: =INF_FC_EUR!O11 -> 0 | H11: =INF_FC_EUR!P11 -> 0 | I11: =INF_FC_EUR!Q11 -> 0 | ... BQ11: =INF_FC_EUR!BY11 -> 0
A12: =IF(OR(B12=0,B12=""),"",B12&IF(COUNTIF(B$11:$B12,B12)>1,COUNTIF(B$11:$B12,B12),"")) -> M106 | B12: =INF_FC_EUR!J12 -> M106 | C12: =INF_FC_EUR!K12 -> Sales (gross) - Core Business affil. | D12: =INF_FC_EUR!L12 -> 0 | E12: =INF_FC_EUR!M12 -> 0 | F12: =INF_FC_EUR!N12 -> 0 | G12: =INF_FC_EUR!O12 -> 0 | H12: =INF_FC_EUR!P12 -> 0 | I12: =INF_FC_EUR!Q12 -> 0 | ... BQ12: =INF_FC_EUR!BY12 -> 0
A13: =IF(OR(B13=0,B13=""),"",B13&IF(COUNTIF(B$11:$B13,B13)>1,COUNTIF(B$11:$B13,B13),"")) -> M109 | B13: =INF_FC_EUR!J13 -> M109 | C13: =INF_FC_EUR!K13 -> Total Sales (gross) - Core Business | D13: =INF_FC_EUR!L13 -> 0 | E13: =INF_FC_EUR!M13 -> 0 | F13: =INF_FC_EUR!N13 -> 0 | G13: =INF_FC_EUR!O13 -> 0 | H13: =INF_FC_EUR!P13 -> 0 | I13: =INF_FC_EUR!Q13 -> 0 | ... BQ13: =INF_FC_EUR!BY13 -> 0
A14: =IF(OR(B14=0,B14=""),"",B14&IF(COUNTIF(B$11:$B14,B14)>1,COUNTIF(B$11:$B14,B14),"")) -> M115 | B14: =INF_FC_EUR!J14 -> M115 | C14: =INF_FC_EUR!K14 -> Customer Bonus | D14: =INF_FC_EUR!L14 -> 0 | E14: =INF_FC_EUR!M14 -> 0 | F14: =INF_FC_EUR!N14 -> 0 | G14: =INF_FC_EUR!O14 -> 0 | H14: =INF_FC_EUR!P14 -> 0 | I14: =INF_FC_EUR!Q14 -> 0 | ... BQ14: =INF_FC_EUR!BY14 -> 0
A15: =IF(OR(B15=0,B15=""),"",B15&IF(COUNTIF(B$11:$B15,B15)>1,COUNTIF(B$11:$B15,B15),"")) -> M116 | B15: =INF_FC_EUR!J15 -> M116 | C15: =INF_FC_EUR!K15 -> Customer Bonus affil. | D15: =INF_FC_EUR!L15 -> 0 | E15: =INF_FC_EUR!M15 -> 0 | F15: =INF_FC_EUR!N15 -> 0 | G15: =INF_FC_EUR!O15 -> 0 | H15: =INF_FC_EUR!P15 -> 0 | I15: =INF_FC_EUR!Q15 -> 0 | ... BQ15: =INF_FC_EUR!BY15 -> 0
A16: =IF(OR(B16=0,B16=""),"",B16&IF(COUNTIF(B$11:$B16,B16)>1,COUNTIF(B$11:$B16,B16),"")) -> M120 | B16: =INF_FC_EUR!J16 -> M120 | C16: =INF_FC_EUR!K16 -> Claims | D16: =INF_FC_EUR!L16 -> 0 | E16: =INF_FC_EUR!M16 -> 0 | F16: =INF_FC_EUR!N16 -> 0 | G16: =INF_FC_EUR!O16 -> 0 | H16: =INF_FC_EUR!P16 -> 0 | I16: =INF_FC_EUR!Q16 -> 0 | ... BQ16: =INF_FC_EUR!BY16 -> 0
A17: =IF(OR(B17=0,B17=""),"",B17&IF(COUNTIF(B$11:$B17,B17)>1,COUNTIF(B$11:$B17,B17),"")) -> M121 | B17: =INF_FC_EUR!J17 -> M121 | C17: =INF_FC_EUR!K17 -> Claims affil. | D17: =INF_FC_EUR!L17 -> 0 | E17: =INF_FC_EUR!M17 -> 0 | F17: =INF_FC_EUR!N17 -> 0 | G17: =INF_FC_EUR!O17 -> 0 | H17: =INF_FC_EUR!P17 -> 0 | I17: =INF_FC_EUR!Q17 -> 0 | ... BQ17: =INF_FC_EUR!BY17 -> 0
A18: =IF(OR(B18=0,B18=""),"",B18&IF(COUNTIF(B$11:$B18,B18)>1,COUNTIF(B$11:$B18,B18),"")) -> M125 | B18: =INF_FC_EUR!J18 -> M125 | C18: =INF_FC_EUR!K18 -> Discount | D18: =INF_FC_EUR!L18 -> 0 | E18: =INF_FC_EUR!M18 -> 0 | F18: =INF_FC_EUR!N18 -> 0 | G18: =INF_FC_EUR!O18 -> 0 | H18: =INF_FC_EUR!P18 -> 0 | I18: =INF_FC_EUR!Q18 -> 0 | ... BQ18: =INF_FC_EUR!BY18 -> 0
A19: =IF(OR(B19=0,B19=""),"",B19&IF(COUNTIF(B$11:$B19,B19)>1,COUNTIF(B$11:$B19,B19),"")) -> M126 | B19: =INF_FC_EUR!J19 -> M126 | C19: =INF_FC_EUR!K19 -> Discount affil. | D19: =INF_FC_EUR!L19 -> 0 | E19: =INF_FC_EUR!M19 -> 0 | F19: =INF_FC_EUR!N19 -> 0 | G19: =INF_FC_EUR!O19 -> 0 | H19: =INF_FC_EUR!P19 -> 0 | I19: =INF_FC_EUR!Q19 -> 0 | ... BQ19: =INF_FC_EUR!BY19 -> 0
A20: =IF(OR(B20=0,B20=""),"",B20&IF(COUNTIF(B$11:$B20,B20)>1,COUNTIF(B$11:$B20,B20),"")) -> M130 | B20: =INF_FC_EUR!J20 -> M130 | C20: =INF_FC_EUR!K20 -> Freight refund | D20: =INF_FC_EUR!L20 -> 0 | E20: =INF_FC_EUR!M20 -> 0 | F20: =INF_FC_EUR!N20 -> 0 | G20: =INF_FC_EUR!O20 -> 0 | H20: =INF_FC_EUR!P20 -> 0 | I20: =INF_FC_EUR!Q20 -> 0 | ... BQ20: =INF_FC_EUR!BY20 -> 0
A21: =IF(OR(B21=0,B21=""),"",B21&IF(COUNTIF(B$11:$B21,B21)>1,COUNTIF(B$11:$B21,B21),"")) -> M131 | B21: =INF_FC_EUR!J21 -> M131 | C21: =INF_FC_EUR!K21 -> Freight refund affil. | D21: =INF_FC_EUR!L21 -> 0 | E21: =INF_FC_EUR!M21 -> 0 | F21: =INF_FC_EUR!N21 -> 0 | G21: =INF_FC_EUR!O21 -> 0 | H21: =INF_FC_EUR!P21 -> 0 | I21: =INF_FC_EUR!Q21 -> 0 | ... BQ21: =INF_FC_EUR!BY21 -> 0
A22: =IF(OR(B22=0,B22=""),"",B22&IF(COUNTIF(B$11:$B22,B22)>1,COUNTIF(B$11:$B22,B22),"")) -> M139 | B22: =INF_FC_EUR!J22 -> M139 | C22: =INF_FC_EUR!K22 -> Reduction in Sales - Core Business | D22: =INF_FC_EUR!L22 -> 0 | E22: =INF_FC_EUR!M22 -> 0 | F22: =INF_FC_EUR!N22 -> 0 | G22: =INF_FC_EUR!O22 -> 0 | H22: =INF_FC_EUR!P22 -> 0 | I22: =INF_FC_EUR!Q22 -> 0 | ... BQ22: =INF_FC_EUR!BY22 -> 0
A23: =IF(OR(B23=0,B23=""),"",B23&IF(COUNTIF(B$11:$B23,B23)>1,COUNTIF(B$11:$B23,B23),"")) -> M145 | B23: =INF_FC_EUR!J23 -> M145 | C23: =INF_FC_EUR!K23 -> Revenues from trade goods ext. | D23: =INF_FC_EUR!L23 -> 0 | E23: =INF_FC_EUR!M23 -> 0 | F23: =INF_FC_EUR!N23 -> 0 | G23: =INF_FC_EUR!O23 -> 0 | H23: =INF_FC_EUR!P23 -> 0 | I23: =INF_FC_EUR!Q23 -> 0 | ... BQ23: =INF_FC_EUR!BY23 -> 0
... A140: =IF(OR(B140=0,B140=""),"",B140&IF(COUNTIF(B$11:$B140,B140)>1,COUNTIF(B$11:$B140,B140),"")) -> M999 | B140: =INF_FC_EUR!J140 -> M999 | C140: =INF_FC_EUR!K140 -> NET INCOME | D140: =INF_FC_EUR!L140 -> 0 | E140: =INF_FC_EUR!M140 -> 0 | F140: =INF_FC_EUR!N140 -> 0 | G140: =INF_FC_EUR!O140 -> 0 | H140: =INF_FC_EUR!P140 -> 0 | I140: =INF_FC_EUR!Q140 -> 0 | ... BQ140: =INF_FC_EUR!BY140 -> 0
A141: =IF(OR(B141=0,B141=""),"",B141&IF(COUNTIF(B$11:$B141,B141)>1,COUNTIF(B$11:$B141,B141),"")) | B141: =INF_FC_EUR!J142 -> 0 | C141: =INF_FC_EUR!K142 -> Exchange Rate .... | D141: =INF_FC_EUR!L142 -> 0 | E141: =INF_FC_EUR!M142 -> 0 | F141: =INF_FC_EUR!N142 -> 0 | G141: =INF_FC_EUR!O142 -> 0 | H141: =INF_FC_EUR!P142 -> 0 | I141: =INF_FC_EUR!Q142 -> 0 | ... BQ141: =INF_FC_EUR!BY142 -> 0
A142: =IF(OR(B142=0,B142=""),"",B142&IF(COUNTIF(B$11:$B142,B142)>1,COUNTIF(B$11:$B142,B142),"")) | B142: =INF_FC_EUR!J143 -> 0 | C142: =INF_FC_EUR!K143 -> 0 | D142: =INF_FC_EUR!L143 -> 0 | E142: =INF_FC_EUR!M143 -> 0 | F142: =INF_FC_EUR!N143 -> 0 | G142: =INF_FC_EUR!O143 -> 0 | H142: =INF_FC_EUR!P143 -> 0 | I142: =INF_FC_EUR!Q143 -> 0 | ... BQ142: =INF_FC_EUR!BY143 -> 0
A143: =IF(OR(B143=0,B143=""),"",B143&IF(COUNTIF(B$11:$B143,B143)>1,COUNTIF(B$11:$B143,B143),"")) -> S | B143: =INF_FC_EUR!J144 -> S | C143: =INF_FC_EUR!K144 -> Secondary costs | D143: =INF_FC_EUR!L144 -> 0 | E143: =INF_FC_EUR!M144 -> 0 | F143: =INF_FC_EUR!N144 -> 0 | G143: =INF_FC_EUR!O144 -> 0 | H143: =INF_FC_EUR!P144 -> 0 | I143: =INF_FC_EUR!Q144 -> 0 | ... BQ143: =INF_FC_EUR!BY144 -> 0
A144: =IF(OR(B144=0,B144=""),"",B144&IF(COUNTIF(B$11:$B144,B144)>1,COUNTIF(B$11:$B144,B144),"")) | B144: =INF_FC_EUR!J145 -> 0 | D144: =INF_FC_EUR!L145 -> 0 | E144: =INF_FC_EUR!M145 -> 0 | F144: =INF_FC_EUR!N145 -> 0 | G144: =INF_FC_EUR!O145 -> 0 | H144: =INF_FC_EUR!P145 -> 0 | I144: =INF_FC_EUR!Q145 -> 0 | J144: =INF_FC_EUR!R145 -> 0 | K144: =INF_FC_EUR!S145 -> 0 | ... BQ144: =INF_FC_EUR!BY145 -> 0
A145: =IF(OR(B145=0,B145=""),"",B145&IF(COUNTIF(B$11:$B145,B145)>1,COUNTIF(B$11:$B145,B145),"")) | B145: =INF_FC_EUR!J146 -> 0 | D145: =INF_FC_EUR!L146 -> 0 | E145: =INF_FC_EUR!M146 -> 0 | F145: =INF_FC_EUR!N146 -> 0 | G145: =INF_FC_EUR!O146 -> 0 | H145: =INF_FC_EUR!P146 -> 0 | I145: =INF_FC_EUR!Q146 -> 0 | J145: =INF_FC_EUR!R146 -> 0 | K145: =INF_FC_EUR!S146 -> 0 | ... BQ145: =INF_FC_EUR!BY146 -> 0
A146: =IF(OR(B146=0,B146=""),"",B146&IF(COUNTIF(B$11:$B146,B146)>1,COUNTIF(B$11:$B146,B146),"")) -> All Business Types | B146: =INF_FC_EUR!J147 -> All Business Types | D146: =INF_FC_EUR!L147 -> 0 | E146: =INF_FC_EUR!M147 -> 0 | F146: =INF_FC_EUR!N147 -> 0 | G146: =INF_FC_EUR!O147 -> 0 | H146: =INF_FC_EUR!P147 -> 0 | I146: =INF_FC_EUR!Q147 -> 0 | J146: =INF_FC_EUR!R147 -> 0 | K146: =INF_FC_EUR!S147 -> 0 | ... BQ146: =INF_FC_EUR!BY147 -> 0
A147: =IF(OR(B147=0,B147=""),"",B147&IF(COUNTIF(B$11:$B147,B147)>1,COUNTIF(B$11:$B147,B147),"")) -> Papers | B147: =INF_FC_EUR!J148 -> Papers | D147: =INF_FC_EUR!L148 -> 0 | E147: =INF_FC_EUR!M148 -> 0 | F147: =INF_FC_EUR!N148 -> 0 | G147: =INF_FC_EUR!O148 -> 0 | H147: =INF_FC_EUR!P148 -> 0 | I147: =INF_FC_EUR!Q148 -> 0 | J147: =INF_FC_EUR!R148 -> 0 | K147: =INF_FC_EUR!S148 -> 0 | ... BQ147: =INF_FC_EUR!BY148 -> 0
A148: =IF(OR(B148=0,B148=""),"",B148&IF(COUNTIF(B$11:$B148,B148)>1,COUNTIF(B$11:$B148,B148),"")) -> Plastics | B148: =INF_FC_EUR!J149 -> Plastics | D148: =INF_FC_EUR!L149 -> 0 | E148: =INF_FC_EUR!M149 -> 0 | F148: =INF_FC_EUR!N149 -> 0 | G148: =INF_FC_EUR!O149 -> 0 | H148: =INF_FC_EUR!P149 -> 0 | I148: =INF_FC_EUR!Q149 -> 0 | J148: =INF_FC_EUR!R149 -> 0 | K148: =INF_FC_EUR!S149 -> 0 | ... BQ148: =INF_FC_EUR!BY149 -> 0
A149: =IF(OR(B149=0,B149=""),"",B149&IF(COUNTIF(B$11:$B149,B149)>1,COUNTIF(B$11:$B149,B149),"")) -> Refuse Derived Fuels | B149: =INF_FC_EUR!J150 -> Refuse Derived Fuels | D149: =INF_FC_EUR!L150 -> 0 | E149: =INF_FC_EUR!M150 -> 0 | F149: =INF_FC_EUR!N150 -> 0 | G149: =INF_FC_EUR!O150 -> 0 | H149: =INF_FC_EUR!P150 -> 0 | I149: =INF_FC_EUR!Q150 -> 0 | J149: =INF_FC_EUR!R150 -> 0 | K149: =INF_FC_EUR!S150 -> 0 | ... BQ149: =INF_FC_EUR!BY150 -> 0
A150: =IF(OR(B150=0,B150=""),"",B150&IF(COUNTIF(B$11:$B150,B150)>1,COUNTIF(B$11:$B150,B150),"")) -> Metals | B150: =INF_FC_EUR!J151 -> Metals | D150: =INF_FC_EUR!L151 -> 0 | E150: =INF_FC_EUR!M151 -> 0 | F150: =INF_FC_EUR!N151 -> 0 | G150: =INF_FC_EUR!O151 -> 0 | H150: =INF_FC_EUR!P151 -> 0 | I150: =INF_FC_EUR!Q151 -> 0 | J150: =INF_FC_EUR!R151 -> 0 | K150: =INF_FC_EUR!S151 -> 0 | ... BQ150: =INF_FC_EUR!BY151 -> 0
A151: =IF(OR(B151=0,B151=""),"",B151&IF(COUNTIF(B$11:$B151,B151)>1,COUNTIF(B$11:$B151,B151),"")) -> Glass | B151: =INF_FC_EUR!J152 -> Glass | D151: =INF_FC_EUR!L152 -> 0 | E151: =INF_FC_EUR!M152 -> 0 | F151: =INF_FC_EUR!N152 -> 0 | G151: =INF_FC_EUR!O152 -> 0 | H151: =INF_FC_EUR!P152 -> 0 | I151: =INF_FC_EUR!Q152 -> 0 | J151: =INF_FC_EUR!R152 -> 0 | K151: =INF_FC_EUR!S152 -> 0 | ... BQ151: =INF_FC_EUR!BY152 -> 0
A152: =IF(OR(B152=0,B152=""),"",B152&IF(COUNTIF(B$11:$B152,B152)>1,COUNTIF(B$11:$B152,B152),"")) -> Wood | B152: =INF_FC_EUR!J153 -> Wood | D152: =INF_FC_EUR!L153 -> 0 | E152: =INF_FC_EUR!M153 -> 0 | F152: =INF_FC_EUR!N153 -> 0 | G152: =INF_FC_EUR!O153 -> 0 | H152: =INF_FC_EUR!P153 -> 0 | I152: =INF_FC_EUR!Q153 -> 0 | J152: =INF_FC_EUR!R153 -> 0 | K152: =INF_FC_EUR!S153 -> 0 | ... BQ152: =INF_FC_EUR!BY153 -> 0
A153: =IF(OR(B153=0,B153=""),"",B153&IF(COUNTIF(B$11:$B153,B153)>1,COUNTIF(B$11:$B153,B153),"")) -> Final Goods | B153: =INF_FC_EUR!J154 -> Final Goods | D153: =INF_FC_EUR!L154 -> 0 | E153: =INF_FC_EUR!M154 -> 0 | F153: =INF_FC_EUR!N154 -> 0 | G153: =INF_FC_EUR!O154 -> 0 | H153: =INF_FC_EUR!P154 -> 0 | I153: =INF_FC_EUR!Q154 -> 0 | J153: =INF_FC_EUR!R154 -> 0 | K153: =INF_FC_EUR!S154 -> 0 | ... BQ153: =INF_FC_EUR!BY154 -> 0
A154: =IF(OR(B154=0,B154=""),"",B154&IF(COUNTIF(B$11:$B154,B154)>1,COUNTIF(B$11:$B154,B154),"")) -> Compound | B154: =INF_FC_EUR!J155 -> Compound | D154: =INF_FC_EUR!L155 -> 0 | E154: =INF_FC_EUR!M155 -> 0 | F154: =INF_FC_EUR!N155 -> 0 | G154: =INF_FC_EUR!O155 -> 0 | H154: =INF_FC_EUR!P155 -> 0 | I154: =INF_FC_EUR!Q155 -> 0 | J154: =INF_FC_EUR!R155 -> 0 | K154: =INF_FC_EUR!S155 -> 0 | ... BQ154: =INF_FC_EUR!BY155 -> 0
A155: =IF(OR(B155=0,B155=""),"",B155&IF(COUNTIF(B$11:$B155,B155)>1,COUNTIF(B$11:$B155,B155),"")) -> Waste | B155: =INF_FC_EUR!J156 -> Waste | D155: =INF_FC_EUR!L156 -> 0 | E155: =INF_FC_EUR!M156 -> 0 | F155: =INF_FC_EUR!N156 -> 0 | G155: =INF_FC_EUR!O156 -> 0 | H155: =INF_FC_EUR!P156 -> 0 | I155: =INF_FC_EUR!Q156 -> 0 | J155: =INF_FC_EUR!R156 -> 0 | K155: =INF_FC_EUR!S156 -> 0 | ... BQ155: =INF_FC_EUR!BY156 -> 0
... A330: =IF(OR(B330=0,B330=""),"",B330&IF(COUNTIF(B$11:$B330,B330)>1,COUNTIF(B$11:$B330,B330),"")) | B330: =INF_FC_EUR!J331 -> 0 | D330: =INF_FC_EUR!L331 -> 0 | E330: =INF_FC_EUR!M331 -> 0 | F330: =INF_FC_EUR!N331 -> 0 | G330: =INF_FC_EUR!O331 -> 0 | H330: =INF_FC_EUR!P331 -> 0 | I330: =INF_FC_EUR!Q331 -> 0 | J330: =INF_FC_EUR!R331 -> 0 | K330: =INF_FC_EUR!S331 -> 0 | ... BQ330: =INF_FC_EUR!BY331 -> 0

Sheet BusPlanLocation
C6: =IF(START!$C$18="EUR",1,IF($C$9="EUR",1,START!$E$18)) -> 1
C7: =START!$C$10 -> 166101 Bornova | D7: Previous year | F7: Forecast | I7: Business Plan Periods
C8: Registration currency: | D8: =START!C14-1&"-12 YTD" -> 2020-12 YTD | F8: =START!C14&"-12 YTD" -> 2021-12 YTD | I8: =START!C14 -> 2021 | K8: =I8+1 -> 2022 | M8: =K8+1 -> 2023 | O8: =M8+1 -> 2024 | Q8: =O8+1 -> 2025 | S8: =Q8+1 -> 2026
C9: EUR | D9: Actual | F9: Actual | G9: Adaption | I9: Business Plan | K9: Business Plan | M9: Business Plan | O9: Business Plan | Q9: Business Plan | S9: Business Plan
B10: Acc | C10: Name | D10: ="in 1.000 "&$C$9 -> in 1.000 EUR | E10: % | F10: ="in 1.000 "&$C$9 -> in 1.000 EUR | G10: ="in 1.000 "&$C$9 -> in 1.000 EUR | H10: % | I10: ="in 1.000 "&$C$9 -> in 1.000 EUR | J10: % | K10: ="in 1.000 "&$C$9 -> in 1.000 EUR | L10: % | M10: ="in 1.000 "&$C$9 -> in 1.000 EUR | N10: % | O10: ="in 1.000 "&$C$9 -> in 1.000 EUR | P10: % | Q10: ="in 1.000 "&$C$9 -> in 1.000 EUR | R10: % | S10: ="in 1.000 "&$C$9 -> in 1.000 EUR | T10: %
A11: =AA11 -> M105 | B11: M105 | C11: Sales (gross) - Core Business ext. | D11: =VLOOKUP($AA11,Calc_INF_PrevYearEUR!$A$11:$BQ$330,HLOOKUP($C$7,Calc_INF_PrevYearEUR!$E$5:$BQ$6,2,0),0)*IF($C$9="EUR",1,START!$E$18) -> #N/A | E11: =IF(D11=0,0,D11/D$42) -> #N/A | F11: =IF(F13<>0,VLOOKUP($AA11,Calc_INF_FC_EUR!$A$11:$BQ$330,HLOOKUP($C$7,Calc_INF_FC_EUR!$E$5:$BQ$6,2,0),0)*IF($C$9="EUR",1,START!$E$18)+(VLOOKUP($AA11,Calc_INF_FC_EUR!$A$11:$BQ$330,HLOOKUP($C$7,Calc_INF_FC_EUR!$E$5:$BQ$6,2,0),0)*IF($C$9="EUR",1,START!$E$18))/F13*G13,0) -> #N/A | G11: =F11-VLOOKUP($AA11,Calc_INF_FC_EUR!$A$11:$BQ$330,HLOOKUP($C$7,Calc_INF_FC_EUR!$E$5:$BQ$6,2,0),0)*IF($C$9="EUR",1,START!$E$18) -> #N/A | I11: =SUMIFS(SalesReport!$R:$R,SalesReport!$AF:$AF,$AB11,SalesReport!$A:$A,I$8,SalesReport!$B:$B,BusPlanLocation!$C$7)*IF($C$9="EUR",1,START!$E$18)/1000 -> #REF! | J11: =IF(I11=0,0,I11/I$42) -> #REF! | K11: =SUMIFS(SalesReport!$R:$R,SalesReport!$AF:$AF,$AB11,SalesReport!$A:$A,K$8,SalesReport!$B:$B,BusPlanLocation!$C$7)*IF($C$9="EUR",1,START!$E$18)/1000 -> 0 | L11: =IF(K11=0,0,K11/K$42) -> 0 | M11: =SUMIFS(SalesReport!$R:$R,SalesReport!$AF:$AF,$AB11,SalesReport!$A:$A,M$8,SalesReport!$B:$B,BusPlanLocation!$C$7)*IF($C$9="EUR",1,START!$E$18)/1000 -> 0 | N11: =IF(M11=0,0,M11/M$42) -> 0 | O11: =SUMIFS(SalesReport!$R:$R,SalesReport!$AF:$AF,$AB11,SalesReport!$A:$A,O$8,SalesReport!$B:$B,BusPlanLocation!$C$7)*IF($C$9="EUR",1,START!$E$18)/1000 -> 0 | P11: =IF(O11=0,0,O11/O$42) -> 0 | Q11: =SUMIFS(SalesReport!$R:$R,SalesReport!$AF:$AF,$AB11,SalesReport!$A:$A,Q$8,SalesReport!$B:$B,BusPlanLocation!$C$7)*IF($C$9="EUR",1,START!$E$18)/1000 -> 0 | R11: =IF(Q11=0,0,Q11/Q$42) -> 0 | S11: =SUMIFS(SalesReport!$R:$R,SalesReport!$AF:$AF,$AB11,SalesReport!$A:$A,S$8,SalesReport!$B:$B,BusPlanLocation!$C$7)*IF($C$9="EUR",1,START!$E$18)/1000 -> 0 | T11: =IF(S11=0,0,S11/S$42) -> 0 | AA11: =IF(OR(B11=0,B11=""),"",B11&IF(COUNTIF(B$11:$B11,B11)>1,COUNTIF(B$11:$B11,B11),"")) -> M105 | AB11: Collectionext
A12: =AA12 -> M106 | B12: M106 | C12: Sales (gross) - Core Business affil. | D12: =VLOOKUP($AA12,Calc_INF_PrevYearEUR!$A$11:$BQ$330,HLOOKUP($C$7,Calc_INF_PrevYearEUR!$E$5:$BQ$6,2,0),0)*IF($C$9="EUR",1,START!$E$18) -> #N/A | E12: =IF(D12=0,0,D12/D$42) -> #N/A | F12: =IF(F13<>0,VLOOKUP($AA12,Calc_INF_FC_EUR!$A$11:$BQ$330,HLOOKUP($C$7,Calc_INF_FC_EUR!$E$5:$BQ$6,2,0),0)*IF($C$9="EUR",1,START!$E$18)+(VLOOKUP($AA12,Calc_INF_FC_EUR!$A$11:$BQ$330,HLOOKUP($C$7,Calc_INF_FC_EUR!$E$5:$BQ$6,2,0),0)*IF($C$9="EUR",1,START!$E$18))/F13*G13,0) -> #N/A | G12: =F12-VLOOKUP($AA12,Calc_INF_FC_EUR!$A$11:$BQ$330,HLOOKUP($C$7,Calc_INF_FC_EUR!$E$5:$BQ$6,2,0),0)*IF($C$9="EUR",1,START!$E$18) -> #N/A | I12: =SUMIFS(SalesReport!$R:$R,SalesReport!$AF:$AF,$AB12,SalesReport!$A:$A,I$8,SalesReport!$B:$B,BusPlanLocation!$C$7)*IF($C$9="EUR",1,START!$E$18)/1000 -> 0 | J12: =IF(I12=0,0,I12/I$42) -> 0 | K12: =SUMIFS(SalesReport!$R:$R,SalesReport!$AF:$AF,$AB12,SalesReport!$A:$A,K$8,SalesReport!$B:$B,BusPlanLocation!$C$7)*IF($C$9="EUR",1,START!$E$18)/1000 -> 0 | L12: =IF(K12=0,0,K12/K$42) -> 0 | M12: =SUMIFS(SalesReport!$R:$R,SalesReport!$AF:$AF,$AB12,SalesReport!$A:$A,M$8,SalesReport!$B:$B,BusPlanLocation!$C$7)*IF($C$9="EUR",1,START!$E$18)/1000 -> 0 | N12: =IF(M12=0,0,M12/M$42) -> 0 | O12: =SUMIFS(SalesReport!$R:$R,SalesReport!$AF:$AF,$AB12,SalesReport!$A:$A,O$8,SalesReport!$B:$B,BusPlanLocation!$C$7)*IF($C$9="EUR",1,START!$E$18)/1000 -> 0 | P12: =IF(O12=0,0,O12/O$42) -> 0 | Q12: =SUMIFS(SalesReport!$R:$R,SalesReport!$AF:$AF,$AB12,SalesReport!$A:$A,Q$8,SalesReport!$B:$B,BusPlanLocation!$C$7)*IF($C$9="EUR",1,START!$E$18)/1000 -> 0 | R12: =IF(Q12=0,0,Q12/Q$42) -> 0 | S12: =SUMIFS(SalesReport!$R:$R,SalesReport!$AF:$AF,$AB12,SalesReport!$A:$A,S$8,SalesReport!$B:$B,BusPlanLocation!$C$7)*IF($C$9="EUR",1,START!$E$18)/1000 -> 0 | T12: =IF(S12=0,0,S12/S$42) -> 0 | AA12: =IF(OR(B12=0,B12=""),"",B12&IF(COUNTIF(B$11:$B12,B12)>1,COUNTIF(B$11:$B12,B12),"")) -> M106 | AB12: Collectionaff
A13: =AA13 -> M109 | B13: M109 | C13: Total Sales (gross) - Core Business | D13: =VLOOKUP($AA13,Calc_INF_PrevYearEUR!$A$11:$BQ$330,HLOOKUP($C$7,Calc_INF_PrevYearEUR!$E$5:$BQ$6,2,0),0)*IF($C$9="EUR",1,START!$E$18) -> #N/A | E13: =IF(D13=0,0,D13/D$42) -> #N/A | F13: =VLOOKUP($AA13,Calc_INF_FC_EUR!$A$11:$BQ$330,HLOOKUP($C$7,Calc_INF_FC_EUR!$E$5:$BQ$6,2,0),0)*IF($C$9="EUR",1,START!$E$18)+G13 -> #N/A | G13: =IF(AND($G$155<>0,$G$232<>0),((VLOOKUP("Collection",Calc_INF_FC_EUR!$A$11:$BQ$330,HLOOKUP($C$7,Calc_INF_FC_EUR!$E$5:$BQ$6,2,0),0)*IF($C$9="EUR",1,START!$E$18)+$G$155)*(VLOOKUP($AA232,Calc_INF_FC_EUR!$A$11:$BQ$330,HLOOKUP($C$7,Calc_INF_FC_EUR!$E$5:$BQ$6,2,0),0)*IF($C$9="EUR",1,START!$E$18)+$G$232))/1000-VLOOKUP($AA13,Calc_INF_FC_EUR!$A$11:$BQ$330,HLOOKUP($C$7,Calc_INF_FC_EUR!$E$5:$BQ$6,2,0),0)*IF($C$9="EUR",1,START!$E$18),IF(OR($G$155<>0,$G$232<>0),(IF($G$155<>0,$G$155,VLOOKUP($AA155,Calc_INF_FC_EUR!$A$11:$BQ$330,HLOOKUP($C$7,Calc_INF_FC_EUR!$E$5:$BQ$6,2,0),0)*IF($C$9="EUR",1,START!$E$18))*IF($G$232<>0,$G$232,VLOOKUP($AA232,Calc_INF_FC_EUR!$A$11:$BQ$330,HLOOKUP($C$7,Calc_INF_FC_EUR!$E$5:$BQ$6,2,0),0)*IF($C$9="EUR",1,START!$E$18)))/1000,0)) -> 0 | I13: =I11+I12 -> #REF! | J13: =IF(I13=0,0,I13/I$42) -> #REF! | K13: =K11+K12 -> 0 | L13: =IF(K13=0,0,K13/K$42) -> 0 | M13: =M11+M12 -> 0 | N13: =IF(M13=0,0,M13/M$42) -> 0 | O13: =O11+O12 -> 0 | P13: =IF(O13=0,0,O13/O$42) -> 0 | Q13: =Q11+Q12 -> 0 | R13: =IF(Q13=0,0,Q13/Q$42) -> 0 | S13: =S11+S12 -> 0 | T13: =IF(S13=0,0,S13/S$42) -> 0 | AA13: =IF(OR(B13=0,B13=""),"",B13&IF(COUNTIF(B$11:$B13,B13)>1,COUNTIF(B$11:$B13,B13),"")) -> M109
A14: =AA14 -> M115 | B14: M115 | C14: Customer Bonus | D14: =VLOOKUP($AA14,Calc_INF_PrevYearEUR!$A$11:$BQ$330,HLOOKUP($C$7,Calc_INF_PrevYearEUR!$E$5:$BQ$6,2,0),0)*IF($C$9="EUR",1,START!$E$18) -> #N/A | E14: =IF(D14=0,0,D14/D$42) -> #N/A | F14: =VLOOKUP($AA14,Calc_INF_FC_EUR!$A$11:$BQ$330,HLOOKUP($C$7,Calc_INF_FC_EUR!$E$5:$BQ$6,2,0),0)*IF($C$9="EUR",1,START!$E$18)+G14 -> #N/A | J14: =IF(I14=0,0,I14/I$42) -> 0 | L14: =IF(K14=0,0,K14/K$42) -> 0 | N14: =IF(M14=0,0,M14/M$42) -> 0 | P14: =IF(O14=0,0,O14/O$42) -> 0 | R14: =IF(Q14=0,0,Q14/Q$42) -> 0 | T14: =IF(S14=0,0,S14/S$42) -> 0 | AA14: =IF(OR(B14=0,B14=""),"",B14&IF(COUNTIF(B$11:$B14,B14)>1,COUNTIF(B$11:$B14,B14),"")) -> M115
A15: =AA15 -> M116 | B15: M116 | C15: Customer Bonus affil. | D15: =VLOOKUP($AA15,Calc_INF_PrevYearEUR!$A$11:$BQ$330,HLOOKUP($C$7,Calc_INF_PrevYearEUR!$E$5:$BQ$6,2,0),0)*IF($C$9="EUR",1,START!$E$18) -> #N/A | E15: =IF(D15=0,0,D15/D$42) -> #N/A | F15: =VLOOKUP($AA15,Calc_INF_FC_EUR!$A$11:$BQ$330,HLOOKUP($C$7,Calc_INF_FC_EUR!$E$5:$BQ$6,2,0),0)*IF($C$9="EUR",1,START!$E$18)+G15 -> #N/A | J15: =IF(I15=0,0,I15/I$42) -> 0 | L15: =IF(K15=0,0,K15/K$42) -> 0 | N15: =IF(M15=0,0,M15/M$42) -> 0 | P15: =IF(O15=0,0,O15/O$42) -> 0 | R15: =IF(Q15=0,0,Q15/Q$42) -> 0 | T15: =IF(S15=0,0,S15/S$42) -> 0 | AA15: =IF(OR(B15=0,B15=""),"",B15&IF(COUNTIF(B$11:$B15,B15)>1,COUNTIF(B$11:$B15,B15),"")) -> M116
A16: =AA16 -> M120 | B16: M120 | C16: Claims | D16: =VLOOKUP($AA16,Calc_INF_PrevYearEUR!$A$11:$BQ$330,HLOOKUP($C$7,Calc_INF_PrevYearEUR!$E$5:$BQ$6,2,0),0)*IF($C$9="EUR",1,START!$E$18) -> #N/A | E16: =IF(D16=0,0,D16/D$42) -> #N/A | F16: =VLOOKUP($AA16,Calc_INF_FC_EUR!$A$11:$BQ$330,HLOOKUP($C$7,Calc_INF_FC_EUR!$E$5:$BQ$6,2,0),0)*IF($C$9="EUR",1,START!$E$18)+G16 -> #N/A | J16: =IF(I16=0,0,I16/I$42) -> 0 | L16: =IF(K16=0,0,K16/K$42) -> 0 | N16: =IF(M16=0,0,M16/M$42) -> 0 | P16: =IF(O16=0,0,O16/O$42) -> 0 | R16: =IF(Q16=0,0,Q16/Q$42) -> 0 | T16: =IF(S16=0,0,S16/S$42) -> 0 | AA16: =IF(OR(B16=0,B16=""),"",B16&IF(COUNTIF(B$11:$B16,B16)>1,COUNTIF(B$11:$B16,B16),"")) -> M120
A17: =AA17 -> M121 | B17: M121 | C17: Claims affil. | D17: =VLOOKUP($AA17,Calc_INF_PrevYearEUR!$A$11:$BQ$330,HLOOKUP($C$7,Calc_INF_PrevYearEUR!$E$5:$BQ$6,2,0),0)*IF($C$9="EUR",1,START!$E$18) -> #N/A | E17: =IF(D17=0,0,D17/D$42) -> #N/A | F17: =VLOOKUP($AA17,Calc_INF_FC_EUR!$A$11:$BQ$330,HLOOKUP($C$7,Calc_INF_FC_EUR!$E$5:$BQ$6,2,0),0)*IF($C$9="EUR",1,START!$E$18)+G17 -> #N/A | J17: =IF(I17=0,0,I17/I$42) -> 0 | L17: =IF(K17=0,0,K17/K$42) -> 0 | N17: =IF(M17=0,0,M17/M$42) -> 0 | P17: =IF(O17=0,0,O17/O$42) -> 0 | R17: =IF(Q17=0,0,Q17/Q$42) -> 0 | T17: =IF(S17=0,0,S17/S$42) -> 0 | AA17: =IF(OR(B17=0,B17=""),"",B17&IF(COUNTIF(B$11:$B17,B17)>1,COUNTIF(B$11:$B17,B17),"")) -> M121
A18: =AA18 -> M125 | B18: M125 | C18: Discount | D18: =VLOOKUP($AA18,Calc_INF_PrevYearEUR!$A$11:$BQ$330,HLOOKUP($C$7,Calc_INF_PrevYearEUR!$E$5:$BQ$6,2,0),0)*IF($C$9="EUR",1,START!$E$18) -> #N/A | E18: =IF(D18=0,0,D18/D$42) -> #N/A | F18: =VLOOKUP($AA18,Calc_INF_FC_EUR!$A$11:$BQ$330,HLOOKUP($C$7,Calc_INF_FC_EUR!$E$5:$BQ$6,2,0),0)*IF($C$9="EUR",1,START!$E$18)+G18 -> #N/A | J18: =IF(I18=0,0,I18/I$42) -> 0 | L18: =IF(K18=0,0,K18/K$42) -> 0 | N18: =IF(M18=0,0,M18/M$42) -> 0 | P18: =IF(O18=0,0,O18/O$42) -> 0 | R18: =IF(Q18=0,0,Q18/Q$42) -> 0 | T18: =IF(S18=0,0,S18/S$42) -> 0 | AA18: =IF(OR(B18=0,B18=""),"",B18&IF(COUNTIF(B$11:$B18,B18)>1,COUNTIF(B$11:$B18,B18),"")) -> M125
A19: =AA19 -> M126 | B19: M126 | C19: Discount affil. | D19: =VLOOKUP($AA19,Calc_INF_PrevYearEUR!$A$11:$BQ$330,HLOOKUP($C$7,Calc_INF_PrevYearEUR!$E$5:$BQ$6,2,0),0)*IF($C$9="EUR",1,START!$E$18) -> #N/A | E19: =IF(D19=0,0,D19/D$42) -> #N/A | F19: =VLOOKUP($AA19,Calc_INF_FC_EUR!$A$11:$BQ$330,HLOOKUP($C$7,Calc_INF_FC_EUR!$E$5:$BQ$6,2,0),0)*IF($C$9="EUR",1,START!$E$18)+G19 -> #N/A | J19: =IF(I19=0,0,I19/I$42) -> 0 | L19: =IF(K19=0,0,K19/K$42) -> 0 | N19: =IF(M19=0,0,M19/M$42) -> 0 | P19: =IF(O19=0,0,O19/O$42) -> 0 | R19: =IF(Q19=0,0,Q19/Q$42) -> 0 | T19: =IF(S19=0,0,S19/S$42) -> 0 | AA19: =IF(OR(B19=0,B19=""),"",B19&IF(COUNTIF(B$11:$B19,B19)>1,COUNTIF(B$11:$B19,B19),"")) -> M126
A20: =AA20 -> M130 | B20: M130 | C20: Freight refund | D20: =VLOOKUP($AA20,Calc_INF_PrevYearEUR!$A$11:$BQ$330,HLOOKUP($C$7,Calc_INF_PrevYearEUR!$E$5:$BQ$6,2,0),0)*IF($C$9="EUR",1,START!$E$18) -> #N/A | E20: =IF(D20=0,0,D20/D$42) -> #N/A | F20: =VLOOKUP($AA20,Calc_INF_FC_EUR!$A$11:$BQ$330,HLOOKUP($C$7,Calc_INF_FC_EUR!$E$5:$BQ$6,2,0),0)*IF($C$9="EUR",1,START!$E$18)+G20 -> #N/A | J20: =IF(I20=0,0,I20/I$42) -> 0 | L20: =IF(K20=0,0,K20/K$42) -> 0 | N20: =IF(M20=0,0,M20/M$42) -> 0 | P20: =IF(O20=0,0,O20/O$42) -> 0 | R20: =IF(Q20=0,0,Q20/Q$42) -> 0 | T20: =IF(S20=0,0,S20/S$42) -> 0 | AA20: =IF(OR(B20=0,B20=""),"",B20&IF(COUNTIF(B$11:$B20,B20)>1,COUNTIF(B$11:$B20,B20),"")) -> M130
A21: =AA21 -> M131 | B21: M131 | C21: Freight refund affil. | D21: =VLOOKUP($AA21,Calc_INF_PrevYearEUR!$A$11:$BQ$330,HLOOKUP($C$7,Calc_INF_PrevYearEUR!$E$5:$BQ$6,2,0),0)*IF($C$9="EUR",1,START!$E$18) -> #N/A | E21: =IF(D21=0,0,D21/D$42) -> #N/A | F21: =VLOOKUP($AA21,Calc_INF_FC_EUR!$A$11:$BQ$330,HLOOKUP($C$7,Calc_INF_FC_EUR!$E$5:$BQ$6,2,0),0)*IF($C$9="EUR",1,START!$E$18)+G21 -> #N/A | J21: =IF(I21=0,0,I21/I$42) -> 0 | L21: =IF(K21=0,0,K21/K$42) -> 0 | N21: =IF(M21=0,0,M21/M$42) -> 0 | P21: =IF(O21=0,0,O21/O$42) -> 0 | R21: =IF(Q21=0,0,Q21/Q$42) -> 0 | T21: =IF(S21=0,0,S21/S$42) -> 0 | AA21: =IF(OR(B21=0,B21=""),"",B21&IF(COUNTIF(B$11:$B21,B21)>1,COUNTIF(B$11:$B21,B21),"")) -> M131
A22: =AA22 -> M139 | B22: M139 | C22: Reduction in Sales - Core Business | D22: =VLOOKUP($AA22,Calc_INF_PrevYearEUR!$A$11:$BQ$330,HLOOKUP($C$7,Calc_INF_PrevYearEUR!$E$5:$BQ$6,2,0),0)*IF($C$9="EUR",1,START!$E$18) -> #N/A | E22: =IF(D22=0,0,D22/D$42) -> #N/A | F22: =VLOOKUP($AA22,Calc_INF_FC_EUR!$A$11:$BQ$330,HLOOKUP($C$7,Calc_INF_FC_EUR!$E$5:$BQ$6,2,0),0)*IF($C$9="EUR",1,START!$E$18)+G22 -> #N/A | G22: =SUM(G14:G21) -> 0 | I22: =SUM(I14:I21) -> 0 | J22: =IF(I22=0,0,I22/I$42) -> 0 | K22: =SUM(K14:K21) -> 0 | L22: =IF(K22=0,0,K22/K$42) -> 0 | M22: =SUM(M14:M21) -> 0 | N22: =IF(M22=0,0,M22/M$42) -> 0 | O22: =SUM(O14:O21) -> 0 | P22: =IF(O22=0,0,O22/O$42) -> 0 | Q22: =SUM(Q14:Q21) -> 0 | R22: =IF(Q22=0,0,Q22/Q$42) -> 0 | S22: =SUM(S14:S21) -> 0 | T22: =IF(S22=0,0,S22/S$42) -> 0 | AA22: =IF(OR(B22=0,B22=""),"",B22&IF(COUNTIF(B$11:$B22,B22)>1,COUNTIF(B$11:$B22,B22),"")) -> M139
A23: =AA23 -> M145 | B23: M145 | C23: Revenues from trade goods ext. | D23: =VLOOKUP($AA23,Calc_INF_PrevYearEUR!$A$11:$BQ$330,HLOOKUP($C$7,Calc_INF_PrevYearEUR!$E$5:$BQ$6,2,0),0)*IF($C$9="EUR",1,START!$E$18) -> #N/A | E23: =IF(D23=0,0,D23/D$42) -> #N/A | F23: =VLOOKUP($AA23,Calc_INF_FC_EUR!$A$11:$BQ$330,HLOOKUP($C$7,Calc_INF_FC_EUR!$E$5:$BQ$6,2,0),0)*IF($C$9="EUR",1,START!$E$18)+G23 -> #N/A | I23: =SUMIFS(SalesReport!$R:$R,SalesReport!$AF:$AF,$AB23,SalesReport!$A:$A,I$8,SalesReport!$B:$B,BusPlanLocation!$C$7)*IF($C$9="EUR",1,START!$E$18)/1000 -> 0 | J23: =IF(I23=0,0,I23/I$42) -> 0 | K23: =SUMIFS(SalesReport!$R:$R,SalesReport!$AF:$AF,$AB23,SalesReport!$A:$A,K$8,SalesReport!$B:$B,BusPlanLocation!$C$7)*IF($C$9="EUR",1,START!$E$18)/1000 -> 0 | L23: =IF(K23=0,0,K23/K$42) -> 0 | M23: =SUMIFS(SalesReport!$R:$R,SalesReport!$AF:$AF,$AB23,SalesReport!$A:$A,M$8,SalesReport!$B:$B,BusPlanLocation!$C$7)*IF($C$9="EUR",1,START!$E$18)/1000 -> 0 | N23: =IF(M23=0,0,M23/M$42) -> 0 | O23: =SUMIFS(SalesReport!$R:$R,SalesReport!$AF:$AF,$AB23,SalesReport!$A:$A,O$8,SalesReport!$B:$B,BusPlanLocation!$C$7)*IF($C$9="EUR",1,START!$E$18)/1000 -> 0 | P23: =IF(O23=0,0,O23/O$42) -> 0 | Q23: =SUMIFS(SalesReport!$R:$R,SalesReport!$AF:$AF,$AB23,SalesReport!$A:$A,Q$8,SalesReport!$B:$B,BusPlanLocation!$C$7)*IF($C$9="EUR",1,START!$E$18)/1000 -> 0 | R23: =IF(Q23=0,0,Q23/Q$42) -> 0 | S23: =SUMIFS(SalesReport!$R:$R,SalesReport!$AF:$AF,$AB23,SalesReport!$A:$A,S$8,SalesReport!$B:$B,BusPlanLocation!$C$7)*IF($C$9="EUR",1,START!$E$18)/1000 -> 0 | T23: =IF(S23=0,0,S23/S$42) -> 0 | AA23: =IF(OR(B23=0,B23=""),"",B23&IF(COUNTIF(B$11:$B23,B23)>1,COUNTIF(B$11:$B23,B23),"")) -> M145 | AB23: Tradeext
A24: =AA24 -> M146 | B24: M146 | C24: Revenues from trade goods affil. | D24: =VLOOKUP($AA24,Calc_INF_PrevYearEUR!$A$11:$BQ$330,HLOOKUP($C$7,Calc_INF_PrevYearEUR!$E$5:$BQ$6,2,0),0)*IF($C$9="EUR",1,START!$E$18) -> #N/A | E24: =IF(D24=0,0,D24/D$42) -> #N/A | F24: =VLOOKUP($AA24,Calc_INF_FC_EUR!$A$11:$BQ$330,HLOOKUP($C$7,Calc_INF_FC_EUR!$E$5:$BQ$6,2,0),0)*IF($C$9="EUR",1,START!$E$18)+G24 -> #N/A | I24: =SUMIFS(SalesReport!$R:$R,SalesReport!$AF:$AF,$AB24,SalesReport!$A:$A,I$8,SalesReport!$B:$B,BusPlanLocation!$C$7)*IF($C$9="EUR",1,START!$E$18)/1000 -> 0 | J24: =IF(I24=0,0,I24/I$42) -> 0 | K24: =SUMIFS(SalesReport!$R:$R,SalesReport!$AF:$AF,$AB24,SalesReport!$A:$A,K$8,SalesReport!$B:$B,BusPlanLocation!$C$7)*IF($C$9="EUR",1,START!$E$18)/1000 -> 0 | L24: =IF(K24=0,0,K24/K$42) -> 0 | M24: =SUMIFS(SalesReport!$R:$R,SalesReport!$AF:$AF,$AB24,SalesReport!$A:$A,M$8,SalesReport!$B:$B,BusPlanLocation!$C$7)*IF($C$9="EUR",1,START!$E$18)/1000 -> 0 | N24: =IF(M24=0,0,M24/M$42) -> 0 | O24: =SUMIFS(SalesReport!$R:$R,SalesReport!$AF:$AF,$AB24,SalesReport!$A:$A,O$8,SalesReport!$B:$B,BusPlanLocation!$C$7)*IF($C$9="EUR",1,START!$E$18)/1000 -> 0 | P24: =IF(O24=0,0,O24/O$42) -> 0 | Q24: =SUMIFS(SalesReport!$R:$R,SalesReport!$AF:$AF,$AB24,SalesReport!$A:$A,Q$8,SalesReport!$B:$B,BusPlanLocation!$C$7)*IF($C$9="EUR",1,START!$E$18)/1000 -> 0 | R24: =IF(Q24=0,0,Q24/Q$42) -> 0 | S24: =SUMIFS(SalesReport!$R:$R,SalesReport!$AF:$AF,$AB24,SalesReport!$A:$A,S$8,SalesReport!$B:$B,BusPlanLocation!$C$7)*IF($C$9="EUR",1,START!$E$18)/1000 -> 0 | T24: =IF(S24=0,0,S24/S$42) -> 0 | AA24: =IF(OR(B24=0,B24=""),"",B24&IF(COUNTIF(B$11:$B24,B24)>1,COUNTIF(B$11:$B24,B24),"")) -> M146 | AB24: Tradeaff
A25: =AA25 -> M149 | B25: M149 | C25: Sales from trade goods (net) | D25: =VLOOKUP($AA25,Calc_INF_PrevYearEUR!$A$11:$BQ$330,HLOOKUP($C$7,Calc_INF_PrevYearEUR!$E$5:$BQ$6,2,0),0)*IF($C$9="EUR",1,START!$E$18) -> #N/A | E25: =IF(D25=0,0,D25/D$42) -> #N/A | F25: =VLOOKUP($AA25,Calc_INF_FC_EUR!$A$11:$BQ$330,HLOOKUP($C$7,Calc_INF_FC_EUR!$E$5:$BQ$6,2,0),0)*IF($C$9="EUR",1,START!$E$18)+G25 -> #N/A | G25: =+G24+G23 -> 0 | I25: =+I24+I23 -> 0 | J25: =IF(I25=0,0,I25/I$42) -> 0 | K25: =+K24+K23 -> 0 | L25: =IF(K25=0,0,K25/K$42) -> 0 | M25: =+M24+M23 -> 0 | N25: =IF(M25=0,0,M25/M$42) -> 0 | O25: =+O24+O23 -> 0 | P25: =IF(O25=0,0,O25/O$42) -> 0 | Q25: =+Q24+Q23 -> 0 | R25: =IF(Q25=0,0,Q25/Q$42) -> 0 | S25: =+S24+S23 -> 0 | T25: =IF(S25=0,0,S25/S$42) -> 0 | AA25: =IF(OR(B25=0,B25=""),"",B25&IF(COUNTIF(B$11:$B25,B25)>1,COUNTIF(B$11:$B25,B25),"")) -> M149
A26: =AA26 -> M155 | B26: M155 | C26: Other Sales (net) ext. | D26: =VLOOKUP($AA26,Calc_INF_PrevYearEUR!$A$11:$BQ$330,HLOOKUP($C$7,Calc_INF_PrevYearEUR!$E$5:$BQ$6,2,0),0)*IF($C$9="EUR",1,START!$E$18) -> #N/A | E26: =IF(D26=0,0,D26/D$42) -> #N/A | F26: =VLOOKUP($AA26,Calc_INF_FC_EUR!$A$11:$BQ$330,HLOOKUP($C$7,Calc_INF_FC_EUR!$E$5:$BQ$6,2,0),0)*IF($C$9="EUR",1,START!$E$18)+G26 -> #N/A | I26: =SUMIFS(SalesReport!$R:$R,SalesReport!$AF:$AF,$AB26,SalesReport!$A:$A,I$8,SalesReport!$B:$B,BusPlanLocation!$C$7)*IF($C$9="EUR",1,START!$E$18)/1000 -> 0 | J26: =IF(I26=0,0,I26/I$42) -> 0 | K26: =SUMIFS(SalesReport!$R:$R,SalesReport!$AF:$AF,$AB26,SalesReport!$A:$A,K$8,SalesReport!$B:$B,BusPlanLocation!$C$7)*IF($C$9="EUR",1,START!$E$18)/1000 -> 0 | L26: =IF(K26=0,0,K26/K$42) -> 0 | M26: =SUMIFS(SalesReport!$R:$R,SalesReport!$AF:$AF,$AB26,SalesReport!$A:$A,M$8,SalesReport!$B:$B,BusPlanLocation!$C$7)*IF($C$9="EUR",1,START!$E$18)/1000 -> 0 | N26: =IF(M26=0,0,M26/M$42) -> 0 | O26: =SUMIFS(SalesReport!$R:$R,SalesReport!$AF:$AF,$AB26,SalesReport!$A:$A,O$8,SalesReport!$B:$B,BusPlanLocation!$C$7)*IF($C$9="EUR",1,START!$E$18)/1000 -> 0 | P26: =IF(O26=0,0,O26/O$42) -> 0 | Q26: =SUMIFS(SalesReport!$R:$R,SalesReport!$AF:$AF,$AB26,SalesReport!$A:$A,Q$8,SalesReport!$B:$B,BusPlanLocation!$C$7)*IF($C$9="EUR",1,START!$E$18)/1000 -> 0 | R26: =IF(Q26=0,0,Q26/Q$42) -> 0 | S26: =SUMIFS(SalesReport!$R:$R,SalesReport!$AF:$AF,$AB26,SalesReport!$A:$A,S$8,SalesReport!$B:$B,BusPlanLocation!$C$7)*IF($C$9="EUR",1,START!$E$18)/1000 -> 0 | T26: =IF(S26=0,0,S26/S$42) -> 0 | AA26: =IF(OR(B26=0,B26=""),"",B26&IF(COUNTIF(B$11:$B26,B26)>1,COUNTIF(B$11:$B26,B26),"")) -> M155 | AB26: Commission & Servicesext
A27: =AA27 -> M156 | B27: M156 | C27: Other Sales (net) affil. | D27: =VLOOKUP($AA27,Calc_INF_PrevYearEUR!$A$11:$BQ$330,HLOOKUP($C$7,Calc_INF_PrevYearEUR!$E$5:$BQ$6,2,0),0)*IF($C$9="EUR",1,START!$E$18) -> #N/A | E27: =IF(D27=0,0,D27/D$42) -> #N/A | F27: =VLOOKUP($AA27,Calc_INF_FC_EUR!$A$11:$BQ$330,HLOOKUP($C$7,Calc_INF_FC_EUR!$E$5:$BQ$6,2,0),0)*IF($C$9="EUR",1,START!$E$18)+G27 -> #N/A | I27: =SUMIFS(SalesReport!$R:$R,SalesReport!$AF:$AF,$AB27,SalesReport!$A:$A,I$8,SalesReport!$B:$B,BusPlanLocation!$C$7)*IF($C$9="EUR",1,START!$E$18)/1000 -> 0 | J27: =IF(I27=0,0,I27/I$42) -> 0 | K27: =SUMIFS(SalesReport!$R:$R,SalesReport!$AF:$AF,$AB27,SalesReport!$A:$A,K$8,SalesReport!$B:$B,BusPlanLocation!$C$7)*IF($C$9="EUR",1,START!$E$18)/1000 -> 0 | L27: =IF(K27=0,0,K27/K$42) -> 0 | M27: =SUMIFS(SalesReport!$R:$R,SalesReport!$AF:$AF,$AB27,SalesReport!$A:$A,M$8,SalesReport!$B:$B,BusPlanLocation!$C$7)*IF($C$9="EUR",1,START!$E$18)/1000 -> 0 | N27: =IF(M27=0,0,M27/M$42) -> 0 | O27: =SUMIFS(SalesReport!$R:$R,SalesReport!$AF:$AF,$AB27,SalesReport!$A:$A,O$8,SalesReport!$B:$B,BusPlanLocation!$C$7)*IF($C$9="EUR",1,START!$E$18)/1000 -> 0 | P27: =IF(O27=0,0,O27/O$42) -> 0 | Q27: =SUMIFS(SalesReport!$R:$R,SalesReport!$AF:$AF,$AB27,SalesReport!$A:$A,Q$8,SalesReport!$B:$B,BusPlanLocation!$C$7)*IF($C$9="EUR",1,START!$E$18)/1000 -> 0 | R27: =IF(Q27=0,0,Q27/Q$42) -> 0 | S27: =SUMIFS(SalesReport!$R:$R,SalesReport!$AF:$AF,$AB27,SalesReport!$A:$A,S$8,SalesReport!$B:$B,BusPlanLocation!$C$7)*IF($C$9="EUR",1,START!$E$18)/1000 -> 0 | T27: =IF(S27=0,0,S27/S$42) -> 0 | AA27: =IF(OR(B27=0,B27=""),"",B27&IF(COUNTIF(B$11:$B27,B27)>1,COUNTIF(B$11:$B27,B27),"")) -> M156 | AB27: Commission & Servicesaff
A28: =AA28 -> M159 | B28: M159 | C28: Other Sales (net) | D28: =VLOOKUP($AA28,Calc_INF_PrevYearEUR!$A$11:$BQ$330,HLOOKUP($C$7,Calc_INF_PrevYearEUR!$E$5:$BQ$6,2,0),0)*IF($C$9="EUR",1,START!$E$18) -> #N/A | E28: =IF(D28=0,0,D28/D$42) -> #N/A | F28: =VLOOKUP($AA28,Calc_INF_FC_EUR!$A$11:$BQ$330,HLOOKUP($C$7,Calc_INF_FC_EUR!$E$5:$BQ$6,2,0),0)*IF($C$9="EUR",1,START!$E$18)+G28 -> #N/A | G28: =+G27+G26 -> 0 | I28: =+I27+I26 -> 0 | J28: =IF(I28=0,0,I28/I$42) -> 0 | K28: =+K27+K26 -> 0 | L28: =IF(K28=0,0,K28/K$42) -> 0 | M28: =+M27+M26 -> 0 | N28: =IF(M28=0,0,M28/M$42) -> 0 | O28: =+O27+O26 -> 0 | P28: =IF(O28=0,0,O28/O$42) -> 0 | Q28: =+Q27+Q26 -> 0 | R28: =IF(Q28=0,0,Q28/Q$42) -> 0 | S28: =+S27+S26 -> 0 | T28: =IF(S28=0,0,S28/S$42) -> 0 | AA28: =IF(OR(B28=0,B28=""),"",B28&IF(COUNTIF(B$11:$B28,B28)>1,COUNTIF(B$11:$B28,B28),"")) -> M159
A29: =AA29 -> M179 | B29: M179 | C29: TOTAL SALES (net) | D29: =VLOOKUP($AA29,Calc_INF_PrevYearEUR!$A$11:$BQ$330,HLOOKUP($C$7,Calc_INF_PrevYearEUR!$E$5:$BQ$6,2,0),0)*IF($C$9="EUR",1,START!$E$18) -> #N/A | E29: =IF(D29=0,0,D29/D$42) -> #N/A | F29: =VLOOKUP($AA29,Calc_INF_FC_EUR!$A$11:$BQ$330,HLOOKUP($C$7,Calc_INF_FC_EUR!$E$5:$BQ$6,2,0),0)*IF($C$9="EUR",1,START!$E$18)+G29 -> #N/A | G29: =+G28+G25+G22+G13 -> 0 | I29: =+I28+I25+I22+I13 -> #REF! | J29: =IF(I29=0,0,I29/I$42) -> #REF! | K29: =+K28+K25+K22+K13 -> 0 | L29: =IF(K29=0,0,K29/K$42) -> 0 | M29: =+M28+M25+M22+M13 -> 0 | N29: =IF(M29=0,0,M29/M$42) -> 0 | O29: =+O28+O25+O22+O13 -> 0 | P29: =IF(O29=0,0,O29/O$42) -> 0 | Q29: =+Q28+Q25+Q22+Q13 -> 0 | R29: =IF(Q29=0,0,Q29/Q$42) -> 0 | S29: =+S28+S25+S22+S13 -> 0 | T29: =IF(S29=0,0,S29/S$42) -> 0 | AA29: =IF(OR(B29=0,B29=""),"",B29&IF(COUNTIF(B$11:$B29,B29)>1,COUNTIF(B$11:$B29,B29),"")) -> M179
A30: =AA30 -> M189 | B30: M189 | C30: Change in inventory | D30: =VLOOKUP($AA30,Calc_INF_PrevYearEUR!$A$11:$BQ$330,HLOOKUP($C$7,Calc_INF_PrevYearEUR!$E$5:$BQ$6,2,0),0)*IF($C$9="EUR",1,START!$E$18) -> #N/A | E30: =IF(D30=0,0,D30/D$42) -> #N/A | F30: =VLOOKUP($AA30,Calc_INF_FC_EUR!$A$11:$BQ$330,HLOOKUP($C$7,Calc_INF_FC_EUR!$E$5:$BQ$6,2,0),0)*IF($C$9="EUR",1,START!$E$18)+G30 -> #N/A | J30: =IF(I30=0,0,I30/I$42) -> 0 | L30: =IF(K30=0,0,K30/K$42) -> 0 | N30: =IF(M30=0,0,M30/M$42) -> 0 | P30: =IF(O30=0,0,O30/O$42) -> 0 | R30: =IF(Q30=0,0,Q30/Q$42) -> 0 | T30: =IF(S30=0,0,S30/S$42) -> 0 | AA30: =IF(OR(B30=0,B30=""),"",B30&IF(COUNTIF(B$11:$B30,B30)>1,COUNTIF(B$11:$B30,B30),"")) -> M189
A31: =AA31 -> M199 | B31: M199 | C31: OPERATING INCOME | D31: =VLOOKUP($AA31,Calc_INF_PrevYearEUR!$A$11:$BQ$330,HLOOKUP($C$7,Calc_INF_PrevYearEUR!$E$5:$BQ$6,2,0),0)*IF($C$9="EUR",1,START!$E$18) -> #N/A | E31: =IF(D31=0,0,D31/D$42) -> #N/A | F31: =VLOOKUP($AA31,Calc_INF_FC_EUR!$A$11:$BQ$330,HLOOKUP($C$7,Calc_INF_FC_EUR!$E$5:$BQ$6,2,0),0)*IF($C$9="EUR",1,START!$E$18)+G31 -> #N/A | G31: =+G29+G30 -> 0 | I31: =+I29+I30 -> #REF! | J31: =IF(I31=0,0,I31/I$42) -> #REF! | K31: =+K29+K30 -> 0 | L31: =IF(K31=0,0,K31/K$42) -> 0 | M31: =+M29+M30 -> 0 | N31: =IF(M31=0,0,M31/M$42) -> 0 | O31: =+O29+O30 -> 0 | P31: =IF(O31=0,0,O31/O$42) -> 0 | Q31: =+Q29+Q30 -> 0 | R31: =IF(Q31=0,0,Q31/Q$42) -> 0 | S31: =+S29+S30 -> 0 | T31: =IF(S31=0,0,S31/S$42) -> 0 | AA31: =IF(OR(B31=0,B31=""),"",B31&IF(COUNTIF(B$11:$B31,B31)>1,COUNTIF(B$11:$B31,B31),"")) -> M199
A32: =AA32 -> M215 | B32: M215 | C32: Storage costs | D32: =VLOOKUP($AA32,Calc_INF_PrevYearEUR!$A$11:$BQ$330,HLOOKUP($C$7,Calc_INF_PrevYearEUR!$E$5:$BQ$6,2,0),0)*IF($C$9="EUR",1,START!$E$18) -> #N/A | E32: =IF(D32=0,0,D32/D$42) -> #N/A | F32: =VLOOKUP($AA32,Calc_INF_FC_EUR!$A$11:$BQ$330,HLOOKUP($C$7,Calc_INF_FC_EUR!$E$5:$BQ$6,2,0),0)*IF($C$9="EUR",1,START!$E$18)+G32 -> #N/A | J32: =IF(I32=0,0,I32/I$42) -> 0 | L32: =IF(K32=0,0,K32/K$42) -> 0 | N32: =IF(M32=0,0,M32/M$42) -> 0 | P32: =IF(O32=0,0,O32/O$42) -> 0 | R32: =IF(Q32=0,0,Q32/Q$42) -> 0 | T32: =IF(S32=0,0,S32/S$42) -> 0 | AA32: =IF(OR(B32=0,B32=""),"",B32&IF(COUNTIF(B$11:$B32,B32)>1,COUNTIF(B$11:$B32,B32),"")) -> M215
A33: =AA33 -> M220 | B33: M220 | C33: Customs duties | D33: =VLOOKUP($AA33,Calc_INF_PrevYearEUR!$A$11:$BQ$330,HLOOKUP($C$7,Calc_INF_PrevYearEUR!$E$5:$BQ$6,2,0),0)*IF($C$9="EUR",1,START!$E$18) -> #N/A | E33: =IF(D33=0,0,D33/D$42) -> #N/A | F33: =VLOOKUP($AA33,Calc_INF_FC_EUR!$A$11:$BQ$330,HLOOKUP($C$7,Calc_INF_FC_EUR!$E$5:$BQ$6,2,0),0)*IF($C$9="EUR",1,START!$E$18)+G33 -> #N/A | J33: =IF(I33=0,0,I33/I$42) -> 0 | L33: =IF(K33=0,0,K33/K$42) -> 0 | N33: =IF(M33=0,0,M33/M$42) -> 0 | P33: =IF(O33=0,0,O33/O$42) -> 0 | R33: =IF(Q33=0,0,Q33/Q$42) -> 0 | T33: =IF(S33=0,0,S33/S$42) -> 0 | AA33: =IF(OR(B33=0,B33=""),"",B33&IF(COUNTIF(B$11:$B33,B33)>1,COUNTIF(B$11:$B33,B33),"")) -> M220
A34: =AA34 -> M225 | B34: M225 | C34: Commissions | D34: =VLOOKUP($AA34,Calc_INF_PrevYearEUR!$A$11:$BQ$330,HLOOKUP($C$7,Calc_INF_PrevYearEUR!$E$5:$BQ$6,2,0),0)*IF($C$9="EUR",1,START!$E$18) -> #N/A | E34: =IF(D34=0,0,D34/D$42) -> #N/A | F34: =VLOOKUP($AA34,Calc_INF_FC_EUR!$A$11:$BQ$330,HLOOKUP($C$7,Calc_INF_FC_EUR!$E$5:$BQ$6,2,0),0)*IF($C$9="EUR",1,START!$E$18)+G34 -> #N/A | J34: =IF(I34=0,0,I34/I$42) -> 0 | L34: =IF(K34=0,0,K34/K$42) -> 0 | N34: =IF(M34=0,0,M34/M$42) -> 0 | P34: =IF(O34=0,0,O34/O$42) -> 0 | R34: =IF(Q34=0,0,Q34/Q$42) -> 0 | T34: =IF(S34=0,0,S34/S$42) -> 0 | AA34: =IF(OR(B34=0,B34=""),"",B34&IF(COUNTIF(B$11:$B34,B34)>1,COUNTIF(B$11:$B34,B34),"")) -> M225
A35: =AA35 -> M226 | B35: M226 | C35: Commissions affil. | D35: =VLOOKUP($AA35,Calc_INF_PrevYearEUR!$A$11:$BQ$330,HLOOKUP($C$7,Calc_INF_PrevYearEUR!$E$5:$BQ$6,2,0),0)*IF($C$9="EUR",1,START!$E$18) -> #N/A | E35: =IF(D35=0,0,D35/D$42) -> #N/A | F35: =VLOOKUP($AA35,Calc_INF_FC_EUR!$A$11:$BQ$330,HLOOKUP($C$7,Calc_INF_FC_EUR!$E$5:$BQ$6,2,0),0)*IF($C$9="EUR",1,START!$E$18)+G35 -> #N/A | J35: =IF(I35=0,0,I35/I$42) -> 0 | L35: =IF(K35=0,0,K35/K$42) -> 0 | N35: =IF(M35=0,0,M35/M$42) -> 0 | P35: =IF(O35=0,0,O35/O$42) -> 0 | R35: =IF(Q35=0,0,Q35/Q$42) -> 0 | T35: =IF(S35=0,0,S35/S$42) -> 0 | AA35: =IF(OR(B35=0,B35=""),"",B35&IF(COUNTIF(B$11:$B35,B35)>1,COUNTIF(B$11:$B35,B35),"")) -> M226
A36: =AA36 -> M230 | B36: M230 | C36: Transport insurance | D36: =VLOOKUP($AA36,Calc_INF_PrevYearEUR!$A$11:$BQ$330,HLOOKUP($C$7,Calc_INF_PrevYearEUR!$E$5:$BQ$6,2,0),0)*IF($C$9="EUR",1,START!$E$18) -> #N/A | E36: =IF(D36=0,0,D36/D$42) -> #N/A | F36: =VLOOKUP($AA36,Calc_INF_FC_EUR!$A$11:$BQ$330,HLOOKUP($C$7,Calc_INF_FC_EUR!$E$5:$BQ$6,2,0),0)*IF($C$9="EUR",1,START!$E$18)+G36 -> #N/A | J36: =IF(I36=0,0,I36/I$42) -> 0 | L36: =IF(K36=0,0,K36/K$42) -> 0 | N36: =IF(M36=0,0,M36/M$42) -> 0 | P36: =IF(O36=0,0,O36/O$42) -> 0 | R36: =IF(Q36=0,0,Q36/Q$42) -> 0 | T36: =IF(S36=0,0,S36/S$42) -> 0 | AA36: =IF(OR(B36=0,B36=""),"",B36&IF(COUNTIF(B$11:$B36,B36)>1,COUNTIF(B$11:$B36,B36),"")) -> M230
A37: =AA37 -> M235 | B37: M235 | C37: Incidental expenses | D37: =VLOOKUP($AA37,Calc_INF_PrevYearEUR!$A$11:$BQ$330,HLOOKUP($C$7,Calc_INF_PrevYearEUR!$E$5:$BQ$6,2,0),0)*IF($C$9="EUR",1,START!$E$18) -> #N/A | E37: =IF(D37=0,0,D37/D$42) -> #N/A | F37: =VLOOKUP($AA37,Calc_INF_FC_EUR!$A$11:$BQ$330,HLOOKUP($C$7,Calc_INF_FC_EUR!$E$5:$BQ$6,2,0),0)*IF($C$9="EUR",1,START!$E$18)+G37 -> #N/A | J37: =IF(I37=0,0,I37/I$42) -> 0 | L37: =IF(K37=0,0,K37/K$42) -> 0 | N37: =IF(M37=0,0,M37/M$42) -> 0 | P37: =IF(O37=0,0,O37/O$42) -> 0 | R37: =IF(Q37=0,0,Q37/Q$42) -> 0 | T37: =IF(S37=0,0,S37/S$42) -> 0 | AA37: =IF(OR(B37=0,B37=""),"",B37&IF(COUNTIF(B$11:$B37,B37)>1,COUNTIF(B$11:$B37,B37),"")) -> M235
A38: =AA38 -> M240 | B38: M240 | C38: Bad debts | D38: =VLOOKUP($AA38,Calc_INF_PrevYearEUR!$A$11:$BQ$330,HLOOKUP($C$7,Calc_INF_PrevYearEUR!$E$5:$BQ$6,2,0),0)*IF($C$9="EUR",1,START!$E$18) -> #N/A | E38: =IF(D38=0,0,D38/D$42) -> #N/A | F38: =VLOOKUP($AA38,Calc_INF_FC_EUR!$A$11:$BQ$330,HLOOKUP($C$7,Calc_INF_FC_EUR!$E$5:$BQ$6,2,0),0)*IF($C$9="EUR",1,START!$E$18)+G38 -> #N/A | J38: =IF(I38=0,0,I38/I$42) -> 0 | L38: =IF(K38=0,0,K38/K$42) -> 0 | N38: =IF(M38=0,0,M38/M$42) -> 0 | P38: =IF(O38=0,0,O38/O$42) -> 0 | R38: =IF(Q38=0,0,Q38/Q$42) -> 0 | T38: =IF(S38=0,0,S38/S$42) -> 0 | AA38: =IF(OR(B38=0,B38=""),"",B38&IF(COUNTIF(B$11:$B38,B38)>1,COUNTIF(B$11:$B38,B38),"")) -> M240
A39: =AA39 -> M245 | B39: M245 | C39: Other sales expenses | D39: =VLOOKUP($AA39,Calc_INF_PrevYearEUR!$A$11:$BQ$330,HLOOKUP($C$7,Calc_INF_PrevYearEUR!$E$5:$BQ$6,2,0),0)*IF($C$9="EUR",1,START!$E$18) -> #N/A | E39: =IF(D39=0,0,D39/D$42) -> #N/A | F39: =VLOOKUP($AA39,Calc_INF_FC_EUR!$A$11:$BQ$330,HLOOKUP($C$7,Calc_INF_FC_EUR!$E$5:$BQ$6,2,0),0)*IF($C$9="EUR",1,START!$E$18)+G39 -> #N/A | J39: =IF(I39=0,0,I39/I$42) -> 0 | L39: =IF(K39=0,0,K39/K$42) -> 0 | M39: =K39*1.15 -> 0 | N39: =IF(M39=0,0,M39/M$42) -> 0 | P39: =IF(O39=0,0,O39/O$42) -> 0 | R39: =IF(Q39=0,0,Q39/Q$42) -> 0 | T39: =IF(S39=0,0,S39/S$42) -> 0 | AA39: =IF(OR(B39=0,B39=""),"",B39&IF(COUNTIF(B$11:$B39,B39)>1,COUNTIF(B$11:$B39,B39),"")) -> M245
A40: =AA40 -> M249 | B40: M249 | C40: Sales expenses | D40: =VLOOKUP($AA40,Calc_INF_PrevYearEUR!$A$11:$BQ$330,HLOOKUP($C$7,Calc_INF_PrevYearEUR!$E$5:$BQ$6,2,0),0)*IF($C$9="EUR",1,START!$E$18) -> #N/A | E40: =IF(D40=0,0,D40/D$42) -> #N/A | F40: =VLOOKUP($AA40,Calc_INF_FC_EUR!$A$11:$BQ$330,HLOOKUP($C$7,Calc_INF_FC_EUR!$E$5:$BQ$6,2,0),0)*IF($C$9="EUR",1,START!$E$18)+G40 -> #N/A | G40: =SUM(G32:G39) -> 0 | I40: =SUM(I32:I39) -> 0 | J40: =IF(I40=0,0,I40/I$42) -> 0 | K40: =SUM(K32:K39) -> 0 | L40: =IF(K40=0,0,K40/K$42) -> 0 | M40: =SUM(M32:M39) -> 0 | N40: =IF(M40=0,0,M40/M$42) -> 0 | O40: =SUM(O32:O39) -> 0 | P40: =IF(O40=0,0,O40/O$42) -> 0 | Q40: =SUM(Q32:Q39) -> 0 | R40: =IF(Q40=0,0,Q40/Q$42) -> 0 | S40: =SUM(S32:S39) -> 0 | T40: =IF(S40=0,0,S40/S$42) -> 0 | AA40: =IF(OR(B40=0,B40=""),"",B40&IF(COUNTIF(B$11:$B40,B40)>1,COUNTIF(B$11:$B40,B40),"")) -> M249
A41: =AA41 -> M209 | B41: M209 | C41: Shipping expenses | D41: =VLOOKUP($AA41,Calc_INF_PrevYearEUR!$A$11:$BQ$330,HLOOKUP($C$7,Calc_INF_PrevYearEUR!$E$5:$BQ$6,2,0),0)*IF($C$9="EUR",1,START!$E$18) -> #N/A | E41: =IF(D41=0,0,D41/D$42) -> #N/A | F41: =VLOOKUP($AA41,Calc_INF_FC_EUR!$A$11:$BQ$330,HLOOKUP($C$7,Calc_INF_FC_EUR!$E$5:$BQ$6,2,0),0)*IF($C$9="EUR",1,START!$E$18)+G41 -> #N/A | G41: =IF(AND($G$155<>0,$G$233<>0),((VLOOKUP("Collection",Calc_INF_FC_EUR!$A$11:$BQ$330,HLOOKUP($C$7,Calc_INF_FC_EUR!$E$5:$BQ$6,2,0),0)*IF($C$9="EUR",1,START!$E$18)+$G$155)*(VLOOKUP($AA233,Calc_INF_FC_EUR!$A$11:$BQ$330,HLOOKUP($C$7,Calc_INF_FC_EUR!$E$5:$BQ$6,2,0),0)*IF($C$9="EUR",1,START!$E$18)+$G$233))/1000-VLOOKUP($AA41,Calc_INF_FC_EUR!$A$11:$BQ$330,HLOOKUP($C$7,Calc_INF_FC_EUR!$E$5:$BQ$6,2,0),0)*IF($C$9="EUR",1,START!$E$18),IF(OR($G$155<>0,$G$233<>0),(IF($G$155<>0,$G$155,VLOOKUP($AA155,Calc_INF_FC_EUR!$A$11:$BQ$330,HLOOKUP($C$7,Calc_INF_FC_EUR!$E$5:$BQ$6,2,0),0)*IF($C$9="EUR",1,START!$E$18))*IF($G$233<>0,$G$233,VLOOKUP($AA233,Calc_INF_FC_EUR!$A$11:$BQ$330,HLOOKUP($C$7,Calc_INF_FC_EUR!$E$5:$BQ$6,2,0),0)*IF($C$9="EUR",1,START!$E$18)))/1000,0)) -> 0 | I41: =SUMIFS(SalesReport!$T:$T,SalesReport!$A:$A,I$8,SalesReport!$B:$B,BusPlanLocation!$C$7)*IF($C$9="EUR",1,START!$E$18)/-1000 -> #REF! | J41: =IF(I41=0,0,I41/I$42) -> #REF! | K41: =SUMIFS(SalesReport!$T:$T,SalesReport!$A:$A,K$8,SalesReport!$B:$B,BusPlanLocation!$C$7)*IF($C$9="EUR",1,START!$E$18)/-1000 -> 0 | L41: =IF(K41=0,0,K41/K$42) -> 0 | M41: =SUMIFS(SalesReport!$T:$T,SalesReport!$A:$A,M$8,SalesReport!$B:$B,BusPlanLocation!$C$7)*IF($C$9="EUR",1,START!$E$18)/-1000 -> 0 | N41: =IF(M41=0,0,M41/M$42) -> 0 | O41: =SUMIFS(SalesReport!$T:$T,SalesReport!$A:$A,O$8,SalesReport!$B:$B,BusPlanLocation!$C$7)*IF($C$9="EUR",1,START!$E$18)/-1000 -> 0 | P41: =IF(O41=0,0,O41/O$42) -> 0 | Q41: =SUMIFS(SalesReport!$T:$T,SalesReport!$A:$A,Q$8,SalesReport!$B:$B,BusPlanLocation!$C$7)*IF($C$9="EUR",1,START!$E$18)/-1000 -> 0 | R41: =IF(Q41=0,0,Q41/Q$42) -> 0 | S41: =SUMIFS(SalesReport!$T:$T,SalesReport!$A:$A,S$8,SalesReport!$B:$B,BusPlanLocation!$C$7)*IF($C$9="EUR",1,START!$E$18)/-1000 -> 0 | T41: =IF(S41=0,0,S41/S$42) -> 0 | V41: Mean | W41: Rel. To EBITDA | AA41: =IF(OR(B41=0,B41=""),"",B41&IF(COUNTIF(B$11:$B41,B41)>1,COUNTIF(B$11:$B41,B41),"")) -> M209
A42: =AA42 -> M299 | B42: M299 | C42: NET REVENUE | D42: =VLOOKUP($AA42,Calc_INF_PrevYearEUR!$A$11:$BQ$330,HLOOKUP($C$7,Calc_INF_PrevYearEUR!$E$5:$BQ$6,2,0),0)*IF($C$9="EUR",1,START!$E$18) -> #N/A | E42: =IF(D42=0,0,D42/D$42) -> #N/A | F42: =VLOOKUP($AA42,Calc_INF_FC_EUR!$A$11:$BQ$330,HLOOKUP($C$7,Calc_INF_FC_EUR!$E$5:$BQ$6,2,0),0)*IF($C$9="EUR",1,START!$E$18)+G42 -> #N/A | G42: =G31+G41+G40 -> 0 | I42: =I31+I41+I40 -> #REF! | J42: =IF(I42=0,0,I42/I$42) -> #REF! | K42: =K31+K41+K40 -> 0 | L42: =IF(K42=0,0,K42/K$42) -> 0 | M42: =M31+M41+M40 -> 0 | N42: =IF(M42=0,0,M42/M$42) -> 0 | O42: =O31+O41+O40 -> 0 | P42: =IF(O42=0,0,O42/O$42) -> 0 | Q42: =Q31+Q41+Q40 -> 0 | R42: =IF(Q42=0,0,Q42/Q$42) -> 0 | S42: =S31+S41+S40 -> 0 | T42: =IF(S42=0,0,S42/S$42) -> 0 | V42: =(I42+K42+M42+O42+Q42+S42)/6 -> #REF! | W42: =V92/V42 -> #REF! | AA42: =IF(OR(B42=0,B42=""),"",B42&IF(COUNTIF(B$11:$B42,B42)>1,COUNTIF(B$11:$B42,B42),"")) -> M299
A43: =AA43 -> M305 | B43: M305 | C43: Raw mat. & bought products (purch. parts) | D43: =VLOOKUP($AA43,Calc_INF_PrevYearEUR!$A$11:$BQ$330,HLOOKUP($C$7,Calc_INF_PrevYearEUR!$E$5:$BQ$6,2,0),0)*IF($C$9="EUR",1,START!$E$18) -> #N/A | E43: =IF(D43=0,0,D43/D$13) -> #N/A | F43: =VLOOKUP($AA43,Calc_INF_FC_EUR!$A$11:$BQ$330,HLOOKUP($C$7,Calc_INF_FC_EUR!$E$5:$BQ$6,2,0),0)*IF($C$9="EUR",1,START!$E$18)+G43 -> #N/A | G43: =IF(AND($G$155<>0,$G$237<>0),((VLOOKUP("Collection",Calc_INF_FC_EUR!$A$11:$BQ$330,HLOOKUP($C$7,Calc_INF_FC_EUR!$E$5:$BQ$6,2,0),0)*IF($C$9="EUR",1,START!$E$18)+$G$155)*(VLOOKUP($AA237,Calc_INF_FC_EUR!$A$11:$BQ$330,HLOOKUP($C$7,Calc_INF_FC_EUR!$E$5:$BQ$6,2,0),0)*IF($C$9="EUR",1,START!$E$18)+$G$237))/1000-VLOOKUP($AA43,Calc_INF_FC_EUR!$A$11:$BQ$330,HLOOKUP($C$7,Calc_INF_FC_EUR!$E$5:$BQ$6,2,0),0)*IF($C$9="EUR",1,START!$E$18),IF(OR($G$155<>0,$G$237<>0),(IF($G$155<>0,$G$155,VLOOKUP($AA155,Calc_INF_FC_EUR!$A$11:$BQ$330,HLOOKUP($C$7,Calc_INF_FC_EUR!$E$5:$BQ$6,2,0),0)*IF($C$9="EUR",1,START!$E$18))*IF($G$237<>0,$G$237,VLOOKUP($AA237,Calc_INF_FC_EUR!$A$11:$BQ$330,HLOOKUP($C$7,Calc_INF_FC_EUR!$E$5:$BQ$6,2,0),0)*IF($C$9="EUR",1,START!$E$18)))/1000,0)) -> 0 | I43: =SUMIFS(SalesReport!$S:$S,SalesReport!$F:$F,$AB43,SalesReport!$A:$A,I$8,SalesReport!$B:$B,BusPlanLocation!$C$7)*IF($C$9="EUR",1,START!$E$18)/-1000 -> #REF! | J43: =IF(I43=0,0,I43/I$13) -> #REF! | K43: =SUMIFS(SalesReport!$S:$S,SalesReport!$F:$F,$AB43,SalesReport!$A:$A,K$8,SalesReport!$B:$B,BusPlanLocation!$C$7)*IF($C$9="EUR",1,START!$E$18)/-1000 -> 0 | L43: =IF(K43=0,0,K43/K$13) -> 0 | M43: =SUMIFS(SalesReport!$S:$S,SalesReport!$F:$F,$AB43,SalesReport!$A:$A,M$8,SalesReport!$B:$B,BusPlanLocation!$C$7)*IF($C$9="EUR",1,START!$E$18)/-1000 -> 0 | N43: =IF(M43=0,0,M43/M$13) -> 0 | O43: =SUMIFS(SalesReport!$S:$S,SalesReport!$F:$F,$AB43,SalesReport!$A:$A,O$8,SalesReport!$B:$B,BusPlanLocation!$C$7)*IF($C$9="EUR",1,START!$E$18)/-1000 -> 0 | P43: =IF(O43=0,0,O43/O$13) -> 0 | Q43: =SUMIFS(SalesReport!$S:$S,SalesReport!$F:$F,$AB43,SalesReport!$A:$A,Q$8,SalesReport!$B:$B,BusPlanLocation!$C$7)*IF($C$9="EUR",1,START!$E$18)/-1000 -> 0 | R43: =IF(Q43=0,0,Q43/Q$13) -> 0 | S43: =SUMIFS(SalesReport!$S:$S,SalesReport!$F:$F,$AB43,SalesReport!$A:$A,S$8,SalesReport!$B:$B,BusPlanLocation!$C$7)*IF($C$9="EUR",1,START!$E$18)/-1000 -> 0 | T43: =IF(S43=0,0,S43/S$13) -> 0 | AA43: =IF(OR(B43=0,B43=""),"",B43&IF(COUNTIF(B$11:$B43,B43)>1,COUNTIF(B$11:$B43,B43),"")) -> M305 | AB43: Collection
A44: =AA44 -> M310 | B44: M310 | C44: Chemicals | D44: =VLOOKUP($AA44,Calc_INF_PrevYearEUR!$A$11:$BQ$330,HLOOKUP($C$7,Calc_INF_PrevYearEUR!$E$5:$BQ$6,2,0),0)*IF($C$9="EUR",1,START!$E$18) -> #N/A | E44: =IF(D44=0,0,D44/D$13) -> #N/A | F44: =VLOOKUP($AA44,Calc_INF_FC_EUR!$A$11:$BQ$330,HLOOKUP($C$7,Calc_INF_FC_EUR!$E$5:$BQ$6,2,0),0)*IF($C$9="EUR",1,START!$E$18)+G44 -> #N/A | J44: =IF(I44=0,0,I44/I$13) -> 0 | L44: =IF(K44=0,0,K44/K$13) -> 0 | N44: =IF(M44=0,0,M44/M$13) -> 0 | P44: =IF(O44=0,0,O44/O$13) -> 0 | R44: =IF(Q44=0,0,Q44/Q$13) -> 0 | T44: =IF(S44=0,0,S44/S$13) -> 0 | AA44: =IF(OR(B44=0,B44=""),"",B44&IF(COUNTIF(B$11:$B44,B44)>1,COUNTIF(B$11:$B44,B44),"")) -> M310
A45: =AA45 -> M315 | B45: M315 | C45: Cost of tools, wire, felt | D45: =VLOOKUP($AA45,Calc_INF_PrevYearEUR!$A$11:$BQ$330,HLOOKUP($C$7,Calc_INF_PrevYearEUR!$E$5:$BQ$6,2,0),0)*IF($C$9="EUR",1,START!$E$18) -> #N/A | E45: =IF(D45=0,0,D45/D$13) -> #N/A | F45: =VLOOKUP($AA45,Calc_INF_FC_EUR!$A$11:$BQ$330,HLOOKUP($C$7,Calc_INF_FC_EUR!$E$5:$BQ$6,2,0),0)*IF($C$9="EUR",1,START!$E$18)+G45 -> #N/A | I45: ='CC cost Calculations'!#REF!/START!E18*-1/1000 -> #REF! | J45: =IF(I45=0,0,I45/I$13) -> #REF! | K45: =I45 -> #REF! | L45: =IF(K45=0,0,K45/K$13) -> #REF! | M45: =I45*0.84 -> #REF! | N45: =IF(M45=0,0,M45/M$13) -> #REF! | P45: =IF(O45=0,0,O45/O$13) -> 0 | R45: =IF(Q45=0,0,Q45/Q$13) -> 0 | T45: =IF(S45=0,0,S45/S$13) -> 0 | AA45: =IF(OR(B45=0,B45=""),"",B45&IF(COUNTIF(B$11:$B45,B45)>1,COUNTIF(B$11:$B45,B45),"")) -> M315
A46: =AA46 -> M320 | B46: M320 | C46: Other aux. and operation mat. | D46: =VLOOKUP($AA46,Calc_INF_PrevYearEUR!$A$11:$BQ$330,HLOOKUP($C$7,Calc_INF_PrevYearEUR!$E$5:$BQ$6,2,0),0)*IF($C$9="EUR",1,START!$E$18) -> #N/A | E46: =IF(D46=0,0,D46/D$13) -> #N/A | F46: =VLOOKUP($AA46,Calc_INF_FC_EUR!$A$11:$BQ$330,HLOOKUP($C$7,Calc_INF_FC_EUR!$E$5:$BQ$6,2,0),0)*IF($C$9="EUR",1,START!$E$18)+G46 -> #N/A | J46: =IF(I46=0,0,I46/I$13) -> 0 | L46: =IF(K46=0,0,K46/K$13) -> 0 | N46: =IF(M46=0,0,M46/M$13) -> 0 | P46: =IF(O46=0,0,O46/O$13) -> 0 | R46: =IF(Q46=0,0,Q46/Q$13) -> 0 | T46: =IF(S46=0,0,S46/S$13) -> 0 | AA46: =IF(OR(B46=0,B46=""),"",B46&IF(COUNTIF(B$11:$B46,B46)>1,COUNTIF(B$11:$B46,B46),"")) -> M320
A47: =AA47 -> M325 | B47: M325 | C47: External production services | D47: =VLOOKUP($AA47,Calc_INF_PrevYearEUR!$A$11:$BQ$330,HLOOKUP($C$7,Calc_INF_PrevYearEUR!$E$5:$BQ$6,2,0),0)*IF($C$9="EUR",1,START!$E$18) -> #N/A | E47: =IF(D47=0,0,D47/D$13) -> #N/A | F47: =VLOOKUP($AA47,Calc_INF_FC_EUR!$A$11:$BQ$330,HLOOKUP($C$7,Calc_INF_FC_EUR!$E$5:$BQ$6,2,0),0)*IF($C$9="EUR",1,START!$E$18)+G47 -> #N/A | J47: =IF(I47=0,0,I47/I$13) -> 0 | L47: =IF(K47=0,0,K47/K$13) -> 0 | N47: =IF(M47=0,0,M47/M$13) -> 0 | P47: =IF(O47=0,0,O47/O$13) -> 0 | R47: =IF(Q47=0,0,Q47/Q$13) -> 0 | T47: =IF(S47=0,0,S47/S$13) -> 0 | AA47: =IF(OR(B47=0,B47=""),"",B47&IF(COUNTIF(B$11:$B47,B47)>1,COUNTIF(B$11:$B47,B47),"")) -> M325
A48: =AA48 -> M339 | B48: M339 | C48: Material expenditure - Core Business | D48: =VLOOKUP($AA48,Calc_INF_PrevYearEUR!$A$11:$BQ$330,HLOOKUP($C$7,Calc_INF_PrevYearEUR!$E$5:$BQ$6,2,0),0)*IF($C$9="EUR",1,START!$E$18) -> #N/A | E48: =IF(D48=0,0,D48/D$13) -> #N/A | F48: =VLOOKUP($AA48,Calc_INF_FC_EUR!$A$11:$BQ$330,HLOOKUP($C$7,Calc_INF_FC_EUR!$E$5:$BQ$6,2,0),0)*IF($C$9="EUR",1,START!$E$18)+G48 -> #N/A | G48: =+SUM(G43:G47) -> 0 | I48: =SUM(I43:I47) -> #REF! | J48: =IF(I48=0,0,I48/I$13) -> #REF! | K48: =SUM(K43:K47) -> #REF! | L48: =IF(K48=0,0,K48/K$13) -> #REF! | M48: =SUM(M43:M47) -> #REF! | N48: =IF(M48=0,0,M48/M$13) -> #REF! | O48: =SUM(O43:O47) -> 0 | P48: =IF(O48=0,0,O48/O$13) -> 0 | Q48: =SUM(Q43:Q47) -> 0 | R48: =IF(Q48=0,0,Q48/Q$13) -> 0 | S48: =SUM(S43:S47) -> 0 | T48: =IF(S48=0,0,S48/S$13) -> 0 | AA48: =IF(OR(B48=0,B48=""),"",B48&IF(COUNTIF(B$11:$B48,B48)>1,COUNTIF(B$11:$B48,B48),"")) -> M339
A49: =AA49 -> M349 | B49: M349 | C49: Material expenditures - Trade goods | D49: =VLOOKUP($AA49,Calc_INF_PrevYearEUR!$A$11:$BQ$330,HLOOKUP($C$7,Calc_INF_PrevYearEUR!$E$5:$BQ$6,2,0),0)*IF($C$9="EUR",1,START!$E$18) -> #N/A | E49: =IF(D49=0,0,D49/D$25) -> #N/A | F49: =VLOOKUP($AA49,Calc_INF_FC_EUR!$A$11:$BQ$330,HLOOKUP($C$7,Calc_INF_FC_EUR!$E$5:$BQ$6,2,0),0)*IF($C$9="EUR",1,START!$E$18)+G49 -> #N/A | I49: =SUMIFS(SalesReport!$S:$S,SalesReport!$F:$F,$AB49,SalesReport!$A:$A,I$8,SalesReport!$B:$B,BusPlanLocation!$C$7)*IF($C$9="EUR",1,START!$E$18)/-1000 -> 0 | J49: =IF(I49=0,0,I49/I$25) -> 0 | K49: =SUMIFS(SalesReport!$S:$S,SalesReport!$F:$F,$AB49,SalesReport!$A:$A,K$8,SalesReport!$B:$B,BusPlanLocation!$C$7)*IF($C$9="EUR",1,START!$E$18)/-1000 -> 0 | L49: =IF(K49=0,0,K49/K$25) -> 0 | M49: =SUMIFS(SalesReport!$S:$S,SalesReport!$F:$F,$AB49,SalesReport!$A:$A,M$8,SalesReport!$B:$B,BusPlanLocation!$C$7)*IF($C$9="EUR",1,START!$E$18)/-1000 -> 0 | N49: =IF(M49=0,0,M49/M$25) -> 0 | O49: =SUMIFS(SalesReport!$S:$S,SalesReport!$F:$F,$AB49,SalesReport!$A:$A,O$8,SalesReport!$B:$B,BusPlanLocation!$C$7)*IF($C$9="EUR",1,START!$E$18)/-1000 -> 0 | P49: =IF(O49=0,0,O49/O$25) -> 0 | Q49: =SUMIFS(SalesReport!$S:$S,SalesReport!$F:$F,$AB49,SalesReport!$A:$A,Q$8,SalesReport!$B:$B,BusPlanLocation!$C$7)*IF($C$9="EUR",1,START!$E$18)/-1000 -> 0 | R49: =IF(Q49=0,0,Q49/Q$25) -> 0 | S49: =SUMIFS(SalesReport!$S:$S,SalesReport!$F:$F,$AB49,SalesReport!$A:$A,S$8,SalesReport!$B:$B,BusPlanLocation!$C$7)*IF($C$9="EUR",1,START!$E$18)/-1000 -> 0 | T49: =IF(S49=0,0,S49/S$25) -> 0 | AA49: =IF(OR(B49=0,B49=""),"",B49&IF(COUNTIF(B$11:$B49,B49)>1,COUNTIF(B$11:$B49,B49),"")) -> M349 | AB49: Trade
A50: =AA50 -> M359 | B50: M359 | C50: Other Material expenditures | D50: =VLOOKUP($AA50,Calc_INF_PrevYearEUR!$A$11:$BQ$330,HLOOKUP($C$7,Calc_INF_PrevYearEUR!$E$5:$BQ$6,2,0),0)*IF($C$9="EUR",1,START!$E$18) -> #N/A | E50: =IF(D50=0,0,D50/D$28) -> #N/A | F50: =VLOOKUP($AA50,Calc_INF_FC_EUR!$A$11:$BQ$330,HLOOKUP($C$7,Calc_INF_FC_EUR!$E$5:$BQ$6,2,0),0)*IF($C$9="EUR",1,START!$E$18)+G50 -> #N/A | I50: =SUMIFS(SalesReport!$S:$S,SalesReport!$F:$F,$AB50,SalesReport!$A:$A,I$8,SalesReport!$B:$B,BusPlanLocation!$C$7)*IF($C$9="EUR",1,START!$E$18)/-1000 -> 0 | J50: =IF(I50=0,0,I50/I$28) -> 0 | K50: =SUMIFS(SalesReport!$S:$S,SalesReport!$F:$F,$AB50,SalesReport!$A:$A,K$8,SalesReport!$B:$B,BusPlanLocation!$C$7)*IF($C$9="EUR",1,START!$E$18)/-1000 -> 0 | L50: =IF(K50=0,0,K50/K$28) -> 0 | M50: =SUMIFS(SalesReport!$S:$S,SalesReport!$F:$F,$AB50,SalesReport!$A:$A,M$8,SalesReport!$B:$B,BusPlanLocation!$C$7)*IF($C$9="EUR",1,START!$E$18)/-1000 -> 0 | N50: =IF(M50=0,0,M50/M$28) -> 0 | O50: =SUMIFS(SalesReport!$S:$S,SalesReport!$F:$F,$AB50,SalesReport!$A:$A,O$8,SalesReport!$B:$B,BusPlanLocation!$C$7)*IF($C$9="EUR",1,START!$E$18)/-1000 -> 0 | P50: =IF(O50=0,0,O50/O$28) -> 0 | Q50: =SUMIFS(SalesReport!$S:$S,SalesReport!$F:$F,$AB50,SalesReport!$A:$A,Q$8,SalesReport!$B:$B,BusPlanLocation!$C$7)*IF($C$9="EUR",1,START!$E$18)/-1000 -> 0 | R50: =IF(Q50=0,0,Q50/Q$28) -> 0 | S50: =SUMIFS(SalesReport!$S:$S,SalesReport!$F:$F,$AB50,SalesReport!$A:$A,S$8,SalesReport!$B:$B,BusPlanLocation!$C$7)*IF($C$9="EUR",1,START!$E$18)/-1000 -> 0 | T50: =IF(S50=0,0,S50/S$28) -> 0 | AA50: =IF(OR(B50=0,B50=""),"",B50&IF(COUNTIF(B$11:$B50,B50)>1,COUNTIF(B$11:$B50,B50),"")) -> M359 | AB50: Commission & Services
A51: =AA51 -> M369 | B51: M369 | C51: Material expenditure - TOTAL | D51: =VLOOKUP($AA51,Calc_INF_PrevYearEUR!$A$11:$BQ$330,HLOOKUP($C$7,Calc_INF_PrevYearEUR!$E$5:$BQ$6,2,0),0)*IF($C$9="EUR",1,START!$E$18) -> #N/A | E51: =IF(D51=0,0,D51/D$42) -> #N/A | F51: =VLOOKUP($AA51,Calc_INF_FC_EUR!$A$11:$BQ$330,HLOOKUP($C$7,Calc_INF_FC_EUR!$E$5:$BQ$6,2,0),0)*IF($C$9="EUR",1,START!$E$18)+G51 -> #N/A | G51: =+G50+G49+G48 -> 0 | I51: =I48+I49+I50 -> #REF! | J51: =IF(I51=0,0,I51/I$42) -> #REF! | K51: =K48+K49+K50 -> #REF! | L51: =IF(K51=0,0,K51/K$42) -> #REF! | M51: =M48+M49+M50 -> #REF! | N51: =IF(M51=0,0,M51/M$42) -> #REF! | O51: =O48+O49+O50 -> 0 | P51: =IF(O51=0,0,O51/O$42) -> 0 | Q51: =Q48+Q49+Q50 -> 0 | R51: =IF(Q51=0,0,Q51/Q$42) -> 0 | S51: =S48+S49+S50 -> 0 | T51: =IF(S51=0,0,S51/S$42) -> 0 | AA51: =IF(OR(B51=0,B51=""),"",B51&IF(COUNTIF(B$11:$B51,B51)>1,COUNTIF(B$11:$B51,B51),"")) -> M369
A52: =AA52 -> M399 | B52: M399 | C52: CONTRIBUTION | D52: =VLOOKUP($AA52,Calc_INF_PrevYearEUR!$A$11:$BQ$330,HLOOKUP($C$7,Calc_INF_PrevYearEUR!$E$5:$BQ$6,2,0),0)*IF($C$9="EUR",1,START!$E$18) -> #N/A | E52: =IF(D52=0,0,D52/D$42) -> #N/A | F52: =VLOOKUP($AA52,Calc_INF_FC_EUR!$A$11:$BQ$330,HLOOKUP($C$7,Calc_INF_FC_EUR!$E$5:$BQ$6,2,0),0)*IF($C$9="EUR",1,START!$E$18)+G52 -> #N/A | G52: =G42+G51 -> 0 | I52: =I42+I51 -> #REF! | J52: =IF(I52=0,0,I52/I$42) -> #REF! | K52: =K42+K51 -> #REF! | L52: =IF(K52=0,0,K52/K$42) -> #REF! | M52: =M42+M51 -> #REF! | N52: =IF(M52=0,0,M52/M$42) -> #REF! | O52: =O42+O51 -> 0 | P52: =IF(O52=0,0,O52/O$42) -> 0 | Q52: =Q42+Q51 -> 0 | R52: =IF(Q52=0,0,Q52/Q$42) -> 0 | S52: =S42+S51 -> 0 | T52: =IF(S52=0,0,S52/S$42) -> 0 | AA52: =IF(OR(B52=0,B52=""),"",B52&IF(COUNTIF(B$11:$B52,B52)>1,COUNTIF(B$11:$B52,B52),"")) -> M399
A53: =AA53 -> M405 | B53: M405 | C53: Power | D53: =VLOOKUP($AA53,Calc_INF_PrevYearEUR!$A$11:$BQ$330,HLOOKUP($C$7,Calc_INF_PrevYearEUR!$E$5:$BQ$6,2,0),0)*IF($C$9="EUR",1,START!$E$18) -> #N/A | E53: =IF(D53=0,0,D53/D$42) -> #N/A | F53: =VLOOKUP($AA53,Calc_INF_FC_EUR!$A$11:$BQ$330,HLOOKUP($C$7,Calc_INF_FC_EUR!$E$5:$BQ$6,2,0),0)*IF($C$9="EUR",1,START!$E$18)+G53 -> #N/A | I53: ='CC cost Calculations'!#REF!/START!E18*-1/1000 -> #REF! | J53: =IF(I53=0,0,I53/I$42) -> #REF! | K53: =I53 -> #REF! | L53: =IF(K53=0,0,K53/K$42) -> #REF! | M53: =I53*0.84 -> #REF! | N53: =IF(M53=0,0,M53/M$42) -> #REF! | P53: =IF(O53=0,0,O53/O$42) -> 0 | R53: =IF(Q53=0,0,Q53/Q$42) -> 0 | T53: =IF(S53=0,0,S53/S$42) -> 0 | AA53: =IF(OR(B53=0,B53=""),"",B53&IF(COUNTIF(B$11:$B53,B53)>1,COUNTIF(B$11:$B53,B53),"")) -> M405
A54: =AA54 -> M410 | B54: M410 | C54: Fuels / Steam | D54: =VLOOKUP($AA54,Calc_INF_PrevYearEUR!$A$11:$BQ$330,HLOOKUP($C$7,Calc_INF_PrevYearEUR!$E$5:$BQ$6,2,0),0)*IF($C$9="EUR",1,START!$E$18) -> #N/A | E54: =IF(D54=0,0,D54/D$42) -> #N/A | F54: =VLOOKUP($AA54,Calc_INF_FC_EUR!$A$11:$BQ$330,HLOOKUP($C$7,Calc_INF_FC_EUR!$E$5:$BQ$6,2,0),0)*IF($C$9="EUR",1,START!$E$18)+G54 -> #N/A | I54: ='CC cost Calculations'!C57/START!E18*-1/1000 -> -145448.41 | J54: =IF(I54=0,0,I54/I$42) -> #REF! | K54: =I54 -> -145448.41 | L54: =IF(K54=0,0,K54/K$42) -> #DIV/0! | M54: =K54*0.84 -> -122176.66 | N54: =IF(M54=0,0,M54/M$42) -> #DIV/0! | P54: =IF(O54=0,0,O54/O$42) -> 0 | R54: =IF(Q54=0,0,Q54/Q$42) -> 0 | T54: =IF(S54=0,0,S54/S$42) -> 0 | AA54: =IF(OR(B54=0,B54=""),"",B54&IF(COUNTIF(B$11:$B54,B54)>1,COUNTIF(B$11:$B54,B54),"")) -> M410
A55: =AA55 -> M415 | B55: M415 | C55: Water | D55: =VLOOKUP($AA55,Calc_INF_PrevYearEUR!$A$11:$BQ$330,HLOOKUP($C$7,Calc_INF_PrevYearEUR!$E$5:$BQ$6,2,0),0)*IF($C$9="EUR",1,START!$E$18) -> #N/A | E55: =IF(D55=0,0,D55/D$42) -> #N/A | F55: =VLOOKUP($AA55,Calc_INF_FC_EUR!$A$11:$BQ$330,HLOOKUP($C$7,Calc_INF_FC_EUR!$E$5:$BQ$6,2,0),0)*IF($C$9="EUR",1,START!$E$18)+G55 -> #N/A | J55: =IF(I55=0,0,I55/I$42) -> 0 | L55: =IF(K55=0,0,K55/K$42) -> 0 | N55: =IF(M55=0,0,M55/M$42) -> 0 | P55: =IF(O55=0,0,O55/O$42) -> 0 | R55: =IF(Q55=0,0,Q55/Q$42) -> 0 | T55: =IF(S55=0,0,S55/S$42) -> 0 | AA55: =IF(OR(B55=0,B55=""),"",B55&IF(COUNTIF(B$11:$B55,B55)>1,COUNTIF(B$11:$B55,B55),"")) -> M415
A56: =AA56 -> M419 | B56: M419 | C56: Energy consumption | D56: =VLOOKUP($AA56,Calc_INF_PrevYearEUR!$A$11:$BQ$330,HLOOKUP($C$7,Calc_INF_PrevYearEUR!$E$5:$BQ$6,2,0),0)*IF($C$9="EUR",1,START!$E$18) -> #N/A | E56: =IF(D56=0,0,D56/D$42) -> #N/A | F56: =VLOOKUP($AA56,Calc_INF_FC_EUR!$A$11:$BQ$330,HLOOKUP($C$7,Calc_INF_FC_EUR!$E$5:$BQ$6,2,0),0)*IF($C$9="EUR",1,START!$E$18)+G56 -> #N/A | G56: =SUM(G53:G55) -> 0 | I56: =SUM(I53:I55) -> #REF! | J56: =IF(I56=0,0,I56/I$42) -> #REF! | K56: =I56 -> #REF! | L56: =IF(K56=0,0,K56/K$42) -> #REF! | M56: =SUM(M53:M55) -> #REF! | N56: =IF(M56=0,0,M56/M$42) -> #REF! | O56: =SUM(O53:O55) -> 0 | P56: =IF(O56=0,0,O56/O$42) -> 0 | Q56: =SUM(Q53:Q55) -> 0 | R56: =IF(Q56=0,0,Q56/Q$42) -> 0 | S56: =SUM(S53:S55) -> 0 | T56: =IF(S56=0,0,S56/S$42) -> 0 | AA56: =IF(OR(B56=0,B56=""),"",B56&IF(COUNTIF(B$11:$B56,B56)>1,COUNTIF(B$11:$B56,B56),"")) -> M419
A57: =AA57 -> M450 | B57: M450 | C57: Wages | D57: =VLOOKUP($AA57,Calc_INF_PrevYearEUR!$A$11:$BQ$330,HLOOKUP($C$7,Calc_INF_PrevYearEUR!$E$5:$BQ$6,2,0),0)*IF($C$9="EUR",1,START!$E$18) -> #N/A | E57: =IF(D57=0,0,D57/D$42) -> #N/A | F57: =VLOOKUP($AA57,Calc_INF_FC_EUR!$A$11:$BQ$330,HLOOKUP($C$7,Calc_INF_FC_EUR!$E$5:$BQ$6,2,0),0)*IF($C$9="EUR",1,START!$E$18)+G57 -> #N/A | J57: =IF(I57=0,0,I57/I$42) -> 0 | L57: =IF(K57=0,0,K57/K$42) -> 0 | M57: =K57*1.2 -> 0 | N57: =IF(M57=0,0,M57/M$42) -> 0 | P57: =IF(O57=0,0,O57/O$42) -> 0 | R57: =IF(Q57=0,0,Q57/Q$42) -> 0 | T57: =IF(S57=0,0,S57/S$42) -> 0 | AA57: =IF(OR(B57=0,B57=""),"",B57&IF(COUNTIF(B$11:$B57,B57)>1,COUNTIF(B$11:$B57,B57),"")) -> M450
A58: =AA58 -> M455 | B58: M455 | C58: Social security expenses wages | D58: =VLOOKUP($AA58,Calc_INF_PrevYearEUR!$A$11:$BQ$330,HLOOKUP($C$7,Calc_INF_PrevYearEUR!$E$5:$BQ$6,2,0),0)*IF($C$9="EUR",1,START!$E$18) -> #N/A | E58: =IF(D58=0,0,D58/D$42) -> #N/A | F58: =VLOOKUP($AA58,Calc_INF_FC_EUR!$A$11:$BQ$330,HLOOKUP($C$7,Calc_INF_FC_EUR!$E$5:$BQ$6,2,0),0)*IF($C$9="EUR",1,START!$E$18)+G58 -> #N/A | I58: =IF(I57=0,0,IF($F58=0,INF_FC_EUR!$O$58/INF_FC_EUR!$O$57*I57,$F58/$F57*($F57+I57)-$F58)) -> 0 | J58: =IF(I58=0,0,I58/I$42) -> 0 | L58: =IF(K58=0,0,K58/K$42) -> 0 | M58: =K58*1.2 -> 0 | N58: =IF(M58=0,0,M58/M$42) -> 0 | O58: =IF(O57=0,0,IF($F58=0,INF_FC_EUR!$O$58/INF_FC_EUR!$O$57*O57,$F58/$F57*($F57+O57)-$F58)) -> 0 | P58: =IF(O58=0,0,O58/O$42) -> 0 | Q58: =IF(Q57=0,0,IF($F58=0,INF_FC_EUR!$O$58/INF_FC_EUR!$O$57*Q57,$F58/$F57*($F57+Q57)-$F58)) -> 0 | R58: =IF(Q58=0,0,Q58/Q$42) -> 0 | S58: =IF(S57=0,0,IF($F58=0,INF_FC_EUR!$O$58/INF_FC_EUR!$O$57*S57,$F58/$F57*($F57+S57)-$F58)) -> 0 | T58: =IF(S58=0,0,S58/S$42) -> 0 | AA58: =IF(OR(B58=0,B58=""),"",B58&IF(COUNTIF(B$11:$B58,B58)>1,COUNTIF(B$11:$B58,B58),"")) -> M455
A59: =AA59 -> M460 | B59: M460 | C59: Salaries | D59: =VLOOKUP($AA59,Calc_INF_PrevYearEUR!$A$11:$BQ$330,HLOOKUP($C$7,Calc_INF_PrevYearEUR!$E$5:$BQ$6,2,0),0)*IF($C$9="EUR",1,START!$E$18) -> #N/A | E59: =IF(D59=0,0,D59/D$42) -> #N/A | F59: =VLOOKUP($AA59,Calc_INF_FC_EUR!$A$11:$BQ$330,HLOOKUP($C$7,Calc_INF_FC_EUR!$E$5:$BQ$6,2,0),0)*IF($C$9="EUR",1,START!$E$18)+G59 -> #N/A | J59: =IF(I59=0,0,I59/I$42) -> 0 | L59: =IF(K59=0,0,K59/K$42) -> 0 | M59: =K59*1.2 -> 0 | N59: =IF(M59=0,0,M59/M$42) -> 0 | P59: =IF(O59=0,0,O59/O$42) -> 0 | R59: =IF(Q59=0,0,Q59/Q$42) -> 0 | T59: =IF(S59=0,0,S59/S$42) -> 0 | AA59: =IF(OR(B59=0,B59=""),"",B59&IF(COUNTIF(B$11:$B59,B59)>1,COUNTIF(B$11:$B59,B59),"")) -> M460
A60: =AA60 -> M465 | B60: M465 | C60: Social security expenses salaries | D60: =VLOOKUP($AA60,Calc_INF_PrevYearEUR!$A$11:$BQ$330,HLOOKUP($C$7,Calc_INF_PrevYearEUR!$E$5:$BQ$6,2,0),0)*IF($C$9="EUR",1,START!$E$18) -> #N/A | E60: =IF(D60=0,0,D60/D$42) -> #N/A | F60: =VLOOKUP($AA60,Calc_INF_FC_EUR!$A$11:$BQ$330,HLOOKUP($C$7,Calc_INF_FC_EUR!$E$5:$BQ$6,2,0),0)*IF($C$9="EUR",1,START!$E$18)+G60 -> #N/A | I60: =IF(I59=0,0,IF($F60=0,INF_FC_EUR!$O$60/INF_FC_EUR!$O$59*I59,$F60/$F59*($F59+I59)-$F60)) -> 0 | J60: =IF(I60=0,0,I60/I$42) -> 0 | L60: =IF(K60=0,0,K60/K$42) -> 0 | N60: =IF(M60=0,0,M60/M$42) -> 0 | O60: =IF(O59=0,0,IF($F60=0,INF_FC_EUR!$O$60/INF_FC_EUR!$O$59*O59,$F60/$F59*($F59+O59)-$F60)) -> 0 | P60: =IF(O60=0,0,O60/O$42) -> 0 | Q60: =IF(Q59=0,0,IF($F60=0,INF_FC_EUR!$O$60/INF_FC_EUR!$O$59*Q59,$F60/$F59*($F59+Q59)-$F60)) -> 0 | R60: =IF(Q60=0,0,Q60/Q$42) -> 0 | S60: =IF(S59=0,0,IF($F60=0,INF_FC_EUR!$O$60/INF_FC_EUR!$O$59*S59,$F60/$F59*($F59+S59)-$F60)) -> 0 | T60: =IF(S60=0,0,S60/S$42) -> 0 | AA60: =IF(OR(B60=0,B60=""),"",B60&IF(COUNTIF(B$11:$B60,B60)>1,COUNTIF(B$11:$B60,B60),"")) -> M465
A61: =AA61 -> M470 | B61: M470 | C61: Severance expenses | D61: =VLOOKUP($AA61,Calc_INF_PrevYearEUR!$A$11:$BQ$330,HLOOKUP($C$7,Calc_INF_PrevYearEUR!$E$5:$BQ$6,2,0),0)*IF($C$9="EUR",1,START!$E$18) -> #N/A | E61: =IF(D61=0,0,D61/D$42) -> #N/A | F61: =VLOOKUP($AA61,Calc_INF_FC_EUR!$A$11:$BQ$330,HLOOKUP($C$7,Calc_INF_FC_EUR!$E$5:$BQ$6,2,0),0)*IF($C$9="EUR",1,START!$E$18)+G61 -> #N/A | J61: =IF(I61=0,0,I61/I$42) -> 0 | L61: =IF(K61=0,0,K61/K$42) -> 0 | N61: =IF(M61=0,0,M61/M$42) -> 0 | P61: =IF(O61=0,0,O61/O$42) -> 0 | R61: =IF(Q61=0,0,Q61/Q$42) -> 0 | T61: =IF(S61=0,0,S61/S$42) -> 0 | AA61: =IF(OR(B61=0,B61=""),"",B61&IF(COUNTIF(B$11:$B61,B61)>1,COUNTIF(B$11:$B61,B61),"")) -> M470
A62: =AA62 -> M475 | B62: M475 | C62: Pension expenses | D62: =VLOOKUP($AA62,Calc_INF_PrevYearEUR!$A$11:$BQ$330,HLOOKUP($C$7,Calc_INF_PrevYearEUR!$E$5:$BQ$6,2,0),0)*IF($C$9="EUR",1,START!$E$18) -> #N/A | E62: =IF(D62=0,0,D62/D$42) -> #N/A | F62: =VLOOKUP($AA62,Calc_INF_FC_EUR!$A$11:$BQ$330,HLOOKUP($C$7,Calc_INF_FC_EUR!$E$5:$BQ$6,2,0),0)*IF($C$9="EUR",1,START!$E$18)+G62 -> #N/A | J62: =IF(I62=0,0,I62/I$42) -> 0 | L62: =IF(K62=0,0,K62/K$42) -> 0 | N62: =IF(M62=0,0,M62/M$42) -> 0 | P62: =IF(O62=0,0,O62/O$42) -> 0 | R62: =IF(Q62=0,0,Q62/Q$42) -> 0 | T62: =IF(S62=0,0,S62/S$42) -> 0 | AA62: =IF(OR(B62=0,B62=""),"",B62&IF(COUNTIF(B$11:$B62,B62)>1,COUNTIF(B$11:$B62,B62),"")) -> M475
A63: =AA63 -> M480 | B63: M480 | C63: Other benefit costs | D63: =VLOOKUP($AA63,Calc_INF_PrevYearEUR!$A$11:$BQ$330,HLOOKUP($C$7,Calc_INF_PrevYearEUR!$E$5:$BQ$6,2,0),0)*IF($C$9="EUR",1,START!$E$18) -> #N/A | E63: =IF(D63=0,0,D63/D$42) -> #N/A | F63: =VLOOKUP($AA63,Calc_INF_FC_EUR!$A$11:$BQ$330,HLOOKUP($C$7,Calc_INF_FC_EUR!$E$5:$BQ$6,2,0),0)*IF($C$9="EUR",1,START!$E$18)+G63 -> #N/A | I63: =I57+I59*0.2 -> 0 | J63: =IF(I63=0,0,I63/I$42) -> 0 | K63: -1 | L63: =IF(K63=0,0,K63/K$42) -> #DIV/0! | N63: =IF(M63=0,0,M63/M$42) -> 0 | P63: =IF(O63=0,0,O63/O$42) -> 0 | R63: =IF(Q63=0,0,Q63/Q$42) -> 0 | T63: =IF(S63=0,0,S63/S$42) -> 0 | AA63: =IF(OR(B63=0,B63=""),"",B63&IF(COUNTIF(B$11:$B63,B63)>1,COUNTIF(B$11:$B63,B63),"")) -> M480
A64: =AA64 -> M489 | B64: M489 | C64: Personnel expenses | D64: =VLOOKUP($AA64,Calc_INF_PrevYearEUR!$A$11:$BQ$330,HLOOKUP($C$7,Calc_INF_PrevYearEUR!$E$5:$BQ$6,2,0),0)*IF($C$9="EUR",1,START!$E$18) -> #N/A | E64: =IF(D64=0,0,D64/D$42) -> #N/A | F64: =VLOOKUP($AA64,Calc_INF_FC_EUR!$A$11:$BQ$330,HLOOKUP($C$7,Calc_INF_FC_EUR!$E$5:$BQ$6,2,0),0)*IF($C$9="EUR",1,START!$E$18)+G64 -> #N/A | G64: =SUM(G57:G63) -> 0 | I64: ='CC cost Calculations'!C68/START!E18*-1/1000 -> -3102.528 | J64: =IF(I64=0,0,I64/I$42) -> #REF! | K64: =I64 -> -3102.528 | L64: =IF(K64=0,0,K64/K$42) -> #DIV/0! | M64: =I64*0.84 -> -2606.1235 | N64: =IF(M64=0,0,M64/M$42) -> #DIV/0! | O64: =SUM(O57:O63) -> 0 | P64: =IF(O64=0,0,O64/O$42) -> 0 | Q64: =SUM(Q57:Q63) -> 0 | R64: =IF(Q64=0,0,Q64/Q$42) -> 0 | S64: =SUM(S57:S63) -> 0 | T64: =IF(S64=0,0,S64/S$42) -> 0 | AA64: =IF(OR(B64=0,B64=""),"",B64&IF(COUNTIF(B$11:$B64,B64)>1,COUNTIF(B$11:$B64,B64),"")) -> M489
A65: =AA65 -> M509 | B65: M509 | C65: Maintenance costs | D65: =VLOOKUP($AA65,Calc_INF_PrevYearEUR!$A$11:$BQ$330,HLOOKUP($C$7,Calc_INF_PrevYearEUR!$E$5:$BQ$6,2,0),0)*IF($C$9="EUR",1,START!$E$18) -> #N/A | E65: =IF(D65=0,0,D65/D$42) -> #N/A | F65: =VLOOKUP($AA65,Calc_INF_FC_EUR!$A$11:$BQ$330,HLOOKUP($C$7,Calc_INF_FC_EUR!$E$5:$BQ$6,2,0),0)*IF($C$9="EUR",1,START!$E$18)+G65 -> #N/A | I65: ='CC cost Calculations'!C77/START!E18*-1/1000 -> -52 | J65: =IF(I65=0,0,I65/I$42) -> #REF! | K65: =I65 -> -52 | L65: =IF(K65=0,0,K65/K$42) -> #DIV/0! | M65: =K65 -> -52 | N65: =IF(M65=0,0,M65/M$42) -> #DIV/0! | P65: =IF(O65=0,0,O65/O$42) -> 0 | R65: =IF(Q65=0,0,Q65/Q$42) -> 0 | T65: =IF(S65=0,0,S65/S$42) -> 0 | AA65: =IF(OR(B65=0,B65=""),"",B65&IF(COUNTIF(B$11:$B65,B65)>1,COUNTIF(B$11:$B65,B65),"")) -> M509
A66: =AA66 -> M529 | B66: M529 | C66: Environmental costs | D66: =VLOOKUP($AA66,Calc_INF_PrevYearEUR!$A$11:$BQ$330,HLOOKUP($C$7,Calc_INF_PrevYearEUR!$E$5:$BQ$6,2,0),0)*IF($C$9="EUR",1,START!$E$18) -> #N/A | E66: =IF(D66=0,0,D66/D$42) -> #N/A | F66: =VLOOKUP($AA66,Calc_INF_FC_EUR!$A$11:$BQ$330,HLOOKUP($C$7,Calc_INF_FC_EUR!$E$5:$BQ$6,2,0),0)*IF($C$9="EUR",1,START!$E$18)+G66 -> #N/A | J66: =IF(I66=0,0,I66/I$42) -> 0 | L66: =IF(K66=0,0,K66/K$42) -> 0 | N66: =IF(M66=0,0,M66/M$42) -> 0 | P66: =IF(O66=0,0,O66/O$42) -> 0 | R66: =IF(Q66=0,0,Q66/Q$42) -> 0 | T66: =IF(S66=0,0,S66/S$42) -> 0 | AA66: =IF(OR(B66=0,B66=""),"",B66&IF(COUNTIF(B$11:$B66,B66)>1,COUNTIF(B$11:$B66,B66),"")) -> M529
A67: =AA67 -> M604 | B67: M604 | C67: Third party services/leased pers. production | D67: =VLOOKUP($AA67,Calc_INF_PrevYearEUR!$A$11:$BQ$330,HLOOKUP($C$7,Calc_INF_PrevYearEUR!$E$5:$BQ$6,2,0),0)*IF($C$9="EUR",1,START!$E$18) -> #N/A | E67: =IF(D67=0,0,D67/D$42) -> #N/A | F67: =VLOOKUP($AA67,Calc_INF_FC_EUR!$A$11:$BQ$330,HLOOKUP($C$7,Calc_INF_FC_EUR!$E$5:$BQ$6,2,0),0)*IF($C$9="EUR",1,START!$E$18)+G67 -> #N/A | I67: ='CC cost Calculations'!C83/START!E18*-1/1000 -> -23.333333 | J67: =IF(I67=0,0,I67/I$42) -> #REF! | K67: =I67 -> -23.333333 | L67: =IF(K67=0,0,K67/K$42) -> #DIV/0! | M67: =K67*0.84 -> -19.6 | N67: =IF(M67=0,0,M67/M$42) -> #DIV/0! | P67: =IF(O67=0,0,O67/O$42) -> 0 | R67: =IF(Q67=0,0,Q67/Q$42) -> 0 | T67: =IF(S67=0,0,S67/S$42) -> 0 | AA67: =IF(OR(B67=0,B67=""),"",B67&IF(COUNTIF(B$11:$B67,B67)>1,COUNTIF(B$11:$B67,B67),"")) -> M604
A68: =AA68 -> M605 | B68: M605 | C68: Third party services/leased pers. excl. prod. | D68: =VLOOKUP($AA68,Calc_INF_PrevYearEUR!$A$11:$BQ$330,HLOOKUP($C$7,Calc_INF_PrevYearEUR!$E$5:$BQ$6,2,0),0)*IF($C$9="EUR",1,START!$E$18) -> #N/A | E68: =IF(D68=0,0,D68/D$42) -> #N/A | F68: =VLOOKUP($AA68,Calc_INF_FC_EUR!$A$11:$BQ$330,HLOOKUP($C$7,Calc_INF_FC_EUR!$E$5:$BQ$6,2,0),0)*IF($C$9="EUR",1,START!$E$18)+G68 -> #N/A | I68: 0 | J68: =IF(I68=0,0,I68/I$42) -> 0 | K68: =I68 -> 0 | L68: =IF(K68=0,0,K68/K$42) -> 0 | M68: =K68*0.84 -> 0 | N68: =IF(M68=0,0,M68/M$42) -> 0 | P68: =IF(O68=0,0,O68/O$42) -> 0 | R68: =IF(Q68=0,0,Q68/Q$42) -> 0 | T68: =IF(S68=0,0,S68/S$42) -> 0 | AA68: =IF(OR(B68=0,B68=""),"",B68&IF(COUNTIF(B$11:$B68,B68)>1,COUNTIF(B$11:$B68,B68),"")) -> M605
A69: =AA69 -> M610 | B69: M610 | C69: Rental charges | D69: =VLOOKUP($AA69,Calc_INF_PrevYearEUR!$A$11:$BQ$330,HLOOKUP($C$7,Calc_INF_PrevYearEUR!$E$5:$BQ$6,2,0),0)*IF($C$9="EUR",1,START!$E$18) -> #N/A | E69: =IF(D69=0,0,D69/D$42) -> #N/A | F69: =VLOOKUP($AA69,Calc_INF_FC_EUR!$A$11:$BQ$330,HLOOKUP($C$7,Calc_INF_FC_EUR!$E$5:$BQ$6,2,0),0)*IF($C$9="EUR",1,START!$E$18)+G69 -> #N/A | I69: 0 | J69: =IF(I69=0,0,I69/I$42) -> 0 | K69: =I69 -> 0 | L69: =IF(K69=0,0,K69/K$42) -> 0 | M69: =K69*0.84 -> 0 | N69: =IF(M69=0,0,M69/M$42) -> 0 | P69: =IF(O69=0,0,O69/O$42) -> 0 | R69: =IF(Q69=0,0,Q69/Q$42) -> 0 | T69: =IF(S69=0,0,S69/S$42) -> 0 | AA69: =IF(OR(B69=0,B69=""),"",B69&IF(COUNTIF(B$11:$B69,B69)>1,COUNTIF(B$11:$B69,B69),"")) -> M610
A70: =AA70 -> M615 | B70: M615 | C70: Travel expenses | D70: =VLOOKUP($AA70,Calc_INF_PrevYearEUR!$A$11:$BQ$330,HLOOKUP($C$7,Calc_INF_PrevYearEUR!$E$5:$BQ$6,2,0),0)*IF($C$9="EUR",1,START!$E$18) -> #N/A | E70: =IF(D70=0,0,D70/D$42) -> #N/A | F70: =VLOOKUP($AA70,Calc_INF_FC_EUR!$A$11:$BQ$330,HLOOKUP($C$7,Calc_INF_FC_EUR!$E$5:$BQ$6,2,0),0)*IF($C$9="EUR",1,START!$E$18)+G70 -> #N/A | I70: ='CC cost Calculations'!C89/START!E18/1000*-1 -> -26.666667 | J70: =IF(I70=0,0,I70/I$42) -> #REF! | K70: =I70 -> -26.666667 | L70: =IF(K70=0,0,K70/K$42) -> #DIV/0! | M70: =K70*0.84 -> -22.4 | N70: =IF(M70=0,0,M70/M$42) -> #DIV/0! | P70: =IF(O70=0,0,O70/O$42) -> 0 | R70: =IF(Q70=0,0,Q70/Q$42) -> 0 | T70: =IF(S70=0,0,S70/S$42) -> 0 | AA70: =IF(OR(B70=0,B70=""),"",B70&IF(COUNTIF(B$11:$B70,B70)>1,COUNTIF(B$11:$B70,B70),"")) -> M615
A71: =AA71 -> M620 | B71: M620 | C71: Communication exp. | D71: =VLOOKUP($AA71,Calc_INF_PrevYearEUR!$A$11:$BQ$330,HLOOKUP($C$7,Calc_INF_PrevYearEUR!$E$5:$BQ$6,2,0),0)*IF($C$9="EUR",1,START!$E$18) -> #N/A | E71: =IF(D71=0,0,D71/D$42) -> #N/A | F71: =VLOOKUP($AA71,Calc_INF_FC_EUR!$A$11:$BQ$330,HLOOKUP($C$7,Calc_INF_FC_EUR!$E$5:$BQ$6,2,0),0)*IF($C$9="EUR",1,START!$E$18)+G71 -> #N/A | I71: ='CC cost Calculations'!C90/START!E18/1000*-1 -> -2.2666667 | J71: =IF(I71=0,0,I71/I$42) -> #REF! | K71: =I71 -> -2.2666667 | L71: =IF(K71=0,0,K71/K$42) -> #DIV/0! | M71: =K71*0.84 -> -1.904 | N71: =IF(M71=0,0,M71/M$42) -> #DIV/0! | P71: =IF(O71=0,0,O71/O$42) -> 0 | R71: =IF(Q71=0,0,Q71/Q$42) -> 0 | T71: =IF(S71=0,0,S71/S$42) -> 0 | AA71: =IF(OR(B71=0,B71=""),"",B71&IF(COUNTIF(B$11:$B71,B71)>1,COUNTIF(B$11:$B71,B71),"")) -> M620
A72: =AA72 -> M625 | B72: M625 | C72: Legal/audit/consultation costs | D72: =VLOOKUP($AA72,Calc_INF_PrevYearEUR!$A$11:$BQ$330,HLOOKUP($C$7,Calc_INF_PrevYearEUR!$E$5:$BQ$6,2,0),0)*IF($C$9="EUR",1,START!$E$18) -> #N/A | E72: =IF(D72=0,0,D72/D$42) -> #N/A | F72: =VLOOKUP($AA72,Calc_INF_FC_EUR!$A$11:$BQ$330,HLOOKUP($C$7,Calc_INF_FC_EUR!$E$5:$BQ$6,2,0),0)*IF($C$9="EUR",1,START!$E$18)+G72 -> #N/A | I72: 0 | J72: =IF(I72=0,0,I72/I$42) -> 0 | K72: =I72 -> 0 | L72: =IF(K72=0,0,K72/K$42) -> 0 | M72: =K72*0.84 -> 0 | N72: =IF(M72=0,0,M72/M$42) -> 0 | P72: =IF(O72=0,0,O72/O$42) -> 0 | R72: =IF(Q72=0,0,Q72/Q$42) -> 0 | T72: =IF(S72=0,0,S72/S$42) -> 0 | AA72: =IF(OR(B72=0,B72=""),"",B72&IF(COUNTIF(B$11:$B72,B72)>1,COUNTIF(B$11:$B72,B72),"")) -> M625
A73: =AA73 -> M630 | B73: M630 | C73: Advertising/publicity costs | D73: =VLOOKUP($AA73,Calc_INF_PrevYearEUR!$A$11:$BQ$330,HLOOKUP($C$7,Calc_INF_PrevYearEUR!$E$5:$BQ$6,2,0),0)*IF($C$9="EUR",1,START!$E$18) -> #N/A | E73: =IF(D73=0,0,D73/D$42) -> #N/A | F73: =VLOOKUP($AA73,Calc_INF_FC_EUR!$A$11:$BQ$330,HLOOKUP($C$7,Calc_INF_FC_EUR!$E$5:$BQ$6,2,0),0)*IF($C$9="EUR",1,START!$E$18)+G73 -> #N/A | I73: 0 | J73: =IF(I73=0,0,I73/I$42) -> 0 | K73: =I73 -> 0 | L73: =IF(K73=0,0,K73/K$42) -> 0 | M73: =K73*0.84 -> 0 | N73: =IF(M73=0,0,M73/M$42) -> 0 | P73: =IF(O73=0,0,O73/O$42) -> 0 | R73: =IF(Q73=0,0,Q73/Q$42) -> 0 | T73: =IF(S73=0,0,S73/S$42) -> 0 | AA73: =IF(OR(B73=0,B73=""),"",B73&IF(COUNTIF(B$11:$B73,B73)>1,COUNTIF(B$11:$B73,B73),"")) -> M630
A74: =AA74 -> M635 | B74: M635 | C74: Insurances (excl. transport insurance) | D74: =VLOOKUP($AA74,Calc_INF_PrevYearEUR!$A$11:$BQ$330,HLOOKUP($C$7,Calc_INF_PrevYearEUR!$E$5:$BQ$6,2,0),0)*IF($C$9="EUR",1,START!$E$18) -> #N/A | E74: =IF(D74=0,0,D74/D$42) -> #N/A | F74: =VLOOKUP($AA74,Calc_INF_FC_EUR!$A$11:$BQ$330,HLOOKUP($C$7,Calc_INF_FC_EUR!$E$5:$BQ$6,2,0),0)*IF($C$9="EUR",1,START!$E$18)+G74 -> #N/A | I74: 0 | J74: =IF(I74=0,0,I74/I$42) -> 0 | K74: =I74 -> 0 | L74: =IF(K74=0,0,K74/K$42) -> 0 | M74: =K74*0.84 -> 0 | N74: =IF(M74=0,0,M74/M$42) -> 0 | P74: =IF(O74=0,0,O74/O$42) -> 0 | R74: =IF(Q74=0,0,Q74/Q$42) -> 0 | T74: =IF(S74=0,0,S74/S$42) -> 0 | AA74: =IF(OR(B74=0,B74=""),"",B74&IF(COUNTIF(B$11:$B74,B74)>1,COUNTIF(B$11:$B74,B74),"")) -> M635
A75: =AA75 -> M640 | B75: M640 | C75: IT-costs ext. | D75: =VLOOKUP($AA75,Calc_INF_PrevYearEUR!$A$11:$BQ$330,HLOOKUP($C$7,Calc_INF_PrevYearEUR!$E$5:$BQ$6,2,0),0)*IF($C$9="EUR",1,START!$E$18) -> #N/A | E75: =IF(D75=0,0,D75/D$42) -> #N/A | F75: =VLOOKUP($AA75,Calc_INF_FC_EUR!$A$11:$BQ$330,HLOOKUP($C$7,Calc_INF_FC_EUR!$E$5:$BQ$6,2,0),0)*IF($C$9="EUR",1,START!$E$18)+G75 -> #N/A | I75: ='CC cost Calculations'!C83/START!E18/1000*-1 -> -23.333333 | J75: =IF(I75=0,0,I75/I$42) -> #REF! | K75: =I75 -> -23.333333 | L75: =IF(K75=0,0,K75/K$42) -> #DIV/0! | M75: =K75*0.84 -> -19.6 | N75: =IF(M75=0,0,M75/M$42) -> #DIV/0! | P75: =IF(O75=0,0,O75/O$42) -> 0 | R75: =IF(Q75=0,0,Q75/Q$42) -> 0 | T75: =IF(S75=0,0,S75/S$42) -> 0 | AA75: =IF(OR(B75=0,B75=""),"",B75&IF(COUNTIF(B$11:$B75,B75)>1,COUNTIF(B$11:$B75,B75),"")) -> M640
A76: =AA76 -> M641 | B76: M641 | C76: IT-costs affil. | D76: =VLOOKUP($AA76,Calc_INF_PrevYearEUR!$A$11:$BQ$330,HLOOKUP($C$7,Calc_INF_PrevYearEUR!$E$5:$BQ$6,2,0),0)*IF($C$9="EUR",1,START!$E$18) -> #N/A | E76: =IF(D76=0,0,D76/D$42) -> #N/A | F76: =VLOOKUP($AA76,Calc_INF_FC_EUR!$A$11:$BQ$330,HLOOKUP($C$7,Calc_INF_FC_EUR!$E$5:$BQ$6,2,0),0)*IF($C$9="EUR",1,START!$E$18)+G76 -> #N/A | I76: ='CC cost Calculations'!#REF!/START!E18/1000*-1 -> #REF! | J76: =IF(I76=0,0,I76/I$42) -> #REF! | K76: =I76 -> #REF! | L76: =IF(K76=0,0,K76/K$42) -> #REF! | M76: =K76*0.84 -> #REF! | N76: =IF(M76=0,0,M76/M$42) -> #REF! | P76: =IF(O76=0,0,O76/O$42) -> 0 | R76: =IF(Q76=0,0,Q76/Q$42) -> 0 | T76: =IF(S76=0,0,S76/S$42) -> 0 | AA76: =IF(OR(B76=0,B76=""),"",B76&IF(COUNTIF(B$11:$B76,B76)>1,COUNTIF(B$11:$B76,B76),"")) -> M641
A77: =AA77 -> M645 | B77: M645 | C77: Holding/Division/Admin. costs | D77: =VLOOKUP($AA77,Calc_INF_PrevYearEUR!$A$11:$BQ$330,HLOOKUP($C$7,Calc_INF_PrevYearEUR!$E$5:$BQ$6,2,0),0)*IF($C$9="EUR",1,START!$E$18) -> #N/A | E77: =IF(D77=0,0,D77/D$42) -> #N/A | F77: =VLOOKUP($AA77,Calc_INF_FC_EUR!$A$11:$BQ$330,HLOOKUP($C$7,Calc_INF_FC_EUR!$E$5:$BQ$6,2,0),0)*IF($C$9="EUR",1,START!$E$18)+G77 -> #N/A | I77: ='CC cost Calculations'!#REF!/START!E18/1000*-1 -> #REF! | J77: =IF(I77=0,0,I77/I$42) -> #REF! | K77: =I77 -> #REF! | L77: =IF(K77=0,0,K77/K$42) -> #REF! | M77: =K77*0.84 -> #REF! | N77: =IF(M77=0,0,M77/M$42) -> #REF! | P77: =IF(O77=0,0,O77/O$42) -> 0 | R77: =IF(Q77=0,0,Q77/Q$42) -> 0 | T77: =IF(S77=0,0,S77/S$42) -> 0 | AA77: =IF(OR(B77=0,B77=""),"",B77&IF(COUNTIF(B$11:$B77,B77)>1,COUNTIF(B$11:$B77,B77),"")) -> M645
A78: =AA78 -> M650 | B78: M650 | C78: Bank charges | D78: =VLOOKUP($AA78,Calc_INF_PrevYearEUR!$A$11:$BQ$330,HLOOKUP($C$7,Calc_INF_PrevYearEUR!$E$5:$BQ$6,2,0),0)*IF($C$9="EUR",1,START!$E$18) -> #N/A | E78: =IF(D78=0,0,D78/D$42) -> #N/A | F78: =VLOOKUP($AA78,Calc_INF_FC_EUR!$A$11:$BQ$330,HLOOKUP($C$7,Calc_INF_FC_EUR!$E$5:$BQ$6,2,0),0)*IF($C$9="EUR",1,START!$E$18)+G78 -> #N/A | I78: 0 | J78: =IF(I78=0,0,I78/I$42) -> 0 | K78: =I78 -> 0 | L78: =IF(K78=0,0,K78/K$42) -> 0 | M78: =K78*0.84 -> 0 | N78: =IF(M78=0,0,M78/M$42) -> 0 | P78: =IF(O78=0,0,O78/O$42) -> 0 | R78: =IF(Q78=0,0,Q78/Q$42) -> 0 | T78: =IF(S78=0,0,S78/S$42) -> 0 | AA78: =IF(OR(B78=0,B78=""),"",B78&IF(COUNTIF(B$11:$B78,B78)>1,COUNTIF(B$11:$B78,B78),"")) -> M650
A79: =AA79 -> M655 | B79: M655 | C79: Loss from fx-differences excl. financing | D79: =VLOOKUP($AA79,Calc_INF_PrevYearEUR!$A$11:$BQ$330,HLOOKUP($C$7,Calc_INF_PrevYearEUR!$E$5:$BQ$6,2,0),0)*IF($C$9="EUR",1,START!$E$18) -> #N/A | E79: =IF(D79=0,0,D79/D$42) -> #N/A | F79: =VLOOKUP($AA79,Calc_INF_FC_EUR!$A$11:$BQ$330,HLOOKUP($C$7,Calc_INF_FC_EUR!$E$5:$BQ$6,2,0),0)*IF($C$9="EUR",1,START!$E$18)+G79 -> #N/A | I79: 0 | J79: =IF(I79=0,0,I79/I$42) -> 0 | K79: =I79 -> 0 | L79: =IF(K79=0,0,K79/K$42) -> 0 | M79: =K79*0.84 -> 0 | N79: =IF(M79=0,0,M79/M$42) -> 0 | P79: =IF(O79=0,0,O79/O$42) -> 0 | R79: =IF(Q79=0,0,Q79/Q$42) -> 0 | T79: =IF(S79=0,0,S79/S$42) -> 0 | AA79: =IF(OR(B79=0,B79=""),"",B79&IF(COUNTIF(B$11:$B79,B79)>1,COUNTIF(B$11:$B79,B79),"")) -> M655
A80: =AA80 -> M660 | B80: M660 | C80: Other overhead costs | D80: =VLOOKUP($AA80,Calc_INF_PrevYearEUR!$A$11:$BQ$330,HLOOKUP($C$7,Calc_INF_PrevYearEUR!$E$5:$BQ$6,2,0),0)*IF($C$9="EUR",1,START!$E$18) -> #N/A | E80: =IF(D80=0,0,D80/D$42) -> #N/A | F80: =VLOOKUP($AA80,Calc_INF_FC_EUR!$A$11:$BQ$330,HLOOKUP($C$7,Calc_INF_FC_EUR!$E$5:$BQ$6,2,0),0)*IF($C$9="EUR",1,START!$E$18)+G80 -> #N/A | I80: ='CC cost Calculations'!C92/START!E18/1000*-1 -> -26.666667 | J80: =IF(I80=0,0,I80/I$42) -> #REF! | K80: =I80 -> -26.666667 | L80: =IF(K80=0,0,K80/K$42) -> #DIV/0! | M80: =K80*0.84 -> -22.4 | N80: =IF(M80=0,0,M80/M$42) -> #DIV/0! | P80: =IF(O80=0,0,O80/O$42) -> 0 | R80: =IF(Q80=0,0,Q80/Q$42) -> 0 | T80: =IF(S80=0,0,S80/S$42) -> 0 | AA80: =IF(OR(B80=0,B80=""),"",B80&IF(COUNTIF(B$11:$B80,B80)>1,COUNTIF(B$11:$B80,B80),"")) -> M660
A81: =AA81 -> M665 | B81: M665 | C81: Taxes and duties | D81: =VLOOKUP($AA81,Calc_INF_PrevYearEUR!$A$11:$BQ$330,HLOOKUP($C$7,Calc_INF_PrevYearEUR!$E$5:$BQ$6,2,0),0)*IF($C$9="EUR",1,START!$E$18) -> #N/A | E81: =IF(D81=0,0,D81/D$42) -> #N/A | F81: =VLOOKUP($AA81,Calc_INF_FC_EUR!$A$11:$BQ$330,HLOOKUP($C$7,Calc_INF_FC_EUR!$E$5:$BQ$6,2,0),0)*IF($C$9="EUR",1,START!$E$18)+G81 -> #N/A | I81: 0 | J81: =IF(I81=0,0,I81/I$42) -> 0 | K81: =I81 -> 0 | L81: =IF(K81=0,0,K81/K$42) -> 0 | M81: =K81*0.84 -> 0 | N81: =IF(M81=0,0,M81/M$42) -> 0 | P81: =IF(O81=0,0,O81/O$42) -> 0 | R81: =IF(Q81=0,0,Q81/Q$42) -> 0 | T81: =IF(S81=0,0,S81/S$42) -> 0 | AA81: =IF(OR(B81=0,B81=""),"",B81&IF(COUNTIF(B$11:$B81,B81)>1,COUNTIF(B$11:$B81,B81),"")) -> M665
A82: =AA82 -> M689 | B82: M689 | C82: Other expenditures | D82: =VLOOKUP($AA82,Calc_INF_PrevYearEUR!$A$11:$BQ$330,HLOOKUP($C$7,Calc_INF_PrevYearEUR!$E$5:$BQ$6,2,0),0)*IF($C$9="EUR",1,START!$E$18) -> #N/A | E82: =IF(D82=0,0,D82/D$42) -> #N/A | F82: =VLOOKUP($AA82,Calc_INF_FC_EUR!$A$11:$BQ$330,HLOOKUP($C$7,Calc_INF_FC_EUR!$E$5:$BQ$6,2,0),0)*IF($C$9="EUR",1,START!$E$18)+G82 -> #N/A | G82: =SUM(G67:G81) -> 0 | I82: =SUM(I67:I81) -> #REF! | J82: =IF(I82=0,0,I82/I$42) -> #REF! | K82: =I82 -> #REF! | L82: =IF(K82=0,0,K82/K$42) -> #REF! | M82: =K82*0.84 -> #REF! | N82: =IF(M82=0,0,M82/M$42) -> #REF! | O82: =SUM(O67:O81) -> 0 | P82: =IF(O82=0,0,O82/O$42) -> 0 | Q82: =SUM(Q67:Q81) -> 0 | R82: =IF(Q82=0,0,Q82/Q$42) -> 0 | S82: =SUM(S67:S81) -> 0 | T82: =IF(S82=0,0,S82/S$42) -> 0 | AA82: =IF(OR(B82=0,B82=""),"",B82&IF(COUNTIF(B$11:$B82,B82)>1,COUNTIF(B$11:$B82,B82),"")) -> M689
A83: =AA83 -> M705 | B83: M705 | C83: Capitalization of own work | D83: =VLOOKUP($AA83,Calc_INF_PrevYearEUR!$A$11:$BQ$330,HLOOKUP($C$7,Calc_INF_PrevYearEUR!$E$5:$BQ$6,2,0),0)*IF($C$9="EUR",1,START!$E$18) -> #N/A | E83: =IF(D83=0,0,D83/D$42) -> #N/A | F83: =VLOOKUP($AA83,Calc_INF_FC_EUR!$A$11:$BQ$330,HLOOKUP($C$7,Calc_INF_FC_EUR!$E$5:$BQ$6,2,0),0)*IF($C$9="EUR",1,START!$E$18)+G83 -> #N/A | J83: =IF(I83=0,0,I83/I$42) -> 0 | L83: =IF(K83=0,0,K83/K$42) -> 0 | N83: =IF(M83=0,0,M83/M$42) -> 0 | P83: =IF(O83=0,0,O83/O$42) -> 0 | R83: =IF(Q83=0,0,Q83/Q$42) -> 0 | T83: =IF(S83=0,0,S83/S$42) -> 0 | AA83: =IF(OR(B83=0,B83=""),"",B83&IF(COUNTIF(B$11:$B83,B83)>1,COUNTIF(B$11:$B83,B83),"")) -> M705
A84: =AA84 -> M710 | B84: M710 | C84: Income disp.& write-up FA, excl. FinA | D84: =VLOOKUP($AA84,Calc_INF_PrevYearEUR!$A$11:$BQ$330,HLOOKUP($C$7,Calc_INF_PrevYearEUR!$E$5:$BQ$6,2,0),0)*IF($C$9="EUR",1,START!$E$18) -> #N/A | E84: =IF(D84=0,0,D84/D$42) -> #N/A | F84: =VLOOKUP($AA84,Calc_INF_FC_EUR!$A$11:$BQ$330,HLOOKUP($C$7,Calc_INF_FC_EUR!$E$5:$BQ$6,2,0),0)*IF($C$9="EUR",1,START!$E$18)+G84 -> #N/A | J84: =IF(I84=0,0,I84/I$42) -> 0 | L84: =IF(K84=0,0,K84/K$42) -> 0 | N84: =IF(M84=0,0,M84/M$42) -> 0 | P84: =IF(O84=0,0,O84/O$42) -> 0 | R84: =IF(Q84=0,0,Q84/Q$42) -> 0 | T84: =IF(S84=0,0,S84/S$42) -> 0 | AA84: =IF(OR(B84=0,B84=""),"",B84&IF(COUNTIF(B$11:$B84,B84)>1,COUNTIF(B$11:$B84,B84),"")) -> M710
A85: =AA85 -> M711 | B85: M711 | C85: Income disp.& write-up FA, excl. FinA aff. | D85: =VLOOKUP($AA85,Calc_INF_PrevYearEUR!$A$11:$BQ$330,HLOOKUP($C$7,Calc_INF_PrevYearEUR!$E$5:$BQ$6,2,0),0)*IF($C$9="EUR",1,START!$E$18) -> #N/A | E85: =IF(D85=0,0,D85/D$42) -> #N/A | F85: =VLOOKUP($AA85,Calc_INF_FC_EUR!$A$11:$BQ$330,HLOOKUP($C$7,Calc_INF_FC_EUR!$E$5:$BQ$6,2,0),0)*IF($C$9="EUR",1,START!$E$18)+G85 -> #N/A | J85: =IF(I85=0,0,I85/I$42) -> 0 | L85: =IF(K85=0,0,K85/K$42) -> 0 | N85: =IF(M85=0,0,M85/M$42) -> 0 | P85: =IF(O85=0,0,O85/O$42) -> 0 | R85: =IF(Q85=0,0,Q85/Q$42) -> 0 | T85: =IF(S85=0,0,S85/S$42) -> 0 | AA85: =IF(OR(B85=0,B85=""),"",B85&IF(COUNTIF(B$11:$B85,B85)>1,COUNTIF(B$11:$B85,B85),"")) -> M711
A86: =AA86 -> M715 | B86: M715 | C86: Reversal of provisions | D86: =VLOOKUP($AA86,Calc_INF_PrevYearEUR!$A$11:$BQ$330,HLOOKUP($C$7,Calc_INF_PrevYearEUR!$E$5:$BQ$6,2,0),0)*IF($C$9="EUR",1,START!$E$18) -> #N/A | E86: =IF(D86=0,0,D86/D$42) -> #N/A | F86: =VLOOKUP($AA86,Calc_INF_FC_EUR!$A$11:$BQ$330,HLOOKUP($C$7,Calc_INF_FC_EUR!$E$5:$BQ$6,2,0),0)*IF($C$9="EUR",1,START!$E$18)+G86 -> #N/A | J86: =IF(I86=0,0,I86/I$42) -> 0 | L86: =IF(K86=0,0,K86/K$42) -> 0 | N86: =IF(M86=0,0,M86/M$42) -> 0 | P86: =IF(O86=0,0,O86/O$42) -> 0 | R86: =IF(Q86=0,0,Q86/Q$42) -> 0 | T86: =IF(S86=0,0,S86/S$42) -> 0 | AA86: =IF(OR(B86=0,B86=""),"",B86&IF(COUNTIF(B$11:$B86,B86)>1,COUNTIF(B$11:$B86,B86),"")) -> M715
A87: =AA87 -> M720 | B87: M720 | C87: Profits from fx-differences excl. finance | D87: =VLOOKUP($AA87,Calc_INF_PrevYearEUR!$A$11:$BQ$330,HLOOKUP($C$7,Calc_INF_PrevYearEUR!$E$5:$BQ$6,2,0),0)*IF($C$9="EUR",1,START!$E$18) -> #N/A | E87: =IF(D87=0,0,D87/D$42) -> #N/A | F87: =VLOOKUP($AA87,Calc_INF_FC_EUR!$A$11:$BQ$330,HLOOKUP($C$7,Calc_INF_FC_EUR!$E$5:$BQ$6,2,0),0)*IF($C$9="EUR",1,START!$E$18)+G87 -> #N/A | J87: =IF(I87=0,0,I87/I$42) -> 0 | L87: =IF(K87=0,0,K87/K$42) -> 0 | N87: =IF(M87=0,0,M87/M$42) -> 0 | P87: =IF(O87=0,0,O87/O$42) -> 0 | R87: =IF(Q87=0,0,Q87/Q$42) -> 0 | T87: =IF(S87=0,0,S87/S$42) -> 0 | AA87: =IF(OR(B87=0,B87=""),"",B87&IF(COUNTIF(B$11:$B87,B87)>1,COUNTIF(B$11:$B87,B87),"")) -> M720
A88: =AA88 -> M725 | B88: M725 | C88: Other operating income | D88: =VLOOKUP($AA88,Calc_INF_PrevYearEUR!$A$11:$BQ$330,HLOOKUP($C$7,Calc_INF_PrevYearEUR!$E$5:$BQ$6,2,0),0)*IF($C$9="EUR",1,START!$E$18) -> #N/A | E88: =IF(D88=0,0,D88/D$42) -> #N/A | F88: =VLOOKUP($AA88,Calc_INF_FC_EUR!$A$11:$BQ$330,HLOOKUP($C$7,Calc_INF_FC_EUR!$E$5:$BQ$6,2,0),0)*IF($C$9="EUR",1,START!$E$18)+G88 -> #N/A | J88: =IF(I88=0,0,I88/I$42) -> 0 | L88: =IF(K88=0,0,K88/K$42) -> 0 | N88: =IF(M88=0,0,M88/M$42) -> 0 | P88: =IF(O88=0,0,O88/O$42) -> 0 | R88: =IF(Q88=0,0,Q88/Q$42) -> 0 | T88: =IF(S88=0,0,S88/S$42) -> 0 | AA88: =IF(OR(B88=0,B88=""),"",B88&IF(COUNTIF(B$11:$B88,B88)>1,COUNTIF(B$11:$B88,B88),"")) -> M725
A89: =AA89 -> M726 | B89: M726 | C89: Other operating income affil. | D89: =VLOOKUP($AA89,Calc_INF_PrevYearEUR!$A$11:$BQ$330,HLOOKUP($C$7,Calc_INF_PrevYearEUR!$E$5:$BQ$6,2,0),0)*IF($C$9="EUR",1,START!$E$18) -> #N/A | E89: =IF(D89=0,0,D89/D$42) -> #N/A | F89: =VLOOKUP($AA89,Calc_INF_FC_EUR!$A$11:$BQ$330,HLOOKUP($C$7,Calc_INF_FC_EUR!$E$5:$BQ$6,2,0),0)*IF($C$9="EUR",1,START!$E$18)+G89 -> #N/A | J89: =IF(I89=0,0,I89/I$42) -> 0 | L89: =IF(K89=0,0,K89/K$42) -> 0 | N89: =IF(M89=0,0,M89/M$42) -> 0 | P89: =IF(O89=0,0,O89/O$42) -> 0 | R89: =IF(Q89=0,0,Q89/Q$42) -> 0 | T89: =IF(S89=0,0,S89/S$42) -> 0 | AA89: =IF(OR(B89=0,B89=""),"",B89&IF(COUNTIF(B$11:$B89,B89)>1,COUNTIF(B$11:$B89,B89),"")) -> M726
A90: =AA90 -> M739 | B90: M739 | C90: Other operating income - TOTAL | D90: =VLOOKUP($AA90,Calc_INF_PrevYearEUR!$A$11:$BQ$330,HLOOKUP($C$7,Calc_INF_PrevYearEUR!$E$5:$BQ$6,2,0),0)*IF($C$9="EUR",1,START!$E$18) -> #N/A | E90: =IF(D90=0,0,D90/D$42) -> #N/A | F90: =VLOOKUP($AA90,Calc_INF_FC_EUR!$A$11:$BQ$330,HLOOKUP($C$7,Calc_INF_FC_EUR!$E$5:$BQ$6,2,0),0)*IF($C$9="EUR",1,START!$E$18)+G90 -> #N/A | G90: =SUM(G83:G89) -> 0 | I90: =SUM(I83:I89) -> 0 | J90: =IF(I90=0,0,I90/I$42) -> 0 | K90: =SUM(K83:K89) -> 0 | L90: =IF(K90=0,0,K90/K$42) -> 0 | M90: =SUM(M83:M89) -> 0 | N90: =IF(M90=0,0,M90/M$42) -> 0 | O90: =SUM(O83:O89) -> 0 | P90: =IF(O90=0,0,O90/O$42) -> 0 | Q90: =SUM(Q83:Q89) -> 0 | R90: =IF(Q90=0,0,Q90/Q$42) -> 0 | S90: =SUM(S83:S89) -> 0 | T90: =IF(S90=0,0,S90/S$42) -> 0 | AA90: =IF(OR(B90=0,B90=""),"",B90&IF(COUNTIF(B$11:$B90,B90)>1,COUNTIF(B$11:$B90,B90),"")) -> M739
A91: =AA91 -> M759 | B91: M759 | C91: Leasing | D91: =VLOOKUP($AA91,Calc_INF_PrevYearEUR!$A$11:$BQ$330,HLOOKUP($C$7,Calc_INF_PrevYearEUR!$E$5:$BQ$6,2,0),0)*IF($C$9="EUR",1,START!$E$18) -> #N/A | E91: =IF(D91=0,0,D91/D$42) -> #N/A | F91: =VLOOKUP($AA91,Calc_INF_FC_EUR!$A$11:$BQ$330,HLOOKUP($C$7,Calc_INF_FC_EUR!$E$5:$BQ$6,2,0),0)*IF($C$9="EUR",1,START!$E$18)+G91 -> #N/A | J91: =IF(I91=0,0,I91/I$42) -> 0 | L91: =IF(K91=0,0,K91/K$42) -> 0 | N91: =IF(M91=0,0,M91/M$42) -> 0 | P91: =IF(O91=0,0,O91/O$42) -> 0 | R91: =IF(Q91=0,0,Q91/Q$42) -> 0 | T91: =IF(S91=0,0,S91/S$42) -> 0 | AA91: =IF(OR(B91=0,B91=""),"",B91&IF(COUNTIF(B$11:$B91,B91)>1,COUNTIF(B$11:$B91,B91),"")) -> M759
A92: =AA92 -> M769 | B92: M769 | C92: EBITDA | D92: =VLOOKUP($AA92,Calc_INF_PrevYearEUR!$A$11:$BQ$330,HLOOKUP($C$7,Calc_INF_PrevYearEUR!$E$5:$BQ$6,2,0),0)*IF($C$9="EUR",1,START!$E$18) -> #N/A | E92: =IF(D92=0,0,D92/D$42) -> #N/A | F92: =VLOOKUP($AA92,Calc_INF_FC_EUR!$A$11:$BQ$330,HLOOKUP($C$7,Calc_INF_FC_EUR!$E$5:$BQ$6,2,0),0)*IF($C$9="EUR",1,START!$E$18)+G92 -> #N/A | G92: =G52+G64+G56+G65+G66+G82+G90+G91 -> 0 | I92: =I52+I64+I56+I65+I66+I82+I90+I91 -> #REF! | J92: =IF(I92=0,0,I92/I$42) -> #REF! | K92: =K52+K64+K56+K65+K66+K82+K90+K91 -> #REF! | L92: =IF(K92=0,0,K92/K$42) -> #REF! | M92: =M52+M64+M56+M65+M66+M82+M90+M91 -> #REF! | N92: =IF(M92=0,0,M92/M$42) -> #REF! | O92: =O52+O64+O56+O65+O66+O82+O90+O91 -> 0 | P92: =IF(O92=0,0,O92/O$42) -> 0 | Q92: =Q52+Q64+Q56+Q65+Q66+Q82+Q90+Q91 -> 0 | R92: =IF(Q92=0,0,Q92/Q$42) -> 0 | S92: =S52+S64+S56+S65+S66+S82+S90+S91 -> 0 | T92: =IF(S92=0,0,S92/S$42) -> 0 | V92: =(I92+K92+M92+O92+Q92+S92)/6 -> #REF! | AA92: =IF(OR(B92=0,B92=""),"",B92&IF(COUNTIF(B$11:$B92,B92)>1,COUNTIF(B$11:$B92,B92),"")) -> M769
A93: =AA93 -> M775 | B93: M775 | C93: Ordinary depr. and amort. excl. goodwill | D93: =VLOOKUP($AA93,Calc_INF_PrevYearEUR!$A$11:$BQ$330,HLOOKUP($C$7,Calc_INF_PrevYearEUR!$E$5:$BQ$6,2,0),0)*IF($C$9="EUR",1,START!$E$18) -> #N/A | E93: =IF(D93=0,0,D93/D$42) -> #N/A | F93: =VLOOKUP($AA93,Calc_INF_FC_EUR!$A$11:$BQ$330,HLOOKUP($C$7,Calc_INF_FC_EUR!$E$5:$BQ$6,2,0),0)*IF($C$9="EUR",1,START!$E$18)+G93 -> #N/A | J93: =IF(I93=0,0,I93/I$42) -> 0 | L93: =IF(K93=0,0,K93/K$42) -> 0 | N93: =IF(M93=0,0,M93/M$42) -> 0 | P93: =IF(O93=0,0,O93/O$42) -> 0 | R93: =IF(Q93=0,0,Q93/Q$42) -> 0 | T93: =IF(S93=0,0,S93/S$42) -> 0 | AA93: =IF(OR(B93=0,B93=""),"",B93&IF(COUNTIF(B$11:$B93,B93)>1,COUNTIF(B$11:$B93,B93),"")) -> M775
A94: =AA94 -> M780 | B94: M780 | C94: Ordinary amort. of goodwill | D94: =VLOOKUP($AA94,Calc_INF_PrevYearEUR!$A$11:$BQ$330,HLOOKUP($C$7,Calc_INF_PrevYearEUR!$E$5:$BQ$6,2,0),0)*IF($C$9="EUR",1,START!$E$18) -> #N/A | E94: =IF(D94=0,0,D94/D$42) -> #N/A | F94: =VLOOKUP($AA94,Calc_INF_FC_EUR!$A$11:$BQ$330,HLOOKUP($C$7,Calc_INF_FC_EUR!$E$5:$BQ$6,2,0),0)*IF($C$9="EUR",1,START!$E$18)+G94 -> #N/A | J94: =IF(I94=0,0,I94/I$42) -> 0 | L94: =IF(K94=0,0,K94/K$42) -> 0 | N94: =IF(M94=0,0,M94/M$42) -> 0 | P94: =IF(O94=0,0,O94/O$42) -> 0 | R94: =IF(Q94=0,0,Q94/Q$42) -> 0 | T94: =IF(S94=0,0,S94/S$42) -> 0 | AA94: =IF(OR(B94=0,B94=""),"",B94&IF(COUNTIF(B$11:$B94,B94)>1,COUNTIF(B$11:$B94,B94),"")) -> M780
A95: =AA95 -> M785 | B95: M785 | C95: Extraordinary depr. and amortization | D95: =VLOOKUP($AA95,Calc_INF_PrevYearEUR!$A$11:$BQ$330,HLOOKUP($C$7,Calc_INF_PrevYearEUR!$E$5:$BQ$6,2,0),0)*IF($C$9="EUR",1,START!$E$18) -> #N/A | E95: =IF(D95=0,0,D95/D$42) -> #N/A | F95: =VLOOKUP($AA95,Calc_INF_FC_EUR!$A$11:$BQ$330,HLOOKUP($C$7,Calc_INF_FC_EUR!$E$5:$BQ$6,2,0),0)*IF($C$9="EUR",1,START!$E$18)+G95 -> #N/A | I95: ='INVESTMENT per Year'!H21/3.5/-1000 -> -860.95238 | J95: =IF(I95=0,0,I95/I$42) -> #REF! | K95: ='INVESTMENT per Year'!H21/3.5/-1000 -> -860.95238 | L95: =IF(K95=0,0,K95/K$42) -> #DIV/0! | M95: ='INVESTMENT per Year'!H21/3.5/-1000 -> -860.95238 | N95: =IF(M95=0,0,M95/M$42) -> #DIV/0! | P95: =IF(O95=0,0,O95/O$42) -> 0 | R95: =IF(Q95=0,0,Q95/Q$42) -> 0 | T95: =IF(S95=0,0,S95/S$42) -> 0 | AA95: =IF(OR(B95=0,B95=""),"",B95&IF(COUNTIF(B$11:$B95,B95)>1,COUNTIF(B$11:$B95,B95),"")) -> M785
A96: =AA96 -> M787 | B96: M787 | C96: Depr. CurrA (exceeding convent. depr.) | D96: =VLOOKUP($AA96,Calc_INF_PrevYearEUR!$A$11:$BQ$330,HLOOKUP($C$7,Calc_INF_PrevYearEUR!$E$5:$BQ$6,2,0),0)*IF($C$9="EUR",1,START!$E$18) -> #N/A | E96: =IF(D96=0,0,D96/D$42) -> #N/A | F96: =VLOOKUP($AA96,Calc_INF_FC_EUR!$A$11:$BQ$330,HLOOKUP($C$7,Calc_INF_FC_EUR!$E$5:$BQ$6,2,0),0)*IF($C$9="EUR",1,START!$E$18)+G96 -> #N/A | J96: =IF(I96=0,0,I96/I$42) -> 0 | L96: =IF(K96=0,0,K96/K$42) -> 0 | N96: =IF(M96=0,0,M96/M$42) -> 0 | P96: =IF(O96=0,0,O96/O$42) -> 0 | R96: =IF(Q96=0,0,Q96/Q$42) -> 0 | T96: =IF(S96=0,0,S96/S$42) -> 0 | AA96: =IF(OR(B96=0,B96=""),"",B96&IF(COUNTIF(B$11:$B96,B96)>1,COUNTIF(B$11:$B96,B96),"")) -> M787
A97: =AA97 -> M789 | B97: M789 | C97: Depreciation | D97: =VLOOKUP($AA97,Calc_INF_PrevYearEUR!$A$11:$BQ$330,HLOOKUP($C$7,Calc_INF_PrevYearEUR!$E$5:$BQ$6,2,0),0)*IF($C$9="EUR",1,START!$E$18) -> #N/A | E97: =IF(D97=0,0,D97/D$42) -> #N/A | F97: =VLOOKUP($AA97,Calc_INF_FC_EUR!$A$11:$BQ$330,HLOOKUP($C$7,Calc_INF_FC_EUR!$E$5:$BQ$6,2,0),0)*IF($C$9="EUR",1,START!$E$18)+G97 -> #N/A | G97: =SUM(G93:G96) -> 0 | I97: =SUM(I93:I96) -> -860.95238 | J97: =IF(I97=0,0,I97/I$42) -> #REF! | K97: =SUM(K93:K96) -> -860.95238 | L97: =IF(K97=0,0,K97/K$42) -> #DIV/0! | M97: =SUM(M93:M96) -> -860.95238 | N97: =IF(M97=0,0,M97/M$42) -> #DIV/0! | O97: =SUM(O93:O96) -> 0 | P97: =IF(O97=0,0,O97/O$42) -> 0 | Q97: =SUM(Q93:Q96) -> 0 | R97: =IF(Q97=0,0,Q97/Q$42) -> 0 | S97: =SUM(S93:S96) -> 0 | T97: =IF(S97=0,0,S97/S$42) -> 0 | AA97: =IF(OR(B97=0,B97=""),"",B97&IF(COUNTIF(B$11:$B97,B97)>1,COUNTIF(B$11:$B97,B97),"")) -> M789
A98: =AA98 -> M799 | B98: M799 | C98: EBIT | D98: =VLOOKUP($AA98,Calc_INF_PrevYearEUR!$A$11:$BQ$330,HLOOKUP($C$7,Calc_INF_PrevYearEUR!$E$5:$BQ$6,2,0),0)*IF($C$9="EUR",1,START!$E$18) -> #N/A | E98: =IF(D98=0,0,D98/D$42) -> #N/A | F98: =VLOOKUP($AA98,Calc_INF_FC_EUR!$A$11:$BQ$330,HLOOKUP($C$7,Calc_INF_FC_EUR!$E$5:$BQ$6,2,0),0)*IF($C$9="EUR",1,START!$E$18)+G98 -> #N/A | G98: =G92+G97 -> 0 | I98: =I92+I97 -> #REF! | J98: =IF(I98=0,0,I98/I$42) -> #REF! | K98: =K92+K97 -> #REF! | L98: =IF(K98=0,0,K98/K$42) -> #REF! | M98: =M92+M97 -> #REF! | N98: =IF(M98=0,0,M98/M$42) -> #REF! | O98: =O92+O97 -> 0 | P98: =IF(O98=0,0,O98/O$42) -> 0 | Q98: =Q92+Q97 -> 0 | R98: =IF(Q98=0,0,Q98/Q$42) -> 0 | S98: =S92+S97 -> 0 | T98: =IF(S98=0,0,S98/S$42) -> 0 | AA98: =IF(OR(B98=0,B98=""),"",B98&IF(COUNTIF(B$11:$B98,B98)>1,COUNTIF(B$11:$B98,B98),"")) -> M799
A99: =AA99 -> M800 | B99: M800 | C99: Income investments (dividends) | D99: =VLOOKUP($AA99,Calc_INF_PrevYearEUR!$A$11:$BQ$330,HLOOKUP($C$7,Calc_INF_PrevYearEUR!$E$5:$BQ$6,2,0),0)*IF($C$9="EUR",1,START!$E$18) -> #N/A | E99: =IF(D99=0,0,D99/D$42) -> #N/A | F99: =VLOOKUP($AA99,Calc_INF_FC_EUR!$A$11:$BQ$330,HLOOKUP($C$7,Calc_INF_FC_EUR!$E$5:$BQ$6,2,0),0)*IF($C$9="EUR",1,START!$E$18)+G99 -> #N/A | J99: =IF(I99=0,0,I99/I$42) -> 0 | L99: =IF(K99=0,0,K99/K$42) -> 0 | N99: =IF(M99=0,0,M99/M$42) -> 0 | P99: =IF(O99=0,0,O99/O$42) -> 0 | R99: =IF(Q99=0,0,Q99/Q$42) -> 0 | T99: =IF(S99=0,0,S99/S$42) -> 0 | AA99: =IF(OR(B99=0,B99=""),"",B99&IF(COUNTIF(B$11:$B99,B99)>1,COUNTIF(B$11:$B99,B99),"")) -> M800
A100: =AA100 -> M801 | B100: M801 | C100: Income investments (dividends) affil. | D100: =VLOOKUP($AA100,Calc_INF_PrevYearEUR!$A$11:$BQ$330,HLOOKUP($C$7,Calc_INF_PrevYearEUR!$E$5:$BQ$6,2,0),0)*IF($C$9="EUR",1,START!$E$18) -> #N/A | E100: =IF(D100=0,0,D100/D$42) -> #N/A | F100: =VLOOKUP($AA100,Calc_INF_FC_EUR!$A$11:$BQ$330,HLOOKUP($C$7,Calc_INF_FC_EUR!$E$5:$BQ$6,2,0),0)*IF($C$9="EUR",1,START!$E$18)+G100 -> #N/A | J100: =IF(I100=0,0,I100/I$42) -> 0 | L100: =IF(K100=0,0,K100/K$42) -> 0 | N100: =IF(M100=0,0,M100/M$42) -> 0 | P100: =IF(O100=0,0,O100/O$42) -> 0 | R100: =IF(Q100=0,0,Q100/Q$42) -> 0 | T100: =IF(S100=0,0,S100/S$42) -> 0 | AA100: =IF(OR(B100=0,B100=""),"",B100&IF(COUNTIF(B$11:$B100,B100)>1,COUNTIF(B$11:$B100,B100),"")) -> M801
A101: =AA101 -> M805 | B101: M805 | C101: Income other securities/investm. | D101: =VLOOKUP($AA101,Calc_INF_PrevYearEUR!$A$11:$BQ$330,HLOOKUP($C$7,Calc_INF_PrevYearEUR!$E$5:$BQ$6,2,0),0)*IF($C$9="EUR",1,START!$E$18) -> #N/A | E101: =IF(D101=0,0,D101/D$42) -> #N/A | F101: =VLOOKUP($AA101,Calc_INF_FC_EUR!$A$11:$BQ$330,HLOOKUP($C$7,Calc_INF_FC_EUR!$E$5:$BQ$6,2,0),0)*IF($C$9="EUR",1,START!$E$18)+G101 -> #N/A | J101: =IF(I101=0,0,I101/I$42) -> 0 | L101: =IF(K101=0,0,K101/K$42) -> 0 | N101: =IF(M101=0,0,M101/M$42) -> 0 | P101: =IF(O101=0,0,O101/O$42) -> 0 | R101: =IF(Q101=0,0,Q101/Q$42) -> 0 | T101: =IF(S101=0,0,S101/S$42) -> 0 | AA101: =IF(OR(B101=0,B101=""),"",B101&IF(COUNTIF(B$11:$B101,B101)>1,COUNTIF(B$11:$B101,B101),"")) -> M805
A102: =AA102 -> M806 | B102: M806 | C102: Income other securities/investm. affil. | D102: =VLOOKUP($AA102,Calc_INF_PrevYearEUR!$A$11:$BQ$330,HLOOKUP($C$7,Calc_INF_PrevYearEUR!$E$5:$BQ$6,2,0),0)*IF($C$9="EUR",1,START!$E$18) -> #N/A | E102: =IF(D102=0,0,D102/D$42) -> #N/A | F102: =VLOOKUP($AA102,Calc_INF_FC_EUR!$A$11:$BQ$330,HLOOKUP($C$7,Calc_INF_FC_EUR!$E$5:$BQ$6,2,0),0)*IF($C$9="EUR",1,START!$E$18)+G102 -> #N/A | J102: =IF(I102=0,0,I102/I$42) -> 0 | L102: =IF(K102=0,0,K102/K$42) -> 0 | N102: =IF(M102=0,0,M102/M$42) -> 0 | P102: =IF(O102=0,0,O102/O$42) -> 0 | R102: =IF(Q102=0,0,Q102/Q$42) -> 0 | T102: =IF(S102=0,0,S102/S$42) -> 0 | AA102: =IF(OR(B102=0,B102=""),"",B102&IF(COUNTIF(B$11:$B102,B102)>1,COUNTIF(B$11:$B102,B102),"")) -> M806
A103: =AA103 -> M810 | B103: M810 | C103: Income from long term loans | D103: =VLOOKUP($AA103,Calc_INF_PrevYearEUR!$A$11:$BQ$330,HLOOKUP($C$7,Calc_INF_PrevYearEUR!$E$5:$BQ$6,2,0),0)*IF($C$9="EUR",1,START!$E$18) -> #N/A | E103: =IF(D103=0,0,D103/D$42) -> #N/A | F103: =VLOOKUP($AA103,Calc_INF_FC_EUR!$A$11:$BQ$330,HLOOKUP($C$7,Calc_INF_FC_EUR!$E$5:$BQ$6,2,0),0)*IF($C$9="EUR",1,START!$E$18)+G103 -> #N/A | J103: =IF(I103=0,0,I103/I$42) -> 0 | L103: =IF(K103=0,0,K103/K$42) -> 0 | N103: =IF(M103=0,0,M103/M$42) -> 0 | P103: =IF(O103=0,0,O103/O$42) -> 0 | R103: =IF(Q103=0,0,Q103/Q$42) -> 0 | T103: =IF(S103=0,0,S103/S$42) -> 0 | AA103: =IF(OR(B103=0,B103=""),"",B103&IF(COUNTIF(B$11:$B103,B103)>1,COUNTIF(B$11:$B103,B103),"")) -> M810
A104: =AA104 -> M811 | B104: M811 | C104: Income from long term loans affil. | D104: =VLOOKUP($AA104,Calc_INF_PrevYearEUR!$A$11:$BQ$330,HLOOKUP($C$7,Calc_INF_PrevYearEUR!$E$5:$BQ$6,2,0),0)*IF($C$9="EUR",1,START!$E$18) -> #N/A | E104: =IF(D104=0,0,D104/D$42) -> #N/A | F104: =VLOOKUP($AA104,Calc_INF_FC_EUR!$A$11:$BQ$330,HLOOKUP($C$7,Calc_INF_FC_EUR!$E$5:$BQ$6,2,0),0)*IF($C$9="EUR",1,START!$E$18)+G104 -> #N/A | J104: =IF(I104=0,0,I104/I$42) -> 0 | L104: =IF(K104=0,0,K104/K$42) -> 0 | N104: =IF(M104=0,0,M104/M$42) -> 0 | P104: =IF(O104=0,0,O104/O$42) -> 0 | R104: =IF(Q104=0,0,Q104/Q$42) -> 0 | T104: =IF(S104=0,0,S104/S$42) -> 0 | AA104: =IF(OR(B104=0,B104=""),"",B104&IF(COUNTIF(B$11:$B104,B104)>1,COUNTIF(B$11:$B104,B104),"")) -> M811
A105: =AA105 -> M815 | B105: M815 | C105: Other interest income | D105: =VLOOKUP($AA105,Calc_INF_PrevYearEUR!$A$11:$BQ$330,HLOOKUP($C$7,Calc_INF_PrevYearEUR!$E$5:$BQ$6,2,0),0)*IF($C$9="EUR",1,START!$E$18) -> #N/A | E105: =IF(D105=0,0,D105/D$42) -> #N/A | F105: =VLOOKUP($AA105,Calc_INF_FC_EUR!$A$11:$BQ$330,HLOOKUP($C$7,Calc_INF_FC_EUR!$E$5:$BQ$6,2,0),0)*IF($C$9="EUR",1,START!$E$18)+G105 -> #N/A | J105: =IF(I105=0,0,I105/I$42) -> 0 | L105: =IF(K105=0,0,K105/K$42) -> 0 | N105: =IF(M105=0,0,M105/M$42) -> 0 | P105: =IF(O105=0,0,O105/O$42) -> 0 | R105: =IF(Q105=0,0,Q105/Q$42) -> 0 | T105: =IF(S105=0,0,S105/S$42) -> 0 | AA105: =IF(OR(B105=0,B105=""),"",B105&IF(COUNTIF(B$11:$B105,B105)>1,COUNTIF(B$11:$B105,B105),"")) -> M815
...

Sheet EBITDA-Tracking
B4: EBITDA-Tracking | C4: Years | O4: Notes
C5: =BusPlanLocation!I8 -> 2021 | D5: =BusPlanLocation!K8 -> 2022 | E5: =BusPlanLocation!M8 -> 2023 | F5: =BusPlanLocation!O8 -> 2024 | G5: =BusPlanLocation!Q8 -> 2025 | H5: =BusPlanLocation!S8 -> 2026 | I5: =H5+1 -> 2027 | J5: =I5+1 -> 2028 | K5: =J5+1 -> 2029 | L5: =K5+1 -> 2030 | M5: Sum | N5: Mean | O5: can be adjusted to need
C6: from "BusPlanLocation" | I6: to be planned additional
B7: EBITDA | C7: =+BusPlanLocation!I92 -> #REF! | D7: =+BusPlanLocation!K92 -> #REF! | E7: =+BusPlanLocation!M92 -> #REF! | F7: =+BusPlanLocation!O92 -> 0 | G7: =+BusPlanLocation!Q92 -> 0 | H7: =BusPlanLocation!S92 -> 0 | M7: =SUM(C7:L7) -> #REF! | N7: =AVERAGE(C7:L7) -> #REF!
C8: =IF(C7<>0,1,0) -> #REF! | D8: =IF(D7<>0,1,0) -> #REF! | E8: =IF(E7<>0,1,0) -> #REF! | F8: =IF(F7<>0,1,0) -> 0 | G8: =IF(G7<>0,1,0) -> 0 | H8: =IF(H7<>0,1,0) -> 0 | I8: =IF(I7="",0,1) -> 0 | J8: =IF(J7="",0,1) -> 0 | K8: =IF(K7="",0,1) -> 0 | L8: =IF(L7="",0,1) -> 0 | M8: =SUM(C8:L8) -> #REF!
B10: total investment | N10: ='INVESTMENT per Year'!N21 -> 3640000 | O10: see sheet Investment per year
B12: Pay back periode in years | N12: =IFERROR(N10/N7/1000,0) -> 0
B14: Depreciation (EUR) | C14: ='INVESTMENT per Year'!H31*C8 -> #REF! | D14: ='INVESTMENT per Year'!I31*D8 -> #REF! | E14: ='INVESTMENT per Year'!J31*E8 -> #REF! | F14: ='INVESTMENT per Year'!K31*F8 -> 0 | G14: ='INVESTMENT per Year'!L31*G8 -> 0 | H14: =IF($N$10-SUM($C14:G14)>G14,G14,$N$10-SUM($C14:G14)) -> #REF! | I14: =IF($N$10-SUM($C14:H14)>H14,H14,$N$10-SUM($C14:H14)) -> #REF! | J14: =IF($N$10-SUM($C14:I14)>I14,I14,$N$10-SUM($C14:I14)) -> #REF! | K14: =IF($N$10-SUM($C14:J14)>J14,J14,$N$10-SUM($C14:J14)) -> #REF! | L14: =IF($N$10-SUM($C14:K14)>K14,K14,$N$10-SUM($C14:K14)) -> #REF! | M14: =SUMPRODUCT(C8:L8,C14:L14)/1000 -> #REF! | N14: ='INVESTMENT per Year'!H25/1000 -> 860.95238 | O14: see sheet investment per year
B16: EBIT | M16: =N7-(N14) -> #REF!
B18: Return on Capital employed | M18: =M16/M14 -> #REF!
B22: planned depreciation (Years) | N22: =PP_Form!D52 -> 3.5 | O22: see PP-Form
B23: Value depeciated | N23: =M14*1000/N10 -> #REF! | O23: Depreciation divided by tot. Invest
B24: Number of years depreciated | N24: =N22*N23 -> #REF!

Sheet SalesReport
A1: Period | B1: Supplier | C1: INTERNAL Sub-Supplier | D1: EXTERNAL Sub-Supplier from list | E1: EXTERNAL Sub-Supplier free entry | F1: Business | G1: Quality | H1: Origin country | I1: INTERNAL Customer | J1: EXTERNAL Customer from list | K1: EXTERNAL Customer free entry | L1: Plan QTY in tons | M1: ASP in EUR/ t | N1: APP in EUR/ t | O1: AFP outbound in EUR/ t | P1: AFP inbound in EUR/ t | Q1: Realized QTY in tons | R1: Revenue | S1: Purchase | T1: Freight | U1: ASP | V1: APP | W1: AFP | X1: GM | Y1: PM | Z1: GM Act. | AA1: PM Act. | AB1: Type | AC1: Type II | AD1: Type III | AE1: Type IV | AF1: Type V
A2: 2021 | B2: 166101 Bornova | D2: Own Collection | E2: System Operator | F2: Collection | G2: PET 98 / 02 | H2: Turkey (TR) | K2: Others | L2: ='CC cost Calculations'!#REF! -> #REF! | Q2: =IF(L2="","",L2) -> #REF! | R2: =IF(Q2="","",Q2*M2) -> #REF! | S2: =IF(Q2="","",Q2*(N2+P2)) -> #REF! | T2: =IF(Q2="","",Q2*O2) -> #REF! | U2: =IF(Q2="","",R2/Q2) -> #REF! | V2: =IF(Q2="","",S2/Q2) -> #REF! | W2: =IF(Q2="","",T2/Q2) -> #REF! | X2: =IF(Q2="","",U2-V2) -> #REF! | Y2: =IF(Q2="","",U2-V2-W2) -> #REF! | Z2: =IF(Q2="","",R2-S2) -> #REF! | AA2: =IF(Q2="","",R2-S2-T2) -> #REF! | AB2: =IF(G2="","",VLOOKUP(G2,Qualities!$A$2:$B$156,2,0)) -> Plastics | AC2: =IF(AB2="","",VLOOKUP(AB2,QualityType!$A$2:$B$16,2,0)) -> Plastics | AD2: =D2&AC2 -> Own CollectionPlastics | AE2: =IF(I2="",IF(AND(J2="",K2=""),"",F2&"External"),IF(COUNTIF(BaseData!$B$2:$B$45,I2)=1,F2&"Consolidation intra-divisional",F2&"Group")) -> CollectionExternal | AF2: =IF(A2="","",F2&IF(I2<>"","aff","ext")) -> Collectionext
A3: 2021 | B3: 166101 Bornova | D3: Own Collection | E3: System Operator | F3: Collection | G3: Glass, white | H3: Turkey (TR) | K3: Others | L3: ='CC cost Calculations'!#REF! -> #REF! | Q3: =IF(L3="","",L3) -> #REF! | R3: =IF(Q3="","",Q3*M3) -> #REF! | S3: =IF(Q3="","",Q3*(N3+P3)) -> #REF! | T3: =IF(Q3="","",Q3*O3) -> #REF! | U3: =IF(Q3="","",R3/Q3) -> #REF! | V3: =IF(Q3="","",S3/Q3) -> #REF! | W3: =IF(Q3="","",T3/Q3) -> #REF! | X3: =IF(Q3="","",U3-V3) -> #REF! | Y3: =IF(Q3="","",U3-V3-W3) -> #REF! | Z3: =IF(Q3="","",R3-S3) -> #REF! | AA3: =IF(Q3="","",R3-S3-T3) -> #REF! | AB3: =IF(G3="","",VLOOKUP(G3,Qualities!$A$2:$B$156,2,0)) -> Glass | AC3: =IF(AB3="","",VLOOKUP(AB3,QualityType!$A$2:$B$16,2,0)) -> Glass | AD3: =D3&AC3 -> Own CollectionGlass | AE3: =IF(I3="",IF(AND(J3="",K3=""),"",F3&"External"),IF(COUNTIF(BaseData!$B$2:$B$45,I3)=1,F3&"Consolidation intra-divisional",F3&"Group")) -> CollectionExternal | AF3: =IF(A3="","",F3&IF(I3<>"","aff","ext")) -> Collectionext
A4: 2021 | B4: 166101 Bornova | D4: Own Collection | E4: System Operator | F4: Collection | G4: Aluminium | H4: Turkey (TR) | K4: Others | L4: ='CC cost Calculations'!#REF! -> #REF! | Q4: =IF(L4="","",L4) -> #REF! | R4: =IF(Q4="","",Q4*M4) -> #REF! | S4: =IF(Q4="","",Q4*(N4+P4)) -> #REF! | T4: =IF(Q4="","",Q4*O4) -> #REF! | U4: =IF(Q4="","",R4/Q4) -> #REF! | V4: =IF(Q4="","",S4/Q4) -> #REF! | W4: =IF(Q4="","",T4/Q4) -> #REF! | X4: =IF(Q4="","",U4-V4) -> #REF! | Y4: =IF(Q4="","",U4-V4-W4) -> #REF! | Z4: =IF(Q4="","",R4-S4) -> #REF! | AA4: =IF(Q4="","",R4-S4-T4) -> #REF! | AB4: =IF(G4="","",VLOOKUP(G4,Qualities!$A$2:$B$156,2,0)) -> Metals | AC4: =IF(AB4="","",VLOOKUP(AB4,QualityType!$A$2:$B$16,2,0)) -> Metals | AD4: =D4&AC4 -> Own CollectionMetals | AE4: =IF(I4="",IF(AND(J4="",K4=""),"",F4&"External"),IF(COUNTIF(BaseData!$B$2:$B$45,I4)=1,F4&"Consolidation intra-divisional",F4&"Group")) -> CollectionExternal | AF4: =IF(A4="","",F4&IF(I4<>"","aff","ext")) -> Collectionext
A5: 2021 | B5: 166101 Bornova | D5: Own Collection | F5: Commission & Services | H5: Turkey (TR) | K5: Others | L5: 1 | M5: ='CC cost Calculations'!P98 -> 0 | Q5: =IF(L5="","",L5) -> 1 | R5: =IF(Q5="","",Q5*M5) -> 0 | S5: =IF(Q5="","",Q5*(N5+P5)) -> 0 | T5: =IF(Q5="","",Q5*O5) -> 0 | U5: =IF(Q5="","",R5/Q5) -> 0 | V5: =IF(Q5="","",S5/Q5) -> 0 | W5: =IF(Q5="","",T5/Q5) -> 0 | X5: =IF(Q5="","",U5-V5) -> 0 | Y5: =IF(Q5="","",U5-V5-W5) -> 0 | Z5: =IF(Q5="","",R5-S5) -> 0 | AA5: =IF(Q5="","",R5-S5-T5) -> 0 | AB5: =IF(G5="","",VLOOKUP(G5,Qualities!$A$2:$B$156,2,0)) | AC5: =IF(AB5="","",VLOOKUP(AB5,QualityType!$A$2:$B$16,2,0)) | AD5: =D5&AC5 -> Own Collection | AE5: =IF(I5="",IF(AND(J5="",K5=""),"",F5&"External"),IF(COUNTIF(BaseData!$B$2:$B$45,I5)=1,F5&"Consolidation intra-divisional",F5&"Group")) -> Commission & ServicesExternal | AF5: =IF(A5="","",F5&IF(I5<>"","aff","ext")) -> Commission & Servicesext
A6: 2022 | B6: 166101 Bornova | D6: Own Collection | F6: Commission & Services | H6: Turkey (TR) | K6: Others | L6: 1 | M6: =M5 -> 0 | Q6: =IF(L6="","",L6) -> 1 | R6: =IF(Q6="","",Q6*M6) -> 0 | S6: =IF(Q6="","",Q6*(N6+P6)) -> 0 | T6: =IF(Q6="","",Q6*O6) -> 0 | U6: =IF(Q6="","",R6/Q6) -> 0 | V6: =IF(Q6="","",S6/Q6) -> 0 | W6: =IF(Q6="","",T6/Q6) -> 0 | X6: =IF(Q6="","",U6-V6) -> 0 | Y6: =IF(Q6="","",U6-V6-W6) -> 0 | Z6: =IF(Q6="","",R6-S6) -> 0 | AA6: =IF(Q6="","",R6-S6-T6) -> 0 | AB6: =IF(G6="","",VLOOKUP(G6,Qualities!$A$2:$B$156,2,0)) | AC6: =IF(AB6="","",VLOOKUP(AB6,QualityType!$A$2:$B$16,2,0)) | AD6: =D6&AC6 -> Own Collection | AE6: =IF(I6="",IF(AND(J6="",K6=""),"",F6&"External"),IF(COUNTIF(BaseData!$B$2:$B$45,I6)=1,F6&"Consolidation intra-divisional",F6&"Group")) -> Commission & ServicesExternal | AF6: =IF(A6="","",F6&IF(I6<>"","aff","ext")) -> Commission & Servicesext
A7: 2023 | B7: 166101 Bornova | D7: Own Collection | F7: Commission & Services | H7: Turkey (TR) | K7: Others | L7: 1 | M7: =(M5/93)*78 -> 0 | Q7: =IF(L7="","",L7) -> 1 | R7: =IF(Q7="","",Q7*M7) -> 0 | S7: =IF(Q7="","",Q7*(N7+P7)) -> 0 | T7: =IF(Q7="","",Q7*O7) -> 0 | U7: =IF(Q7="","",R7/Q7) -> 0 | V7: =IF(Q7="","",S7/Q7) -> 0 | W7: =IF(Q7="","",T7/Q7) -> 0 | X7: =IF(Q7="","",U7-V7) -> 0 | Y7: =IF(Q7="","",U7-V7-W7) -> 0 | Z7: =IF(Q7="","",R7-S7) -> 0 | AA7: =IF(Q7="","",R7-S7-T7) -> 0 | AB7: =IF(G7="","",VLOOKUP(G7,Qualities!$A$2:$B$156,2,0)) | AC7: =IF(AB7="","",VLOOKUP(AB7,QualityType!$A$2:$B$16,2,0)) | AD7: =D7&AC7 -> Own Collection | AE7: =IF(I7="",IF(AND(J7="",K7=""),"",F7&"External"),IF(COUNTIF(BaseData!$B$2:$B$45,I7)=1,F7&"Consolidation intra-divisional",F7&"Group")) -> Commission & ServicesExternal | AF7: =IF(A7="","",F7&IF(I7<>"","aff","ext")) -> Commission & Servicesext
Q8: =IF(L8="","",L8) | R8: =IF(Q8="","",Q8*M8) | S8: =IF(Q8="","",Q8*(N8+P8)) | T8: =IF(Q8="","",Q8*O8) | U8: =IF(Q8="","",R8/Q8) | V8: =IF(Q8="","",S8/Q8) | W8: =IF(Q8="","",T8/Q8) | X8: =IF(Q8="","",U8-V8) | Y8: =IF(Q8="","",U8-V8-W8) | Z8: =IF(Q8="","",R8-S8) | AA8: =IF(Q8="","",R8-S8-T8) | AB8: =IF(G8="","",VLOOKUP(G8,Qualities!$A$2:$B$156,2,0)) | AC8: =IF(AB8="","",VLOOKUP(AB8,QualityType!$A$2:$B$16,2,0)) | AD8: =D8&AC8 | AE8: =IF(I8="",IF(AND(J8="",K8=""),"",F8&"External"),IF(COUNTIF(BaseData!$B$2:$B$45,I8)=1,F8&"Consolidation intra-divisional",F8&"Group")) | AF8: =IF(A8="","",F8&IF(I8<>"","aff","ext"))
Q9: =IF(L9="","",L9) | R9: =IF(Q9="","",Q9*M9) | S9: =IF(Q9="","",Q9*(N9+P9)) | T9: =IF(Q9="","",Q9*O9) | U9: =IF(Q9="","",R9/Q9) | V9: =IF(Q9="","",S9/Q9) | W9: =IF(Q9="","",T9/Q9) | X9: =IF(Q9="","",U9-V9) | Y9: =IF(Q9="","",U9-V9-W9) | Z9: =IF(Q9="","",R9-S9) | AA9: =IF(Q9="","",R9-S9-T9) | AB9: =IF(G9="","",VLOOKUP(G9,Qualities!$A$2:$B$156,2,0)) | AC9: =IF(AB9="","",VLOOKUP(AB9,QualityType!$A$2:$B$16,2,0)) | AD9: =D9&AC9 | AE9: =IF(I9="",IF(AND(J9="",K9=""),"",F9&"External"),IF(COUNTIF(BaseData!$B$2:$B$45,I9)=1,F9&"Consolidation intra-divisional",F9&"Group")) | AF9: =IF(A9="","",F9&IF(I9<>"","aff","ext"))
Q10: =IF(L10="","",L10) | R10: =IF(Q10="","",Q10*M10) | S10: =IF(Q10="","",Q10*(N10+P10)) | T10: =IF(Q10="","",Q10*O10) | U10: =IF(Q10="","",R10/Q10) | V10: =IF(Q10="","",S10/Q10) | W10: =IF(Q10="","",T10/Q10) | X10: =IF(Q10="","",U10-V10) | Y10: =IF(Q10="","",U10-V10-W10) | Z10: =IF(Q10="","",R10-S10) | AA10: =IF(Q10="","",R10-S10-T10) | AB10: =IF(G10="","",VLOOKUP(G10,Qualities!$A$2:$B$156,2,0)) | AC10: =IF(AB10="","",VLOOKUP(AB10,QualityType!$A$2:$B$16,2,0)) | AD10: =D10&AC10 | AE10: =IF(I10="",IF(AND(J10="",K10=""),"",F10&"External"),IF(COUNTIF(BaseData!$B$2:$B$45,I10)=1,F10&"Consolidation intra-divisional",F10&"Group")) | AF10: =IF(A10="","",F10&IF(I10<>"","aff","ext"))
Q11: =IF(L11="","",L11) | R11: =IF(Q11="","",Q11*M11) | S11: =IF(Q11="","",Q11*(N11+P11)) | T11: =IF(Q11="","",Q11*O11) | U11: =IF(Q11="","",R11/Q11) | V11: =IF(Q11="","",S11/Q11) | W11: =IF(Q11="","",T11/Q11) | X11: =IF(Q11="","",U11-V11) | Y11: =IF(Q11="","",U11-V11-W11) | Z11: =IF(Q11="","",R11-S11) | AA11: =IF(Q11="","",R11-S11-T11) | AB11: =IF(G11="","",VLOOKUP(G11,Qualities!$A$2:$B$156,2,0)) | AC11: =IF(AB11="","",VLOOKUP(AB11,QualityType!$A$2:$B$16,2,0)) | AD11: =D11&AC11 | AE11: =IF(I11="",IF(AND(J11="",K11=""),"",F11&"External"),IF(COUNTIF(BaseData!$B$2:$B$45,I11)=1,F11&"Consolidation intra-divisional",F11&"Group")) | AF11: =IF(A11="","",F11&IF(I11<>"","aff","ext"))
Q12: =IF(L12="","",L12) | R12: =IF(Q12="","",Q12*M12) | S12: =IF(Q12="","",Q12*(N12+P12)) | T12: =IF(Q12="","",Q12*O12) | U12: =IF(Q12="","",R12/Q12) | V12: =IF(Q12="","",S12/Q12) | W12: =IF(Q12="","",T12/Q12) | X12: =IF(Q12="","",U12-V12) | Y12: =IF(Q12="","",U12-V12-W12) | Z12: =IF(Q12="","",R12-S12) | AA12: =IF(Q12="","",R12-S12-T12) | AB12: =IF(G12="","",VLOOKUP(G12,Qualities!$A$2:$B$156,2,0)) | AC12: =IF(AB12="","",VLOOKUP(AB12,QualityType!$A$2:$B$16,2,0)) | AD12: =D12&AC12 | AE12: =IF(I12="",IF(AND(J12="",K12=""),"",F12&"External"),IF(COUNTIF(BaseData!$B$2:$B$45,I12)=1,F12&"Consolidation intra-divisional",F12&"Group")) | AF12: =IF(A12="","",F12&IF(I12<>"","aff","ext"))
Q13: =IF(L13="","",L13) | R13: =IF(Q13="","",Q13*M13) | S13: =IF(Q13="","",Q13*(N13+P13)) | T13: =IF(Q13="","",Q13*O13) | U13: =IF(Q13="","",R13/Q13) | V13: =IF(Q13="","",S13/Q13) | W13: =IF(Q13="","",T13/Q13) | X13: =IF(Q13="","",U13-V13) | Y13: =IF(Q13="","",U13-V13-W13) | Z13: =IF(Q13="","",R13-S13) | AA13: =IF(Q13="","",R13-S13-T13) | AB13: =IF(G13="","",VLOOKUP(G13,Qualities!$A$2:$B$156,2,0)) | AC13: =IF(AB13="","",VLOOKUP(AB13,QualityType!$A$2:$B$16,2,0)) | AD13: =D13&AC13 | AE13: =IF(I13="",IF(AND(J13="",K13=""),"",F13&"External"),IF(COUNTIF(BaseData!$B$2:$B$45,I13)=1,F13&"Consolidation intra-divisional",F13&"Group")) | AF13: =IF(A13="","",F13&IF(I13<>"","aff","ext"))
Q14: =IF(L14="","",L14) | R14: =IF(Q14="","",Q14*M14) | S14: =IF(Q14="","",Q14*(N14+P14)) | T14: =IF(Q14="","",Q14*O14) | U14: =IF(Q14="","",R14/Q14) | V14: =IF(Q14="","",S14/Q14) | W14: =IF(Q14="","",T14/Q14) | X14: =IF(Q14="","",U14-V14) | Y14: =IF(Q14="","",U14-V14-W14) | Z14: =IF(Q14="","",R14-S14) | AA14: =IF(Q14="","",R14-S14-T14) | AB14: =IF(G14="","",VLOOKUP(G14,Qualities!$A$2:$B$156,2,0)) | AC14: =IF(AB14="","",VLOOKUP(AB14,QualityType!$A$2:$B$16,2,0)) | AD14: =D14&AC14 | AE14: =IF(I14="",IF(AND(J14="",K14=""),"",F14&"External"),IF(COUNTIF(BaseData!$B$2:$B$45,I14)=1,F14&"Consolidation intra-divisional",F14&"Group")) | AF14: =IF(A14="","",F14&IF(I14<>"","aff","ext"))
Q15: =IF(L15="","",L15) | R15: =IF(Q15="","",Q15*M15) | S15: =IF(Q15="","",Q15*(N15+P15)) | T15: =IF(Q15="","",Q15*O15) | U15: =IF(Q15="","",R15/Q15) | V15: =IF(Q15="","",S15/Q15) | W15: =IF(Q15="","",T15/Q15) | X15: =IF(Q15="","",U15-V15) | Y15: =IF(Q15="","",U15-V15-W15) | Z15: =IF(Q15="","",R15-S15) | AA15: =IF(Q15="","",R15-S15-T15) | AB15: =IF(G15="","",VLOOKUP(G15,Qualities!$A$2:$B$156,2,0)) | AC15: =IF(AB15="","",VLOOKUP(AB15,QualityType!$A$2:$B$16,2,0)) | AD15: =D15&AC15 | AE15: =IF(I15="",IF(AND(J15="",K15=""),"",F15&"External"),IF(COUNTIF(BaseData!$B$2:$B$45,I15)=1,F15&"Consolidation intra-divisional",F15&"Group")) | AF15: =IF(A15="","",F15&IF(I15<>"","aff","ext"))
Q16: =IF(L16="","",L16) | R16: =IF(Q16="","",Q16*M16) | S16: =IF(Q16="","",Q16*(N16+P16)) | T16: =IF(Q16="","",Q16*O16) | U16: =IF(Q16="","",R16/Q16) | V16: =IF(Q16="","",S16/Q16) | W16: =IF(Q16="","",T16/Q16) | X16: =IF(Q16="","",U16-V16) | Y16: =IF(Q16="","",U16-V16-W16) | Z16: =IF(Q16="","",R16-S16) | AA16: =IF(Q16="","",R16-S16-T16) | AB16: =IF(G16="","",VLOOKUP(G16,Qualities!$A$2:$B$156,2,0)) | AC16: =IF(AB16="","",VLOOKUP(AB16,QualityType!$A$2:$B$16,2,0)) | AD16: =D16&AC16 | AE16: =IF(I16="",IF(AND(J16="",K16=""),"",F16&"External"),IF(COUNTIF(BaseData!$B$2:$B$45,I16)=1,F16&"Consolidation intra-divisional",F16&"Group")) | AF16: =IF(A16="","",F16&IF(I16<>"","aff","ext"))
Q17: =IF(L17="","",L17) | R17: =IF(Q17="","",Q17*M17) | S17: =IF(Q17="","",Q17*(N17+P17)) | T17: =IF(Q17="","",Q17*O17) | U17: =IF(Q17="","",R17/Q17) | V17: =IF(Q17="","",S17/Q17) | W17: =IF(Q17="","",T17/Q17) | X17: =IF(Q17="","",U17-V17) | Y17: =IF(Q17="","",U17-V17-W17) | Z17: =IF(Q17="","",R17-S17) | AA17: =IF(Q17="","",R17-S17-T17) | AB17: =IF(G17="","",VLOOKUP(G17,Qualities!$A$2:$B$156,2,0)) | AC17: =IF(AB17="","",VLOOKUP(AB17,QualityType!$A$2:$B$16,2,0)) | AD17: =D17&AC17 | AE17: =IF(I17="",IF(AND(J17="",K17=""),"",F17&"External"),IF(COUNTIF(BaseData!$B$2:$B$45,I17)=1,F17&"Consolidation intra-divisional",F17&"Group")) | AF17: =IF(A17="","",F17&IF(I17<>"","aff","ext"))
Q18: =IF(L18="","",L18) | R18: =IF(Q18="","",Q18*M18) | S18: =IF(Q18="","",Q18*(N18+P18)) | T18: =IF(Q18="","",Q18*O18) | U18: =IF(Q18="","",R18/Q18) | V18: =IF(Q18="","",S18/Q18) | W18: =IF(Q18="","",T18/Q18) | X18: =IF(Q18="","",U18-V18) | Y18: =IF(Q18="","",U18-V18-W18) | Z18: =IF(Q18="","",R18-S18) | AA18: =IF(Q18="","",R18-S18-T18) | AB18: =IF(G18="","",VLOOKUP(G18,Qualities!$A$2:$B$156,2,0)) | AC18: =IF(AB18="","",VLOOKUP(AB18,QualityType!$A$2:$B$16,2,0)) | AD18: =D18&AC18 | AE18: =IF(I18="",IF(AND(J18="",K18=""),"",F18&"External"),IF(COUNTIF(BaseData!$B$2:$B$45,I18)=1,F18&"Consolidation intra-divisional",F18&"Group")) | AF18: =IF(A18="","",F18&IF(I18<>"","aff","ext"))
Q19: =IF(L19="","",L19) | R19: =IF(Q19="","",Q19*M19) | S19: =IF(Q19="","",Q19*(N19+P19)) | T19: =IF(Q19="","",Q19*O19) | U19: =IF(Q19="","",R19/Q19) | V19: =IF(Q19="","",S19/Q19) | W19: =IF(Q19="","",T19/Q19) | X19: =IF(Q19="","",U19-V19) | Y19: =IF(Q19="","",U19-V19-W19) | Z19: =IF(Q19="","",R19-S19) | AA19: =IF(Q19="","",R19-S19-T19) | AB19: =IF(G19="","",VLOOKUP(G19,Qualities!$A$2:$B$156,2,0)) | AC19: =IF(AB19="","",VLOOKUP(AB19,QualityType!$A$2:$B$16,2,0)) | AD19: =D19&AC19 | AE19: =IF(I19="",IF(AND(J19="",K19=""),"",F19&"External"),IF(COUNTIF(BaseData!$B$2:$B$45,I19)=1,F19&"Consolidation intra-divisional",F19&"Group")) | AF19: =IF(A19="","",F19&IF(I19<>"","aff","ext"))
... Q922: =IF(L922="","",L922) | R922: =IF(Q922="","",Q922*M922) | S922: =IF(Q922="","",Q922*(N922+P922)) | T922: =IF(Q922="","",Q922*O922) | U922: =IF(Q922="","",R922/Q922) | V922: =IF(Q922="","",S922/Q922) | W922: =IF(Q922="","",T922/Q922) | X922: =IF(Q922="","",U922-V922) | Y922: =IF(Q922="","",U922-V922-W922) | Z922: =IF(Q922="","",R922-S922) | AA922: =IF(Q922="","",R922-S922-T922) | AB922: =IF(G922="","",VLOOKUP(G922,Qualities!$A$2:$B$156,2,0)) | AC922: =IF(AB922="","",VLOOKUP(AB922,QualityType!$A$2:$B$16,2,0)) | AD922: =D922&AC922 | AE922: =IF(I922="",IF(AND(J922="",K922=""),"",F922&"External"),IF(COUNTIF(BaseData!$B$2:$B$45,I922)=1,F922&"Consolidation intra-divisional",F922&"Group")) | AF922: =IF(A922="","",F922&IF(I922<>"","aff","ext"))

Sheet CC cost Calculations
C2: 2022 | D2: 2023 | E2: 2024 | F2: Av. 3 years (2021-22-23) | I2: Avarage | L2: Reloop | P2: Quantity (Tons/year) 2021 | T2: Number (pcs/year) 2021
A3: Yearly expected increase of consumption | D3: 0.05 | E3: 0.05
A4: Number of packaging in izmir | C4: =T7 -> 1.0683979e+09 | D4: =C4*(D3+1) -> 1.1218178e+09 | E4: =D4*(E3+1) -> 1.1779087e+09 | F4: =SUM(C4:E4)/3 -> 1.1227081e+09 | G4: pcs/year
A5: Working Days for collection | C5: 300 | D5: 300 | E5: 300 | F5: =SUM(C5:E5)/3 -> 300 | G5: days/year | L5: City | M5: Population | N5: Populaton Rate % in Turkey | O5: Populaton Rate % in Aegean Region | P5: Baverage Packaging Assumptions (Ton/year) | Q5: Glass 85% (tons/year) | R5: PET 10% (tons/year) | S5: Cans 5% (tons/year) | T5: Baverage Packaging Assumptions (pcs/year) | U5: Glass 36% (pcs/year) | V5: PET 45% (pcs/year) | W5: Cans 19% (pcs/year)
A6: Total packaging in İzmir | C6: =C4/C5 -> 3561326.4 | D6: =D4/D5 -> 3739392.7 | E6: =E4/E5 -> 3926362.4 | F6: =SUM(C6:E6)/3 -> 3742360.5 | G6: pcs/day | L6: Manisa | M6: 1429643 | N6: =(M6/80000000) -> 0.017870537 | O6: =M6/M$15 -> 0.13597259 | P6: =N6*Q$20 -> 23142.346 | Q6: =P6*0.85 -> 19670.994 | R6: =P6*0.1 -> 2314.2346 | S6: =P6*0.05 -> 1157.1173 | T6: =O6*Q$21 -> 3.5352873e+08 | U6: =T6*0.36 -> 1.2727034e+08 | V6: =T6*0.45 -> 1.5908793e+08 | W6: =T6*0.19 -> 67170459
A7: Target collection rate | C7: 0.7 | D7: 0.8 | E7: 0.9 | L7: İzmir | M7: 4320519 | N7: =(M7/80000000) -> 0.054006487 | O7: =M7/M$15 -> 0.41092228 | P7: =N7*Q$20 -> 69938.401 | Q7: =P7*0.85 -> 59447.641 | R7: =P7*0.1 -> 6993.8401 | S7: =P7*0.05 -> 3496.9201 | T7: =O7*Q$21 -> 1.0683979e+09 | U7: =T7*0.36 -> 3.8462325e+08 | V7: =T7*0.45 -> 4.8077906e+08 | W7: =T7*0.19 -> 2.029956e+08
A8: Target Manuel collection rate | C8: 0.93 | D8: 0.93 | E8: 0.78 | L8: Aydın | M8: 1097746 | N8: =(M8/80000000) -> 0.013721825 | O8: =M8/M$15 -> 0.10440604 | P8: =N8*Q$20 -> 17769.763 | Q8: =P8*0.85 -> 15104.299 | R8: =P8*0.1 -> 1776.9763 | S8: =P8*0.05 -> 888.48817 | T8: =O8*Q$21 -> 2.7145571e+08 | U8: =T8*0.36 -> 97724055 | V8: =T8*0.45 -> 1.2215507e+08 | W8: =T8*0.19 -> 51576584
A9: Target Manuel packaging collection (day) | C9: =C$6*C7*C8 -> 2318423.5 | D9: =D$6*D7*D8 -> 2782108.2 | E9: =E$6*E7*E8 -> 2756306.4 | F9: =SUM(C9:E9)/3 -> 2618946 | G9: pcs/day
A10: Target Manuel packaging collection (year) | C10: =C9*300 -> 6.9552705e+08 | D10: =D9*300 -> 8.3463245e+08 | E10: =E9*300 -> 8.2689191e+08 | F10: =F9*300 -> 7.856838e+08 | G10: pcs/year | L10: Denizli | M10: 1027782 | N10: =(M10/80000000) -> 0.012847275 | O10: =M10/M$15 -> 0.097751802 | P10: =N10*Q$20 -> 16637.221 | Q10: =P10*0.85 -> 14141.638 | R10: =P10*0.1 -> 1663.7221 | S10: =P10*0.05 -> 831.86106 | T10: =O10*Q$21 -> 2.5415469e+08 | U10: =T10*0.36 -> 91495687 | V10: =T10*0.45 -> 1.1436961e+08 | W10: =T10*0.19 -> 48289390
L11: Muğla | M11: 967487 | N11: =(M11/80000000) -> 0.012093588 | O11: =M11/M$15 -> 0.092017177 | P11: =N11*Q$20 -> 15661.196 | Q11: =P11*0.85 -> 13312.016 | R11: =P11*0.1 -> 1566.1196 | S11: =P11*0.05 -> 783.05979 | T11: =O11*Q$21 -> 2.3924466e+08 | U11: =T11*0.36 -> 86128077 | V11: =T11*0.45 -> 1.076601e+08 | W11: =T11*0.19 -> 45456485
A12: Content glass | C12: 0.36 | D12: 0.36 | E12: 0.36 | F12: =SUM(C12:E12)/3 -> 0.36 | L12: Uşak | M12: 367514 | N12: =(M12/80000000) -> 0.004593925 | O12: =M12/M$15 -> 0.034954062 | P12: =N12*Q$20 -> 5949.1329 | Q12: =P12*0.85 -> 5056.7629 | R12: =P12*0.1 -> 594.91329 | S12: =P12*0.05 -> 297.45664 | T12: =O12*Q$21 -> 90880562 | U12: =T12*0.36 -> 32717002 | V12: =T12*0.45 -> 40896253 | W12: =T12*0.19 -> 17267307
A13: Content pet | C13: 0.45 | D13: 0.45 | E13: 0.45 | F13: =SUM(C13:E13)/3 -> 0.45 | L13: Afyon | M13: 725568 | N13: =(M13/80000000) -> 0.0090696 | O13: =M13/M$15 -> 0.069008389 | P13: =N13*Q$20 -> 11745.132 | Q13: =P13*0.85 -> 9983.3622 | R13: =P13*0.1 -> 1174.5132 | S13: =P13*0.05 -> 587.2566 | T13: =O13*Q$21 -> 1.7942181e+08 | U13: =T13*0.36 -> 64591852 | V13: =T13*0.45 -> 80739815 | W13: =T13*0.19 -> 34090144
A14: Content Alu | C14: 0.19 | D14: 0.19 | E14: 0.19 | F14: =SUM(C14:E14)/3 -> 0.19 | L14: Kütahya | M14: 577941 | N14: =(M14/80000000) -> 0.0072242625 | O14: =M14/M$15 -> 0.054967663 | P14: =N14*Q$20 -> 9355.4199 | Q14: =P14*0.85 -> 7952.1069 | R14: =P14*0.1 -> 935.54199 | S14: =P14*0.05 -> 467.771 | T14: =O14*Q$21 -> 1.4291592e+08 | U14: =T14*0.36 -> 51449732 | V14: =T14*0.45 -> 64312165 | W14: =T14*0.19 -> 27154025
A15: Number of Glass Packaging in izmir (collection Target) | C15: =C$9*(C12/100) -> 8346.3245 | D15: =D$9*(D12/100) -> 10015.589 | E15: =E$9*(E12/100) -> 9922.7029 | F15: =SUM(C15:E15)/3 -> 9428.2056 | G15: pcs/day | L15: Total | M15: =SUM(M6:M14) -> 10514200 | N15: =SUM(N6:N14) -> 0.1314275 | P15: =SUM(P6:P14) -> 170198.61 | Q15: =P15*0.85 -> 144668.82 | R15: =P15*0.1 -> 17019.861 | S15: =P15*0.05 -> 8509.9306 | T15: =SUM(T6:T14) -> 2600000000 | U15: =SUM(U6:U14) -> 9.36e+08 | V15: =SUM(V6:V14) -> 1170000000 | W15: =SUM(W6:W14) -> 494000000
A16: Number of PET Packaging in İzmir (collection Target) | C16: =C$9*(C13/100) -> 10432.906 | D16: =D$9*(D13/100) -> 12519.487 | E16: =E$9*(E13/100) -> 12403.379 | F16: =SUM(C16:E16)/3 -> 11785.257 | G16: pcs/day
A17: Number of Alu Packaging in İzmir (collection Target) | C17: =C$9*(C14/100) -> 4405.0046 | D17: =D$9*(D14/100) -> 5286.0055 | E17: =E$9*(E14/100) -> 5236.9821 | F17: =SUM(C17:E17)/3 -> 4975.9974 | G17: pcs/day
A18: Number of Glass Packaging (0,5 Lt) | B18: checkout figures | C18: 700 | D18: 700 | E18: 700 | F18: =SUM(C18:E18)/3 -> 700 | G18: pcs/m3
A19: Number of PET Packaging (mixed) | B19: checkout figures | C19: 500 | D19: 500 | E19: 500 | F19: =SUM(C19:E19)/3 -> 500 | G19: pcs/m3
A20: Number of Alu Packaging (0,33 Lt) | B20: checkout figures | C20: 2000 | D20: 2000 | E20: 2000 | F20: =SUM(C20:E20)/3 -> 2000 | G20: pcs/m3 | L20: Total Amount of Baverage Packaging in Turkey (ton/year) 2021 | Q20: 1295000
A21: Capacity of 1 bag | C21: =((C12*C18)+(C13*C19)+(C14*C20)) -> 857 | D21: =((D12*D18)+(D13*D19)+(D14*D20)) -> 857 | E21: =((E12*E18)+(E13*E19)+(E14*E20)) -> 857 | F21: =SUM(C21:E21)/3 -> 857 | G21: pcs/m3 | L21: Total Number of Baverage Packaging in Aegean Region of Turkey (pcs/year) 2021 | Q21: 2600000000
A22: Number of bags in a day in İzmir | C22: =C6/C21 -> 4155.5734 | D22: =D6/D21 -> 4363.3521 | E22: =E6/E21 -> 4581.5197 | F22: =SUM(C22:E22)/3 -> 4366.815 | G22: bags/day | L22: Total Number of Baverage Packaging in Aegean Region of Turkey (pcs/year) 2021 | Q22: =SUM(Q27:Q31) -> 19600000000
A24: Truck type 1 (10m3) | C24: =ROUND(C47*C44,0) -> 47 | D24: =ROUND(D47*D44,0) -> 56 | E24: =ROUND(E47*E44,0) -> 56 | F24: =SUM(C24:E24)/3 -> 53 | G24: trucks
A25: Efficiency on loading bags on truck | B25: discuss about efficiency | C25: 0.7 | D25: =C25 -> 0.7 | E25: =D25 -> 0.7 | F25: =SUM(C25:E25)/3 -> 0.7 | G25: %
A26: Capacity of Truck (10m3 type) | C26: 10 | D26: 10 | E26: 10 | F26: =SUM(C26:E26)/3 -> 10 | G26: m3
A27: Volume of 1 bag | C27: 1 | D27: 1 | E27: 1 | F27: 1 | G27: m3 | P27: PET | Q27: 8900000000
A28: Bag Capacity of truck | C28: =C26/C27*C25 -> 7 | D28: =D26/D27*D25 -> 7 | E28: =E26/E27*E25 -> 7 | F28: =F26/F27*F25 -> 7 | G28: bags | P28: Alu | Q28: 6600000000
A29: Capacity of Truck | C29: =C28*C21 -> 5999 | D29: =D28*D21 -> 5999 | E29: =E28*E21 -> 5999 | F29: =SUM(C29:E29)/3 -> 5999 | G29: pcs/truck
A30: Number of Tour in a day | C30: 4 | D30: 4 | E30: 4 | F30: =SUM(C30:E30)/3 -> 4 | G30: tours/day
A31: Collected packaging with 10 m3 capacity truck | C31: =C29*C30 -> 23996 | D31: =D29*D30 -> 23996 | E31: =E29*E30 -> 23996 | F31: =SUM(C31:E31)/3 -> 23996 | G31: pcs/day | P31: Glass | Q31: 4100000000
A32: Total capacity of 10m3 trucks fleet | C32: =C31*C24 -> 1127812 | D32: =D31*D24 -> 1343776 | E32: =E31*E24 -> 1343776 | F32: =F31*F24 -> 1271788 | G32: pcs/day
A34: Truck type 2 (19m3) | C34: =ROUND(C47*C45,0) -> 31 | D34: =ROUND(D47*D45,0) -> 38 | E34: =ROUND(E47*E45,0) -> 37 | F34: =SUM(C34:E34)/3 -> 35.333333 | G34: trucks
A35: Efficiency on loading bags on truck | B35: discuss about efficiency | C35: 0.7 | D35: =C35 -> 0.7 | E35: =D35 -> 0.7 | F35: =SUM(C35:E35)/3 -> 0.7 | G35: %
A36: Capacity of Truck (19m3 type) | C36: 19 | D36: 19 | E36: 19 | F36: =SUM(C36:E36)/3 -> 19 | G36: m3
A37: Volume of 1 bag | C37: 1 | D37: 1 | E37: 1 | F37: 1 | G37: m3
A38: Bag Capacity of truck | C38: =C36/C37*C35 -> 13.3 | D38: =D36/D37*D35 -> 13.3 | E38: =E36/E37*E35 -> 13.3 | F38: =F36/F37*F35 -> 13.3 | G38: bags
A39: Capacity of Truck | C39: =C38*C21 -> 11398.1 | D39: =D38*D21 -> 11398.1 | E39: =E38*E21 -> 11398.1 | F39: =SUM(C39:E39)/3 -> 11398.1 | G39: pcs/truck
A40: Number of Tour in a day | C40: 4 | D40: 4 | E40: 4 | F40: =SUM(C40:E40)/3 -> 4 | G40: tours/day
A41: Collected packaging with 19 m3 capacity truck | C41: =C39*C40 -> 45592.4 | D41: =D39*D40 -> 45592.4 | E41: =E39*E40 -> 45592.4 | F41: =SUM(C41:E41)/3 -> 45592.4 | G41: pcs/day
A42: Total capacity of 19m3 trucks fleet | C42: =C41*C34 -> 1413364.4 | D42: =D41*D34 -> 1732511.2 | E42: =E41*E34 -> 1686918.8 | F42: =F41*F34 -> 1610931.5 | G42: pcs/day
A44: ratio of 10m3 trucks in fleet | C44: 0.6 | D44: 0.6 | E44: 0.6
A45: ratio of 19m3 trucks in fleet | C45: 0.4 | D45: 0.4 | E45: 0.4
A46: Capacity ratio | C46: =(C29*C44)+(C45*C39) -> 8158.64 | D46: =(D29*D44)+(D45*D39) -> 8158.64 | E46: =(E29*E44)+(E45*E39) -> 8158.64
A47: Trucks Needed | C47: =(C50*1.1/C46)/C40 -> 78.146169 | D47: =(D50*1.1/D46)/D40 -> 93.775402 | E47: =(E50*1.1/E46)/E40 -> 92.905711
A49: Capacity of truck fleet | C49: =C42+C32 -> 2541176.4 | D49: =D42+D32 -> 3076287.2 | E49: =E42+E32 -> 3030694.8 | F49: =SUM(C49:E49)/3 -> 2882719.5 | G49: pcs/day
A50: Target Collection | C50: =C9 -> 2318423.5 | D50: =D9 -> 2782108.2 | E50: =E9 -> 2756306.4 | F50: =SUM(C50:E50)/3 -> 2618946 | G50: pcs/day
A51: Coverage rate | C51: =C49/C50 -> 1.0960795 | D51: =D49/D50 -> 1.1057396 | E51: =E49/E50 -> 1.0995493 | F51: =SUM(C51:E51)/3 -> 1.1004561 | G51: %
A53: 1 counting center capacity (5 vending machines) | C53: =18900000/30 -> 630000 | D53: =18900000/30 -> 630000 | E53: =18900000/30 -> 630000 | F53: =SUM(C53:E53)/3 -> 630000 | G53: pcs/day
A54: Av. VM capacity | C54: =C53/5 -> 126000 | D54: =D53/5 -> 126000 | E54: =E53/5 -> 126000 | F54: =SUM(C54:E54)/3 -> 126000 | G54: pcs/day
A55: Vending machines needed to cover İzmir | C55: =C9/C54 -> 18.400186 | D55: =D9/D54 -> 22.080224 | E55: =E9/E54 -> 21.875447 | F55: =SUM(C55:E55)/3 -> 20.785286 | G55: Vending Machines
A57: M410 | B57: Fuels / Steam | C57: =(C62+C66)*C5 -> 1090863072 | D57: =(D62+D66)*D5 -> 1.4481283e+09 | E57: =(E62+E66)*E5 -> 1.5739141e+09 | F57: =SUM(C57:E57)/3 -> 1.3709685e+09 | G57: ₺/year
A58: Price of fuel | B58: assume for fuel | C58: 6 | D58: =C58*1.1 -> 6.6 | E58: =D58*1.1 -> 7.26 | F58: =SUM(C58:E58)/3 -> 6.62 | G58: ₺/lt
A59: Average km/day.truck (10m3) | B59: discuss 561k km in 3 year depreciation | C59: =Q62 -> 624 | D59: =C59 -> 624 | E59: =D59 -> 624 | F59: =SUM(C59:E59)/3 -> 624 | G59: km/day.truck
A60: Number of Truck (10 m3 capacity) | C60: =C24 -> 47 | D60: =D24 -> 56 | E60: =E24 -> 56 | F60: =SUM(C60:E60)/3 -> 53 | G60: pcs
A61: Fuel Consumption for (10m3 capacity) | C61: 11.43 | D61: =C61 -> 11.43 | E61: =D61 -> 11.43 | F61: =SUM(C61:E61)/3 -> 11.43 | G61: lt/100 km | M61: Tours/day | N61: Average km/tour | O61: Buffer % | P61: Total km/day | Q61: Buffered Km
A62: Total Fuel Consumption 10m3 | B62: discuss about fuel cost | C62: =C60*C61*C59*C58 -> 2011314.2 | D62: =D60*D61*D59*D58 -> 2636105.5 | E62: =E60*E61*E59*E58 -> 2899716 | F62: =SUM(C62:E62)/3 -> 2515711.9 | G62: ₺/day | L62: 10 m3 capacity trucks | M62: =C30 -> 4 | N62: 120 | O62: 0.3 | P62: =N62*M62 -> 480 | Q62: =P62*(1+O62) -> 624
A63: Average km/day.truck (19m3) | C63: =Q63 -> 624 | D63: =C63 -> 624 | E63: =D63 -> 624 | F63: =SUM(C63:E63)/3 -> 624 | G63: km/day.truck | L63: 19 m3 capacity trucks | M63: 4 | N63: 120 | O63: 0.3 | P63: =N63*M63 -> 480 | Q63: =P63*(1+O63) -> 624
A64: Number of Truck (19 m3 capacity) | C64: =C34 -> 31 | D64: =D34 -> 38 | E64: =E34 -> 37 | F64: =SUM(C64:E64)/3 -> 35.333333 | G64: pcs
A65: Fuel Consumption for (19 m3 capacity) | C65: 14 | D65: =C65 -> 14 | E65: =D65 -> 14 | F65: =SUM(C65:E65)/3 -> 14 | G65: lt/100 km
A66: Total Fuel Consumption 19m3 | C66: =C64*C65*C63*C58 -> 1624896 | D66: =D64*D65*D63*D58 -> 2190988.8 | E66: =E64*E65*E63*E58 -> 2346664.3 | F66: =F64*F65*F63*F58 -> 2043408.6 | G66: ₺/day
A68: M489 | B68: Wages | C68: =SUM(C69:C71)*12 -> 23268960 | D68: =SUM(D69:D71)*12 -> 30846288 | E68: =SUM(E69:E71)*12 -> 33569950 | F68: =SUM(C68:E68)/3 -> 29228399 | G68: ₺/year | L68: employee | M68: 2022 | N68: 2023 | O68: 2024
A69: Truck Driver | C69: =M71*M75 -> 858000 | D69: =N71*N75 -> 1137400 | E69: =O71*O75 -> 1237830 | F69: =SUM(C69:E69)/3 -> 1077743.3 | G69: ₺/month | L69: Number of trucks | M69: =C24+C34 -> 78 | N69: =D24+D34 -> 94 | O69: =E24+E34 -> 93
A70: Truck Driver Helper | C70: =M72*M75 -> 858000 | D70: =N72*N75 -> 1137400 | E70: =O72*O75 -> 1237830 | F70: =SUM(C70:E70)/3 -> 1077743.3 | G70: ₺/month | L70: Shifts needed | M70: 2 | N70: 2 | O70: 2
A71: Additional employee for substitute | C71: =M73*M75 -> 223080 | D71: =N73*N75 -> 295724 | E71: =O73*O75 -> 321835.8 | F71: =SUM(C71:E71)/3 -> 280213.27 | G71: ₺/month | L71: Drivers | M71: =M69*M70 -> 156 | N71: =N69*N70 -> 188 | O71: =O69*O70 -> 186
A72: M460 | B72: Salaries | C72: =C75*12 -> 588000 | D72: =D75*12 -> 646800 | E72: =E75*12 -> 646800 | F72: =SUM(C72:E72)/3 -> 627200 | G72: ₺/year | L72: Truck Driver Helper | M72: =M69*M70 -> 156 | N72: =N69*N70 -> 188 | O72: =O69*O70 -> 186
A73: Logistic supervisor | B73: discuss about supervisors | C73: 7 | D73: 7 | E73: 7 | F73: =SUM(C73:E73)/3 -> 7 | G73: person | L73: Additional employee for substitute | M73: =(M72+M71)*0.13 -> 40.56 | N73: =(N72+N71)*0.13 -> 48.88 | O73: =(O72+O71)*0.13 -> 48.36
A74: Cost of a supervisor | C74: 7000 | D74: =7000*1.1 -> 7700 | E74: =7000*1.1 -> 7700 | F74: =SUM(C74:E74)/3 -> 7466.6667 | G74: ₺/month | L74: Total Number of workers | M74: =SUM(M71:M73) -> 352.56 | N74: =SUM(N71:N73) -> 424.88 | O74: =SUM(O71:O73) -> 420.36
A75: Total supervisor cost | C75: =C74*C73 -> 49000 | D75: =D74*D73 -> 53900 | E75: =E74*E73 -> 53900 | F75: =SUM(C75:E75)/3 -> 52266.667 | G75: ₺/month | L75: cost of one employee (wage+other)/month | M75: 5500 | N75: =5500*1.1 -> 6050 | O75: =N75*1.1 -> 6655
A77: M509 | B77: Maintenance costs | C77: =C78*M69 -> 390000 | D77: =D78*N69 -> 517000 | E77: =E78*O69 -> 511500 | F77: =SUM(C77:E77)/3 -> 472833.33 | G77: ₺/year
A78: Maintanence cost per truck per year | C78: 5000 | D78: =C78*1.1 -> 5500 | E78: =D78*1*1 -> 5500 | F78: =SUM(C78:E78)/3 -> 5333.3333 | G78: ₺/month
A80: M635 | B80: Insurances (excl. transport insurance) | C80: =C81*M69 -> 468000 | D80: =D81*N69 -> 564000 | E80: =E81*O69 -> 558000 | F80: =SUM(C80:E80)/3 -> 530000 | G80: ₺/year
A81: Yearly İnsurence cost per truck | C81: 6000 | D81: =C81 -> 6000 | E81: =D81 -> 6000 | F81: =SUM(C81:E81)/3 -> 6000 | G81: ₺/year
A83: M640 | B83: IT-costs affil. | C83: =C84*C73 -> 175000 | D83: =D84*D73 -> 175000 | E83: =E84*E73 -> 175000 | F83: =SUM(C83:E83)/3 -> 175000 | G83: ₺/year
A84: Cost per supervisor | B84: discuss about supervisors | C84: 25000 | D84: =C84 -> 25000 | E84: =D84 -> 25000
A86: M641 | B86: IT-costs ext. | C86: =C87*M69 -> 23400 | D86: =D87*N69 -> 31020 | E86: =E87*O69 -> 33759 | F86: =SUM(C86:E86)/3 -> 29393 | G86: ₺/year
A87: gps system cost per year per truck | C87: 300 | D87: =C87*1.1 -> 330 | E87: =D87*1.1 -> 363
A89: M615 | B89: Travel expenses | C89: 200000 | D89: 200000 | E89: 200000 | F89: =SUM(C89:E89)/3 -> 200000 | G89: ₺/year
A90: M620 | B90: Communication exp. | C90: 17000 | D90: 17000 | E90: 17000 | F90: =SUM(C90:E90)/3 -> 17000 | G90: ₺/year
A92: M660 | B92: Other overhead costs | C92: 200000 | D92: 200000 | E92: 200000 | F92: =SUM(C92:E92)/3 -> 200000 | G92: ₺/year
A93: Total Cost | C93: =C68+C77+C83+C57+C92+C89+C90+C72 -> 1115702032 | D93: =D68+D77+D83+D57+D92+D89+D90+D72 -> 1.4807304e+09 | E93: =E68+E77+E83+E57+E92+E89+E90+E72 -> 1.6092344e+09 | F93: =F92+F90+F89+F86+F83+F80+F77+F68+F57+F72 -> 1.4024483e+09 | G93: ₺/year
A94: Investment payback in 3,5 years | G94: ₺/year
B95: Total investments | G95: ₺
A96: M845 | B96: Financial cost | C96: (-(BusPlanLocation!I116+BusPlanLocation!K116+BusPlanLocation!M116)/3)*1000*START!$E$18 | F96: =SUM(C96:E96)/3 -> 0 | G96: ₺/year | M96: Target Ebt/Cost | N96: 1.15
F97: =SUM(C97:E97)/3 -> 0 | L97: Business Model 2 | M97: Quantity (pcs/year) | N97: Service Price (₺/pcs) | O97: Target revenue ₺/year | P97: Target revenue €/year
G98: Total cost (TL/pcs) | H98: =(F93+F96)/F10 -> 1.7850035 | L98: counting of units | M98: ='CC cost Calculations'!C6 -> 3561326.4 | N98: =(H93+H94+H96)*N96 -> 0 | O98: =M98*N98 -> 0 | P98: =O98/START!E18 -> 0
AB109: kw/h
AA110: 7.5 | AB110: kw/h

Sheet İnvestments-CC conditions
B2: Price
A3: Truck 10 m3 capacity | B3: =250000/START!E18 -> 33333.333
A4: Truck 19 m3 capacity | B4: =350000/START!E18 -> 46666.667
A6: Number of truck purchase | B6: 2022 | C6: 2023 | D6: 2024
A7: Truck 10 m3 capacity | B7: ='CC cost Calculations'!C24 -> 47 | C7: ='CC cost Calculations'!D24-B7 -> 9 | D7: ='CC cost Calculations'!E24-C7-B7 -> 0 | E7: trucks
A8: Truck 19 m3 capacity | B8: ='CC cost Calculations'!C34 -> 31 | C8: ='CC cost Calculations'!D34-B8 -> 7 | D8: ='CC cost Calculations'!E34-C8-B8 -> -1 | E8: trucks
A9: Cost of 10m3 € | B9: =$B$3*B7 -> 1566666.7 | C9: =$B$3*C7 -> 300000 | D9: =$B$3*D7 -> 0 | E9: €
A10: Cost of 19m3 € | B10: =$B$4*B8 -> 1446666.7 | C10: =$B$4*C8 -> 326666.67 | D10: =$B$4*D8 -> -46666.667 | E10: €
A11: Total Cost (Euro) | B11: =SUM(B9:B10) -> 3013333.3 | C11: =SUM(C9:C10) -> 626666.67 | D11: =SUM(D9:D10) -> -46666.667 | E11: €
A17: Stock Area | B17: m2
A18: Area for Trucks - 10 m3 | B18: =9*B7 -> 423 | C18: open
A19: Area for Trucks - 19 m3 | B19: =12*B8 -> 372 | C19: open
A20: Area for drivers and helpers | B20: 100 | C20: Closed | D20: including cafeteria+changing room
A21: Total Area | B21: =SUM(B18:B20) -> 895

Sheet INVESTMENT per Year
B1: =START!$C$6 -> 1661 HR Turkey | C1: Registration currency:
B2: =START!$C$10 -> 166101 Bornova | C2: EUR
A3: IPNumber | B3: Title | C3: Category | D3: Priority | E3: Asset category | F3: Description | G3: Ownership percentage | H3: =START!$C$14 -> 2021 | I3: =H3+1 -> 2022 | J3: =I3+1 -> 2023 | K3: =J3+1 -> 2024 | L3: =K3+1 -> 2025 | M3: =L3+1 -> 2026 | N3: Total Investment | O3: Depreciation in years
A4: =IF(PP_Form!$L$5="","",IF(E4="","",PP_Form!$L$5)) -> P-12007 | B4: =IF(PP_Form!$D$10="","",IF(E4="","",PP_Form!$D$10)) -> Logistic Service Provider For Bornova Counting Center | C4: =IF(PP_Form!$D$6="","",IF(E4="","",PP_Form!$D$6)) -> [C] Major Project | D4: =IF(PP_Form!$D$8="","",IF(A4="","",PP_Form!$D$8)) -> NO | E4: MA250 Technical equipment and machinery | F4: ='İnvestments-CC conditions'!B7&" "&'İnvestments-CC conditions'!A7 -> 47 Truck 10 m3 capacity | G4: 1 | H4: ='İnvestments-CC conditions'!B9 -> 1566666.7 | N4: =SUM(H4:M4) -> 1566666.7 | O4: 3.5 | P4: =IF(O4="","",N4/O4) -> 447619.05
A5: =IF(PP_Form!$L$5="","",IF(E5="","",PP_Form!$L$5)) -> P-12007 | B5: =IF(PP_Form!$D$10="","",IF(E5="","",PP_Form!$D$10)) -> Logistic Service Provider For Bornova Counting Center | C5: =IF(PP_Form!$D$6="","",IF(E5="","",PP_Form!$D$6)) -> [C] Major Project | D5: =IF(PP_Form!$D$8="","",IF(A5="","",PP_Form!$D$8)) -> NO | E5: MA250 Technical equipment and machinery | F5: ='İnvestments-CC conditions'!B8&" "&'İnvestments-CC conditions'!A8 -> 31 Truck 19 m3 capacity | G5: 1 | H5: ='İnvestments-CC conditions'!B10 -> 1446666.7 | N5: =SUM(H5:M5) -> 1446666.7 | O5: 3.5 | P5: =IF(O5="","",N5/O5) -> 413333.33
A6: =IF(PP_Form!$L$5="","",IF(E6="","",PP_Form!$L$5)) -> P-12007 | B6: =IF(PP_Form!$D$10="","",IF(E6="","",PP_Form!$D$10)) -> Logistic Service Provider For Bornova Counting Center | C6: =IF(PP_Form!$D$6="","",IF(E6="","",PP_Form!$D$6)) -> [C] Major Project | D6: =IF(PP_Form!$D$8="","",IF(A6="","",PP_Form!$D$8)) -> NO | E6: MA250 Technical equipment and machinery | F6: ='İnvestments-CC conditions'!C7&" "&'İnvestments-CC conditions'!A7 -> 9 Truck 10 m3 capacity | G6: 1 | I6: ='İnvestments-CC conditions'!C9 -> 300000 | N6: =SUM(H6:M6) -> 300000 | O6: 3.5 | P6: =IF(O6="","",N6/O6) -> 85714.286
A7: =IF(PP_Form!$L$5="","",IF(E7="","",PP_Form!$L$5)) -> P-12007 | B7: =IF(PP_Form!$D$10="","",IF(E7="","",PP_Form!$D$10)) -> Logistic Service Provider For Bornova Counting Center | C7: =IF(PP_Form!$D$6="","",IF(E7="","",PP_Form!$D$6)) -> [C] Major Project | D7: =IF(PP_Form!$D$8="","",IF(A7="","",PP_Form!$D$8)) -> NO | E7: MA250 Technical equipment and machinery | F7: ='İnvestments-CC conditions'!C8&" "&'İnvestments-CC conditions'!A8 -> 7 Truck 19 m3 capacity | G7: 1 | I7: ='İnvestments-CC conditions'!C10 -> 326666.67 | N7: =SUM(H7:M7) -> 326666.67 | O7: 3.5 | P7: =IF(O7="","",N7/O7) -> 93333.333
A8: =IF(PP_Form!$L$5="","",IF(E8="","",PP_Form!$L$5)) -> P-12007 | B8: =IF(PP_Form!$D$10="","",IF(E8="","",PP_Form!$D$10)) -> Logistic Service Provider For Bornova Counting Center | C8: =IF(PP_Form!$D$6="","",IF(E8="","",PP_Form!$D$6)) -> [C] Major Project | D8: =IF(PP_Form!$D$8="","",IF(A8="","",PP_Form!$D$8)) -> NO | E8: MA250 Technical equipment and machinery | F8: ='İnvestments-CC conditions'!D7&" "&'İnvestments-CC conditions'!A7 -> 0 Truck 10 m3 capacity | G8: 1 | N8: =SUM(H8:M8) -> 0 | O8: 3.5 | P8: =IF(O8="","",N8/O8) -> 0
A9: =IF(PP_Form!$L$5="","",IF(E9="","",PP_Form!$L$5)) -> P-12007 | B9: =IF(PP_Form!$D$10="","",IF(E9="","",PP_Form!$D$10)) -> Logistic Service Provider For Bornova Counting Center | C9: =IF(PP_Form!$D$6="","",IF(E9="","",PP_Form!$D$6)) -> [C] Major Project | D9: =IF(PP_Form!$D$8="","",IF(A9="","",PP_Form!$D$8)) -> NO | E9: MA250 Technical equipment and machinery | F9: ='İnvestments-CC conditions'!D8&" "&'İnvestments-CC conditions'!A8 -> -1 Truck 19 m3 capacity | G9: 1 | N9: =SUM(H9:M9) -> 0 | O9: 3.5 | P9: =IF(O9="","",N9/O9) -> 0
A10: =IF(PP_Form!$L$5="","",IF(E10="","",PP_Form!$L$5)) -> P-12007 | B10: =IF(PP_Form!$D$10="","",IF(E10="","",PP_Form!$D$10)) -> Logistic Service Provider For Bornova Counting Center | C10: =IF(PP_Form!$D$6="","",IF(E10="","",PP_Form!$D$6)) -> [C] Major Project | D10: =IF(PP_Form!$D$8="","",IF(A10="","",PP_Form!$D$8)) -> NO | E10: MA250 Technical equipment and machinery | G10: 1 | N10: =SUM(H10:M10) -> 0 | O10: 3.5 | P10: =IF(O10="","",N10/O10) -> 0
A11: =IF(PP_Form!$L$5="","",IF(E11="","",PP_Form!$L$5)) -> P-12007 | B11: =IF(PP_Form!$D$10="","",IF(E11="","",PP_Form!$D$10)) -> Logistic Service Provider For Bornova Counting Center | C11: =IF(PP_Form!$D$6="","",IF(E11="","",PP_Form!$D$6)) -> [C] Major Project | D11: =IF(PP_Form!$D$8="","",IF(A11="","",PP_Form!$D$8)) -> NO | E11: MA250 Technical equipment and machinery | G11: 1 | N11: =SUM(H11:M11) -> 0 | O11: 3.5 | P11: =IF(O11="","",N11/O11) -> 0
A12: =IF(PP_Form!$L$5="","",IF(E12="","",PP_Form!$L$5)) -> P-12007 | B12: =IF(PP_Form!$D$10="","",IF(E12="","",PP_Form!$D$10)) -> Logistic Service Provider For Bornova Counting Center | C12: =IF(PP_Form!$D$6="","",IF(E12="","",PP_Form!$D$6)) -> [C] Major Project | D12: =IF(PP_Form!$D$8="","",IF(A12="","",PP_Form!$D$8)) -> NO | E12: MA250 Technical equipment and machinery | G12: 1 | N12: =SUM(H12:M12) -> 0 | O12: 3.5 | P12: =IF(O12="","",N12/O12) -> 0
A13: =IF(PP_Form!$L$5="","",IF(E13="","",PP_Form!$L$5)) -> P-12007 | B13: =IF(PP_Form!$D$10="","",IF(E13="","",PP_Form!$D$10)) -> Logistic Service Provider For Bornova Counting Center | C13: =IF(PP_Form!$D$6="","",IF(E13="","",PP_Form!$D$6)) -> [C] Major Project | D13: =IF(PP_Form!$D$8="","",IF(A13="","",PP_Form!$D$8)) -> NO | E13: MA250 Technical equipment and machinery | G13: 1 | N13: =SUM(H13:M13) -> 0 | O13: 3.5 | P13: =IF(O13="","",N13/O13) -> 0
A14: =IF(PP_Form!$L$5="","",IF(E14="","",PP_Form!$L$5)) -> P-12007 | B14: =IF(PP_Form!$D$10="","",IF(E14="","",PP_Form!$D$10)) -> Logistic Service Provider For Bornova Counting Center | C14: =IF(PP_Form!$D$6="","",IF(E14="","",PP_Form!$D$6)) -> [C] Major Project | D14: =IF(PP_Form!$D$8="","",IF(A14="","",PP_Form!$D$8)) -> NO | E14: MA250 Technical equipment and machinery | G14: 1 | N14: =SUM(H14:M14) -> 0 | O14: 3.5 | P14: =IF(O14="","",N14/O14) -> 0
A15: =IF(PP_Form!$L$5="","",IF(E15="","",PP_Form!$L$5)) -> P-12007 | B15: =IF(PP_Form!$D$10="","",IF(E15="","",PP_Form!$D$10)) -> Logistic Service Provider For Bornova Counting Center | C15: =IF(PP_Form!$D$6="","",IF(E15="","",PP_Form!$D$6)) -> [C] Major Project | D15: =IF(PP_Form!$D$8="","",IF(A15="","",PP_Form!$D$8)) -> NO | E15: MA250 Technical equipment and machinery | G15: 1 | N15: =SUM(H15:M15) -> 0 | O15: 3.5 | P15: =IF(O15="","",N15/O15) -> 0
A16: =IF(PP_Form!$L$5="","",IF(E16="","",PP_Form!$L$5)) -> P-12007 | B16: =IF(PP_Form!$D$10="","",IF(E16="","",PP_Form!$D$10)) -> Logistic Service Provider For Bornova Counting Center | C16: =IF(PP_Form!$D$6="","",IF(E16="","",PP_Form!$D$6)) -> [C] Major Project | D16: =IF(PP_Form!$D$8="","",IF(A16="","",PP_Form!$D$8)) -> NO | E16: MA250 Technical equipment and machinery | G16: 1 | N16: =SUM(H16:M16) -> 0 | O16: 3.5 | P16: =IF(O16="","",N16/O16) -> 0
A17: =IF(PP_Form!$L$5="","",IF(E17="","",PP_Form!$L$5)) -> P-12007 | B17: =IF(PP_Form!$D$10="","",IF(E17="","",PP_Form!$D$10)) -> Logistic Service Provider For Bornova Counting Center | C17: =IF(PP_Form!$D$6="","",IF(E17="","",PP_Form!$D$6)) -> [C] Major Project | D17: =IF(PP_Form!$D$8="","",IF(A17="","",PP_Form!$D$8)) -> NO | E17: MA250 Technical equipment and machinery | G17: 1 | N17: =SUM(H17:M17) -> 0 | O17: 3.5 | P17: =IF(O17="","",N17/O17) -> 0
A18: =IF(PP_Form!$L$5="","",IF(E18="","",PP_Form!$L$5)) -> P-12007 | B18: =IF(PP_Form!$D$10="","",IF(E18="","",PP_Form!$D$10)) -> Logistic Service Provider For Bornova Counting Center | C18: =IF(PP_Form!$D$6="","",IF(E18="","",PP_Form!$D$6)) -> [C] Major Project | D18: =IF(PP_Form!$D$8="","",IF(A18="","",PP_Form!$D$8)) -> NO | E18: MA250 Technical equipment and machinery | G18: 1 | N18: =SUM(H18:M18) -> 0 | O18: 3.5 | P18: =IF(O18="","",N18/O18) -> 0
A19: =IF(PP_Form!$L$5="","",IF(E19="","",PP_Form!$L$5)) -> P-12007 | B19: =IF(PP_Form!$D$10="","",IF(E19="","",PP_Form!$D$10)) -> Logistic Service Provider For Bornova Counting Center | C19: =IF(PP_Form!$D$6="","",IF(E19="","",PP_Form!$D$6)) -> [C] Major Project | D19: =IF(PP_Form!$D$8="","",IF(A19="","",PP_Form!$D$8)) -> NO | E19: MA250 Technical equipment and machinery | G19: 1 | N19: =SUM(H19:M19) -> 0 | O19: 3.5 | P19: =IF(O19="","",N19/O19) -> 0
A20: =IF(PP_Form!$L$5="","",IF(E20="","",PP_Form!$L$5)) -> P-12007 | B20: =IF(PP_Form!$D$10="","",IF(E20="","",PP_Form!$D$10)) -> Logistic Service Provider For Bornova Counting Center | C20: =IF(PP_Form!$D$6="","",IF(E20="","",PP_Form!$D$6)) -> [C] Major Project | D20: =IF(PP_Form!$D$8="","",IF(A20="","",PP_Form!$D$8)) -> NO | E20: MA250 Technical equipment and machinery | G20: 1 | N20: =SUM(H20:M20) -> 0 | O20: 3.5
G21: Total | H21: =SUM(H4:H20) -> 3013333.3 | I21: =SUM(I4:I18) -> 626666.67 | J21: =SUM(J4:J18) -> 0 | K21: =SUM(K4:K18) -> 0 | L21: =SUM(L4:L18) -> 0 | M21: =SUM(M4:M18) -> 0 | N21: =SUM(H21:M21) -> 3640000 | O21: =IF(SUM(P4:P18)=0,"",SUM(N4:N18)/SUM(P4:P18)) -> 3.5 | P21: =SUM(P4:P18) -> 1040000
D24: =IF(O21="",0,1/O21) -> 0.28571429 | E24: Depreciation in %
E25: =H3 -> 2021 | H25: =SUM('Cashflow per quarter'!G$20:H$20)*D24+SUM('Cashflow per quarter'!I$20:J$20)*$D$24/2 -> 860952.38 | I25: =$H21*$D$24 -> 860952.38 | J25: =$H21*$D$24 -> 860952.38 | K25: =$H21*$D$24 -> 860952.38 | L25: =$H21*$D$24 -> 860952.38 | M25: =$H21*$D$24 -> 860952.38 | N25: =SUM(H25:M25) -> 5165714.3
E26: =E25+1 -> 2022 | I26: =+I$21*$D$24 -> 179047.62 | J26: =+I26 -> 179047.62 | K26: =+J26 -> 179047.62 | L26: =+K26 -> 179047.62 | M26: =+L26 -> 179047.62 | N26: =SUM(H26:M26) -> 895238.1
E27: =E26+1 -> 2023 | J27: =+J$21*$D$24 -> 0 | K27: =+J27 -> 0 | L27: =+K27 -> 0 | M27: =+L27 -> 0 | N27: =SUM(H27:M27) -> 0
E28: =+E27+1 -> 2024 | K28: =+K$21*$D$24 -> 0 | L28: =+K28 -> 0 | M28: =+L28 -> 0 | N28: =SUM(H28:M28) -> 0
E29: =+E28+1 -> 2025 | L29: =+L$21*$D$24 -> 0 | M29: =+L29 -> 0 | N29: =SUM(H29:M29) -> 0
E30: =+E29+1 -> 2026 | M30: =+M21*D24 -> 0 | N30: =SUM(H30:M30) -> 0
E31: Summe | H31: =SUM(H25:H30) -> 860952.38 | I31: =SUM(I25:I30) -> 1040000 | J31: =SUM(J25:J30) -> 1040000 | K31: =SUM(K25:K30) -> 1040000 | L31: =SUM(L25:L30) -> 1040000 | M31: =SUM(M25:M30) -> 1040000 | N31: =SUM(H31:M31) -> 6060952.4
E32: Accumulated | H32: =+H31 -> 860952.38 | I32: =+H32+I31 -> 1900952.4 | J32: =+I32+J31 -> 2940952.4 | K32: =+J32+K31 -> 3980952.4 | L32: =+K32+L31 -> 5020952.4 | M32: =+L32+M31 -> 6060952.4 | N32: =M32 -> 6060952.4
D33: =IF(O21="",0,2.7%) -> 0.027 | E33: Interest in %
E34: =+E25 -> 2021 | H34: =SUM('Cashflow per quarter'!G$20:H$20)*D33+SUM('Cashflow per quarter'!I$20:J$20)*$D$33/2 -> 81360 | I34: =$H21*$D$33 -> 81360 | J34: =$H21*$D$33 -> 81360 | K34: =$H21*$D$33 -> 81360 | L34: =$H21*$D$33 -> 81360 | M34: =$H21*$D$33 -> 81360 | N34: =SUM(H34:M34) -> 488160
E35: =+E26 -> 2022 | I35: =+I$21*$D$33 -> 16920 | J35: =+I35 -> 16920 | K35: =+J35 -> 16920 | L35: =+K35 -> 16920 | M35: =+L35 -> 16920 | N35: =SUM(H35:M35) -> 84600
E36: =+E27 -> 2023 | J36: =+J$21*$D$33 -> 0 | K36: =+J36 -> 0 | L36: =+K36 -> 0 | M36: =+L36 -> 0 | N36: =SUM(H36:M36) -> 0
E37: =+E28 -> 2024 | K37: =+K$21*$D$33 -> 0 | L37: =+K37 -> 0 | M37: =+L37 -> 0 | N37: =SUM(H37:M37) -> 0
E38: =+E29 -> 2025 | L38: =+L$21*$D$33 -> 0 | M38: =+L38 -> 0 | N38: =SUM(H38:M38) -> 0
E39: =+E30 -> 2026 | M39: =+M21*D33 -> 0 | N39: =SUM(H39:M39) -> 0
E40: Summe | H40: =SUM(H34:H39) -> 81360 | I40: =SUM(I34:I39) -> 98280 | J40: =SUM(J34:J39) -> 98280 | K40: =SUM(K34:K39) -> 98280 | L40: =SUM(L34:L39) -> 98280 | M40: =SUM(M34:M39) -> 98280 | N40: =SUM(H40:M40) -> 572760
E41: Accumulated | H41: =+H40 -> 81360 | I41: =+H41+I40 -> 179640 | J41: =+I41+J40 -> 277920 | K41: =+J41+K40 -> 376200 | L41: =+K41+L40 -> 474480 | M41: =+L41+M40 -> 572760 | N41: =M41 -> 572760

Sheet Headcount
A2: Total employees (Actual + BusPlan)
B3: SUMMARY
B4: WAGES & SALARIES | D4: =G4-1 -> 2020 | G4: =START!$C$14 -> 2021 | J4: =+G4+1 -> 2022 | M4: =+J4+1 -> 2023 | P4: =+M4+1 -> 2024 | S4: =+P4+1 -> 2025 | V4: =+S4+1 -> 2026
B5: in EUR | D5: Wages | E5: Salaries | F5: Total | G5: Wages | H5: Salaries | I5: D Prev.year % | J5: Wages | K5: Salaries | L5: D Prev.year % | M5: Wages | N5: Salaries | O5: D Prev.year % | P5: Wages | Q5: Salaries | R5: D Prev.year % | S5: Wages | T5: Salaries | U5: D Prev.year % | V5: Wages | W5: Salaries | X5: D Prev.year %
C6: Average per head | D6: 4000 | E6: =IF(E33=0,0,BusPlanCompanyEUR!D59/E33) -> 0 | F6: =E6+D6 -> 4000 | G6: 4000 | H6: =IF(H33=0,0,BusPlanCompanyEUR!I59/H33) -> 0 | I6: =SUM(G6:H6)/SUM(D6:E6)-1 -> 0 | J6: =IF(J33=0,0,BusPlanCompanyEUR!K57/J33) -> 0 | K6: =IF(K33=0,0,BusPlanCompanyEUR!K59/K33) -> 0 | L6: =SUM(J6:K6)/SUM(G6:H6)-1 -> -1 | M6: =IF(M33=0,0,BusPlanCompanyEUR!M57/M33) -> 0 | N6: =IF(N33=0,0,BusPlanCompanyEUR!M59/N33) -> 0 | O6: =SUM(M6:N6)/SUM(J6:K6)-1 -> #DIV/0! | P6: =IF(P33=0,0,BusPlanCompanyEUR!O57/P33) -> 0 | Q6: =IF(Q33=0,0,BusPlanCompanyEUR!O59/Q33) -> 0 | R6: =SUM(P6:Q6)/SUM(M6:N6)-1 -> #DIV/0! | S6: =IF(S33=0,0,BusPlanCompanyEUR!Q57/S33) -> 0 | T6: =IF(T33=0,0,BusPlanCompanyEUR!Q59/T33) -> 0 | U6: =SUM(S6:T6)/SUM(P6:Q6)-1 -> #DIV/0! | V6: =IF(V33=0,0,BusPlanCompanyEUR!S57/V33) -> 0 | W6: =IF(W33=0,0,BusPlanCompanyEUR!S59/W33) -> 0 | X6: =SUM(V6:W6)/SUM(S6:T6)-1 -> #DIV/0!
C7: Social security expenses per head | D7: 1500 | E7: =IF(E33=0,0,BusPlanCompanyEUR!D60/E33) -> 0 | F7: =E7+D7 -> 1500 | G7: 5500 | H7: =IF(H33=0,0,BusPlanCompanyEUR!I60/H33) -> 0 | I7: =SUM(G7:H7)/SUM(D7:E7)-1 -> 2.6666667 | J7: =IF(J33=0,0,BusPlanCompanyEUR!K58/J33) -> 0 | K7: =IF(K33=0,0,BusPlanCompanyEUR!K60/K33) -> 0 | L7: =SUM(J7:K7)/SUM(G7:H7)-1 -> -1 | M7: =IF(M33=0,0,BusPlanCompanyEUR!M58/M33) -> 0 | N7: =IF(N33=0,0,BusPlanCompanyEUR!M60/N33) -> 0 | O7: =SUM(M7:N7)/SUM(J7:K7)-1 -> #DIV/0! | P7: =IF(P33=0,0,BusPlanCompanyEUR!O58/P33) -> 0 | Q7: =IF(Q33=0,0,BusPlanCompanyEUR!O60/Q33) -> 0 | R7: =SUM(P7:Q7)/SUM(M7:N7)-1 -> #DIV/0! | S7: =IF(S33=0,0,BusPlanCompanyEUR!Q58/S33) -> 0 | T7: =IF(T33=0,0,BusPlanCompanyEUR!Q60/T33) -> 0 | U7: =SUM(S7:T7)/SUM(P7:Q7)-1 -> #DIV/0! | V7: =IF(V33=0,0,BusPlanCompanyEUR!S58/V33) -> 0 | W7: =IF(W33=0,0,BusPlanCompanyEUR!S60/W33) -> 0 | X7: =SUM(V7:W7)/SUM(S7:T7)-1 -> #DIV/0!
C8: Staff expenses per head | D8: =SUM(D6:D7) -> 5500 | E8: =SUM(E6:E7) -> 0 | F8: =SUM(F6:F7) -> 5500 | G8: =SUM(G6:G7) -> 9500 | H8: =SUM(H6:H7) -> 0 | I8: =SUM(G8:H8)/SUM(D8:E8)-1 -> 0.72727273 | J8: =SUM(J6:J7) -> 0 | K8: =SUM(K6:K7) -> 0 | L8: =SUM(J8:K8)/SUM(G8:H8)-1 -> -1 | M8: =SUM(M6:M7) -> 0 | N8: =SUM(N6:N7) -> 0 | O8: =SUM(M8:N8)/SUM(J8:K8)-1 -> #DIV/0! | P8: =SUM(P6:P7) -> 0 | Q8: =SUM(Q6:Q7) -> 0 | R8: =SUM(P8:Q8)/SUM(M8:N8)-1 -> #DIV/0! | S8: =SUM(S6:S7) -> 0 | T8: =SUM(T6:T7) -> 0 | U8: =SUM(S8:T8)/SUM(P8:Q8)-1 -> #DIV/0! | V8: =SUM(V6:V7) -> 0 | W8: =SUM(W6:W7) -> 0 | X8: =SUM(V8:W8)/SUM(S8:T8)-1 -> #DIV/0!
B10: SUMMARY
B11: HEAD COUNT | D11: =G11-1 -> 2020 | G11: =START!$C$14 -> 2021 | J11: =+G11+1 -> 2022 | M11: =+J11+1 -> 2023 | P11: =+M11+1 -> 2024 | S11: =+P11+1 -> 2025 | V11: =+S11+1 -> 2026
D12: Blue | E12: White | F12: Total | G12: Blue | H12: White | I12: Total | J12: Blue | K12: White | L12: Total | M12: Blue | N12: White | O12: Total | P12: Blue | Q12: White | R12: Total | S12: Blue | T12: White | U12: Total | V12: Blue | W12: White | X12: Total
B13: Depot Manager | C13: FTE Empl. | D13: =D39 -> 0 | E13: =E39 -> 0 | F13: =F39+F65 -> 0 | G13: =G39+G65 -> 0 | H13: =H39+H65 -> 0 | I13: =I39+I65 -> 0 | J13: =J39+J65 -> 0 | K13: =K39+K65 -> 0 | L13: =L39+L65 -> 0 | M13: =M39+M65 -> 0 | ... X13: =X39+X65 -> 0
C14: FTE Temps | D14: =D40 -> 0 | E14: =E40 -> 0 | F14: =F40+F66 -> 0 | G14: =G40+G66 -> 0 | H14: =H40+H66 -> 0 | I14: =I40+I66 -> 0 | J14: =J40+J66 -> 0 | K14: =K40+K66 -> 0 | L14: =L40+L66 -> 0 | M14: =M40+M66 -> 0 | ... X14: =X40+X66 -> 0
C15: Total | D15: =D41 -> 0 | E15: =E41 -> 0 | F15: =F41+F67 -> 0 | G15: =G41+G67 -> 0 | H15: =H41+H67 -> 0 | I15: =I41+I67 -> 0 | J15: =J41+J67 -> 0 | K15: =K41+K67 -> 0 | L15: =L41+L67 -> 0 | M15: =M41+M67 -> 0 | ... X15: =X41+X67 -> 0
B16: Sales | C16: FTE Empl. | D16: =D42 -> 0 | E16: =E42 -> 0 | F16: =F42+F68 -> 0 | G16: =G42+G68 -> 0 | H16: =H42+H68 -> 0 | I16: =I42+I68 -> 0 | J16: =J42+J68 -> 0 | K16: =K42+K68 -> 0 | L16: =L42+L68 -> 0 | M16: =M42+M68 -> 0 | ... X16: =X42+X68 -> 0
C17: FTE Temps | D17: =D43 -> 0 | E17: =E43 -> 0 | F17: =F43+F69 -> 0 | G17: =G43+G69 -> 0 | H17: =H43+H69 -> 0 | I17: =I43+I69 -> 0 | J17: =J43+J69 -> 0 | K17: =K43+K69 -> 0 | L17: =L43+L69 -> 0 | M17: =M43+M69 -> 0 | ... X17: =X43+X69 -> 0
C18: Total | D18: =D44 -> 0 | E18: =E44 -> 0 | F18: =F44+F70 -> 0 | G18: =G44+G70 -> 0 | H18: =H44+H70 -> 0 | I18: =I44+I70 -> 0 | J18: =J44+J70 -> 0 | K18: =K44+K70 -> 0 | L18: =L44+L70 -> 0 | M18: =M44+M70 -> 0 | ... X18: =X44+X70 -> 0
B19: Production | C19: FTE Empl. | D19: =D45 -> 0 | E19: =E45 -> 0 | F19: =F45+F71 -> 0 | G19: =G45+G71 -> 0 | H19: =H45+H71 -> 0 | I19: =I45+I71 -> 0 | J19: =J45+J71 -> 22 | K19: =K45+K71 -> 0 | L19: =L45+L71 -> 22 | M19: =M45+M71 -> 22 | ... X19: =X45+X71 -> 0
C20: FTE Temps | D20: =D46 -> 0 | E20: =E46 -> 0 | F20: =F46+F72 -> 0 | G20: =G46+G72 -> 0 | H20: =H46+H72 -> 0 | I20: =I46+I72 -> 0 | J20: =J46+J72 -> 0 | K20: =K46+K72 -> 0 | L20: =L46+L72 -> 0 | M20: =M46+M72 -> 0 | ... X20: =X46+X72 -> 0
C21: Total | D21: =D47 -> 0 | E21: =E47 -> 0 | F21: =F47+F73 -> 0 | G21: =G47+G73 -> 0 | H21: =H47+H73 -> 0 | I21: =I47+I73 -> 0 | J21: =J47+J73 -> 22 | K21: =K47+K73 -> 0 | L21: =L47+L73 -> 22 | M21: =M47+M73 -> 22 | ... X21: =X47+X73 -> 0
B22: Drivers | C22: FTE Empl. | D22: =D48 -> 0 | E22: =E48 -> 0 | F22: =F48+F74 -> 0 | G22: =G48+G74 -> 0 | H22: =H48+H74 -> 0 | I22: =I48+I74 -> 0 | J22: =J48+J74 -> 1 | K22: =K48+K74 -> 0 | L22: =L48+L74 -> 1 | M22: =M48+M74 -> 1 | ... X22: =X48+X74 -> 0
C23: FTE Temps | D23: =D49 -> 0 | E23: =E49 -> 0 | F23: =F49+F75 -> 0 | G23: =G49+G75 -> 0 | H23: =H49+H75 -> 0 | I23: =I49+I75 -> 0 | J23: =J49+J75 -> 0 | K23: =K49+K75 -> 0 | L23: =L49+L75 -> 0 | M23: =M49+M75 -> 0 | ... X23: =X49+X75 -> 0
C24: Total | D24: =D50 -> 0 | E24: =E50 -> 0 | F24: =F50+F76 -> 0 | G24: =G50+G76 -> 0 | H24: =H50+H76 -> 0 | I24: =I50+I76 -> 0 | J24: =J50+J76 -> 1 | K24: =K50+K76 -> 0 | L24: =L50+L76 -> 1 | M24: =M50+M76 -> 1 | ... X24: =X50+X76 -> 0
B25: Administration | C25: FTE Empl. | D25: =D51 -> 0 | E25: =E51 -> 0 | F25: =F51+F77 -> 0 | G25: =G51+G77 -> 0 | H25: =H51+H77 -> 0 | I25: =I51+I77 -> 0 | J25: =J51+J77 -> 0 | K25: =K51+K77 -> 2 | L25: =L51+L77 -> 2 | M25: =M51+M77 -> 0 | ... X25: =X51+X77 -> 0
C26: FTE Temps | D26: =D52 -> 0 | E26: =E52 -> 0 | F26: =F52+F78 -> 0 | G26: =G52+G78 -> 0 | H26: =H52+H78 -> 0 | I26: =I52+I78 -> 0 | J26: =J52+J78 -> 0 | K26: =K52+K78 -> 0 | L26: =L52+L78 -> 0 | M26: =M52+M78 -> 0 | ... X26: =X52+X78 -> 0
C27: Total | D27: =D53 -> 0 | E27: =E53 -> 0 | F27: =F53+F79 -> 0 | G27: =G53+G79 -> 0 | H27: =H53+H79 -> 0 | I27: =I53+I79 -> 0 | J27: =J53+J79 -> 0 | K27: =K53+K79 -> 2 | L27: =L53+L79 -> 2 | M27: =M53+M79 -> 0 | ... X27: =X53+X79 -> 0
B28: Others | C28: FTE Empl. | D28: =D54 -> 0 | E28: =E54 -> 0 | F28: =F54+F80 -> 0 | G28: =G54+G80 -> 0 | H28: =H54+H80 -> 0 | I28: =I54+I80 -> 0 | J28: =J54+J80 -> 0 | K28: =K54+K80 -> 0 | L28: =L54+L80 -> 0 | M28: =M54+M80 -> 0 | ... X28: =X54+X80 -> 0
C29: FTE Temps | D29: =D55 -> 0 | E29: =E55 -> 0 | F29: =F55+F81 -> 0 | G29: =G55+G81 -> 0 | H29: =H55+H81 -> 0 | I29: =I55+I81 -> 0 | J29: =J55+J81 -> 0 | K29: =K55+K81 -> 0 | L29: =L55+L81 -> 0 | M29: =M55+M81 -> 0 | ... X29: =X55+X81 -> 0
C30: Total | D30: =D56 -> 0 | E30: =E56 -> 0 | F30: =F56+F82 -> 0 | G30: =G56+G82 -> 0 | H30: =H56+H82 -> 0 | I30: =I56+I82 -> 0 | J30: =J56+J82 -> 0 | K30: =K56+K82 -> 0 | L30: =L56+L82 -> 0 | M30: =M56+M82 -> 0 | ... X30: =X56+X82 -> 0
B31: Total | C31: FTE Empl. | D31: =D57+D83 -> 0 | E31: =E57+E83 -> 0 | F31: =F57+F83 -> 0 | G31: =G57+G83 -> 0 | H31: =H57+H83 -> 0 | I31: =I57+I83 -> 0 | J31: =J57+J83 -> 23 | K31: =K57+K83 -> 2 | ... X31: =X57+X83 -> 0
C32: FTE Temps | D32: =D58+D84 -> 0 | E32: =E58+E84 -> 0 | F32: =F58+F84 -> 0 | G32: =G58+G84 -> 0 | H32: =H58+H84 -> 0 | I32: =I58+I84 -> 0 | J32: =J58+J84 -> 0 | K32: =K58+K84 -> 0 | ... X32: =X58+X84 -> 0
C33: Total | D33: =D59+D85 -> 0 | E33: =E59+E85 -> 0 | F33: =F59+F85 -> 0 | G33: =G59+G85 -> 0 | H33: =H59+H85 -> 0 | I33: =I59+I85 -> 0 | J33: =J59+J85 -> 23 | K33: =K59+K85 -> 2 | ... X33: =X59+X85 -> 0
B35: Actual employees
C37: Period | D37: =G37-1 -> 2020 | G37: =START!$C$14 -> 2021 | J37: =+G37+1 -> 2022 | M37: =+J37+1 -> 2023 | P37: =+M37+1 -> 2024 | S37: =+P37+1 -> 2025 | V37: =+S37+1 -> 2026
D38: Blue | E38: White | F38: Total | G38: Blue | H38: White | I38: Total | J38: Blue | K38: White | L38: Total | M38: Blue | N38: White | O38: Total | P38: Blue | Q38: White | R38: Total | S38: Blue | T38: White | U38: Total | V38: Blue | W38: White | X38: Total
B39: Depot Manager | C39: FTE Empl. | F39: =SUM(D39:E39) -> 0 | I39: =SUM(G39:H39) -> 0 | L39: =SUM(J39:K39) -> 0 | O39: =SUM(M39:N39) -> 0 | R39: =SUM(P39:Q39) -> 0 | U39: =SUM(S39:T39) -> 0 | X39: =SUM(V39:W39) -> 0
C40: FTE Temps | F40: =SUM(D40:E40) -> 0 | I40: =SUM(G40:H40) -> 0 | L40: =SUM(J40:K40) -> 0 | O40: =SUM(M40:N40) -> 0 | R40: =SUM(P40:Q40) -> 0 | U40: =SUM(S40:T40) -> 0 | X40: =SUM(V40:W40) -> 0
C41: Total | D41: =SUM(D39:D40) -> 0 | E41: =SUM(E39:E40) -> 0 | F41: =SUM(F39:F40) -> 0 | G41: =SUM(G39:G40) -> 0 | H41: =SUM(H39:H40) -> 0 | I41: =SUM(I39:I40) -> 0 | J41: =SUM(J39:J40) -> 0 | K41: =SUM(K39:K40) -> 0 | ... X41: =SUM(X39:X40) -> 0
B42: Sales | C42: FTE Empl. | F42: =SUM(D42:E42) -> 0 | I42: =SUM(G42:H42) -> 0 | L42: =SUM(J42:K42) -> 0 | O42: =SUM(M42:N42) -> 0 | R42: =SUM(P42:Q42) -> 0 | U42: =SUM(S42:T42) -> 0 | X42: =SUM(V42:W42) -> 0
C43: FTE Temps | F43: =SUM(D43:E43) -> 0 | I43: =SUM(G43:H43) -> 0 | L43: =SUM(J43:K43) -> 0 | O43: =SUM(M43:N43) -> 0 | R43: =SUM(P43:Q43) -> 0 | U43: =SUM(S43:T43) -> 0 | X43: =SUM(V43:W43) -> 0
C44: Total | D44: =SUM(D42:D43) -> 0 | E44: =SUM(E42:E43) -> 0 | F44: =SUM(F42:F43) -> 0 | G44: =SUM(G42:G43) -> 0 | H44: =SUM(H42:H43) -> 0 | I44: =SUM(I42:I43) -> 0 | J44: =SUM(J42:J43) -> 0 | K44: =SUM(K42:K43) -> 0 | ... X44: =SUM(X42:X43) -> 0
B45: Production | C45: FTE Empl. | F45: =SUM(D45:E45) -> 0 | I45: =SUM(G45:H45) -> 0 | L45: =SUM(J45:K45) -> 0 | O45: =SUM(M45:N45) -> 0 | R45: =SUM(P45:Q45) -> 0 | U45: =SUM(S45:T45) -> 0 | X45: =SUM(V45:W45) -> 0
C46: FTE Temps | F46: =SUM(D46:E46) -> 0 | I46: =SUM(G46:H46) -> 0 | L46: =SUM(J46:K46) -> 0 | O46: =SUM(M46:N46) -> 0 | R46: =SUM(P46:Q46) -> 0 | U46: =SUM(S46:T46) -> 0 | X46: =SUM(V46:W46) -> 0
C47: Total | D47: =SUM(D45:D46) -> 0 | E47: =SUM(E45:E46) -> 0 | F47: =SUM(F45:F46) -> 0 | G47: =SUM(G45:G46) -> 0 | H47: =SUM(H45:H46) -> 0 | I47: =SUM(I45:I46) -> 0 | J47: =SUM(J45:J46) -> 0 | K47: =SUM(K45:K46) -> 0 | ... X47: =SUM(X45:X46) -> 0
B48: Drivers | C48: FTE Empl. | F48: =SUM(D48:E48) -> 0 | I48: =SUM(G48:H48) -> 0 | L48: =SUM(J48:K48) -> 0 | O48: =SUM(M48:N48) -> 0 | R48: =SUM(P48:Q48) -> 0 | U48: =SUM(S48:T48) -> 0 | X48: =SUM(V48:W48) -> 0
C49: FTE Temps | F49: =SUM(D49:E49) -> 0 | I49: =SUM(G49:H49) -> 0 | L49: =SUM(J49:K49) -> 0 | O49: =SUM(M49:N49) -> 0 | R49: =SUM(P49:Q49) -> 0 | U49: =SUM(S49:T49) -> 0 | X49: =SUM(V49:W49) -> 0
C50: Total | D50: =SUM(D48:D49) -> 0 | E50: =SUM(E48:E49) -> 0 | F50: =SUM(F48:F49) -> 0 | G50: =SUM(G48:G49) -> 0 | H50: =SUM(H48:H49) -> 0 | I50: =SUM(I48:I49) -> 0 | J50: =SUM(J48:J49) -> 0 | K50: =SUM(K48:K49) -> 0 | ... X50: =SUM(X48:X49) -> 0
B51: Administration | C51: FTE Empl. | F51: =SUM(D51:E51) -> 0 | I51: =SUM(G51:H51) -> 0 | L51: =SUM(J51:K51) -> 0 | O51: =SUM(M51:N51) -> 0 | R51: =SUM(P51:Q51) -> 0 | U51: =SUM(S51:T51) -> 0 | X51: =SUM(V51:W51) -> 0
C52: FTE Temps | F52: =SUM(D52:E52) -> 0 | I52: =SUM(G52:H52) -> 0 | L52: =SUM(J52:K52) -> 0 | O52: =SUM(M52:N52) -> 0 | R52: =SUM(P52:Q52) -> 0 | U52: =SUM(S52:T52) -> 0 | X52: =SUM(V52:W52) -> 0
C53: Total | D53: =SUM(D51:D52) -> 0 | E53: =SUM(E51:E52) -> 0 | F53: =SUM(F51:F52) -> 0 | G53: =SUM(G51:G52) -> 0 | H53: =SUM(H51:H52) -> 0 | I53: =SUM(I51:I52) -> 0 | J53: =SUM(J51:J52) -> 0 | K53: =SUM(K51:K52) -> 0 | ... X53: =SUM(X51:X52) -> 0
B54: Others | C54: FTE Empl. | F54: =SUM(D54:E54) -> 0 | I54: =SUM(G54:H54) -> 0 | L54: =SUM(J54:K54) -> 0 | O54: =SUM(M54:N54) -> 0 | R54: =SUM(P54:Q54) -> 0 | U54: =SUM(S54:T54) -> 0 | X54: =SUM(V54:W54) -> 0
C55: FTE Temps | F55: =SUM(D55:E55) -> 0 | I55: =SUM(G55:H55) -> 0 | L55: =SUM(J55:K55) -> 0 | O55: =SUM(M55:N55) -> 0 | R55: =SUM(P55:Q55) -> 0 | U55: =SUM(S55:T55) -> 0 | X55: =SUM(V55:W55) -> 0
C56: Total | D56: =SUM(D54:D55) -> 0 | E56: =SUM(E54:E55) -> 0 | F56: =SUM(F54:F55) -> 0 | G56: =SUM(G54:G55) -> 0 | H56: =SUM(H54:H55) -> 0 | I56: =SUM(I54:I55) -> 0 | J56: =SUM(J54:J55) -> 0 | K56: =SUM(K54:K55) -> 0 | ... X56: =SUM(X54:X55) -> 0
B57: Total | C57: FTE Empl. | D57: =D39+D45+D42+D51+D54+D48 -> 0 | E57: =E39+E45+E42+E51+E54+E48 -> 0 | F57: =F39+F45+F42+F51+F54+F48 -> 0 | G57: =G39+G45+G42+G51+G54+G48 -> 0 | H57: =H39+H45+H42+H51+H54+H48 -> 0 | I57: =I39+I45+I42+I51+I54+I48 -> 0 | J57: =J39+J45+J42+J51+J54+J48 -> 0 | K57: =K39+K45+K42+K51+K54+K48 -> 0 | ... X57: =X39+X45+X42+X51+X54+X48 -> 0
C58: FTE Temps | D58: =D40+D46+D43+D52+D55+D49 -> 0 | E58: =E40+E46+E43+E52+E55+E49 -> 0 | F58: =F40+F46+F43+F52+F55+F49 -> 0 | G58: =G40+G46+G43+G52+G55+G49 -> 0 | H58: =H40+H46+H43+H52+H55+H49 -> 0 | I58: =I40+I46+I43+I52+I55+I49 -> 0 | J58: =J40+J46+J43+J52+J55+J49 -> 0 | K58: =K40+K46+K43+K52+K55+K49 -> 0 | ... X58: =X40+X46+X43+X52+X55+X49 -> 0
C59: Total | D59: =D41+D47+D44+D53+D56+D50 -> 0 | E59: =E41+E47+E44+E53+E56+E50 -> 0 | F59: =F41+F47+F44+F53+F56+F50 -> 0 | G59: =G41+G47+G44+G53+G56+G50 -> 0 | H59: =H41+H47+H44+H53+H56+H50 -> 0 | I59: =I41+I47+I44+I53+I56+I50 -> 0 | J59: =J41+J47+J44+J53+J56+J50 -> 0 | K59: =K41+K47+K44+K53+K56+K50 -> 0 | ... X59: =X41+X47+X44+X53+X56+X50 -> 0
B61: Additional employees (BusPlan)
C63: Period | D63: =G63-1 -> 2020 | G63: =START!$C$14 -> 2021 | J63: =+G63+1 -> 2022 | M63: =+J63+1 -> 2023 | P63: =+M63+1 -> 2024 | S63: =+P63+1 -> 2025 | V63: =+S63+1 -> 2026
D64: Blue | E64: White | F64: Total | G64: Blue | H64: White | I64: Total | J64: Blue | K64: White | L64: Total | M64: Blue | N64: White | O64: Total | P64: Blue | Q64: White | R64: Total | S64: Blue | T64: White | U64: Total | V64: Blue | W64: White | X64: Total
B65: Depot Manager | C65: FTE Empl. | F65: =SUM(D65:E65) -> 0 | I65: =SUM(G65:H65) -> 0 | L65: =SUM(J65:K65) -> 0 | O65: =SUM(M65:N65) -> 0 | R65: =SUM(P65:Q65) -> 0 | U65: =SUM(S65:T65) -> 0 | X65: =SUM(V65:W65) -> 0
C66: FTE Temps | F66: =SUM(D66:E66) -> 0 | I66: =SUM(G66:H66) -> 0 | L66: =SUM(J66:K66) -> 0 | O66: =SUM(M66:N66) -> 0 | R66: =SUM(P66:Q66) -> 0 | U66: =SUM(S66:T66) -> 0 | X66: =SUM(V66:W66) -> 0
C67: Total | F67: =SUM(F65:F66) -> 0 | G67: =SUM(G65:G66) -> 0 | H67: =SUM(H65:H66) -> 0 | I67: =SUM(I65:I66) -> 0 | J67: =SUM(J65:J66) -> 0 | K67: =SUM(K65:K66) -> 0 | L67: =SUM(L65:L66) -> 0 | M67: =SUM(M65:M66) -> 0 | ... X67: =SUM(X65:X66) -> 0
B68: Sales | C68: FTE Empl. | F68: =SUM(D68:E68) -> 0 | I68: =SUM(G68:H68) -> 0 | L68: =SUM(J68:K68) -> 0 | O68: =SUM(M68:N68) -> 0 | R68: =SUM(P68:Q68) -> 0 | U68: =SUM(S68:T68) -> 0 | X68: =SUM(V68:W68) -> 0
C69: FTE Temps | F69: =SUM(D69:E69) -> 0 | I69: =SUM(G69:H69) -> 0 | L69: =SUM(J69:K69) -> 0 | O69: =SUM(M69:N69) -> 0 | R69: =SUM(P69:Q69) -> 0 | U69: =SUM(S69:T69) -> 0 | X69: =SUM(V69:W69) -> 0
C70: Total | F70: =SUM(F68:F69) -> 0 | G70: =SUM(G68:G69) -> 0 | H70: =SUM(H68:H69) -> 0 | I70: =SUM(I68:I69) -> 0 | J70: =SUM(J68:J69) -> 0 | K70: =SUM(K68:K69) -> 0 | L70: =SUM(L68:L69) -> 0 | M70: =SUM(M68:M69) -> 0 | ... X70: =SUM(X68:X69) -> 0
B71: Production | C71: FTE Empl. | F71: =SUM(D71:E71) -> 0 | I71: =SUM(G71:H71) -> 0 | J71: 22 | L71: =SUM(J71:K71) -> 22 | M71: 22 | O71: =SUM(M71:N71) -> 22 | R71: =SUM(P71:Q71) -> 0 | U71: =SUM(S71:T71) -> 0 | X71: =SUM(V71:W71) -> 0
C72: FTE Temps | F72: =SUM(D72:E72) -> 0 | I72: =SUM(G72:H72) -> 0 | L72: =SUM(J72:K72) -> 0 | O72: =SUM(M72:N72) -> 0 | R72: =SUM(P72:Q72) -> 0 | U72: =SUM(S72:T72) -> 0 | X72: =SUM(V72:W72) -> 0
C73: Total | F73: =SUM(F71:F72) -> 0 | G73: =SUM(G71:G72) -> 0 | H73: =SUM(H71:H72) -> 0 | I73: =SUM(I71:I72) -> 0 | J73: =SUM(J71:J72) -> 22 | K73: =SUM(K71:K72) -> 0 | L73: =SUM(L71:L72) -> 22 | M73: =SUM(M71:M72) -> 22 | ... X73: =SUM(X71:X72) -> 0
B74: Drivers | C74: FTE Empl. | F74: =SUM(D74:E74) -> 0 | I74: =SUM(G74:H74) -> 0 | J74: 1 | L74: =SUM(J74:K74) -> 1 | M74: 1 | O74: =SUM(M74:N74) -> 1 | R74: =SUM(P74:Q74) -> 0 | U74: =SUM(S74:T74) -> 0 | X74: =SUM(V74:W74) -> 0
C75: FTE Temps | F75: =SUM(D75:E75) -> 0 | I75: =SUM(G75:H75) -> 0 | L75: =SUM(J75:K75) -> 0 | O75: =SUM(M75:N75) -> 0 | R75: =SUM(P75:Q75) -> 0 | U75: =SUM(S75:T75) -> 0 | X75: =SUM(V75:W75) -> 0
C76: Total | F76: =SUM(F74:F75) -> 0 | G76: =SUM(G74:G75) -> 0 | H76: =SUM(H74:H75) -> 0 | I76: =SUM(I74:I75) -> 0 | J76: =SUM(J74:J75) -> 1 | K76: =SUM(K74:K75) -> 0 | L76: =SUM(L74:L75) -> 1 | M76: =SUM(M74:M75) -> 1 | ... X76: =SUM(X74:X75) -> 0
B77: Administration | C77: FTE Empl. | F77: =SUM(D77:E77) -> 0 | I77: =SUM(G77:H77) -> 0 | K77: 2 | L77: =SUM(J77:K77) -> 2 | N77: 2 | O77: =SUM(M77:N77) -> 2 | R77: =SUM(P77:Q77) -> 0 | U77: =SUM(S77:T77) -> 0 | X77: =SUM(V77:W77) -> 0
C78: FTE Temps | F78: =SUM(D78:E78) -> 0 | I78: =SUM(G78:H78) -> 0 | L78: =SUM(J78:K78) -> 0 | O78: =SUM(M78:N78) -> 0 | R78: =SUM(P78:Q78) -> 0 | U78: =SUM(S78:T78) -> 0 | X78: =SUM(V78:W78) -> 0
C79: Total | F79: =SUM(F77:F78) -> 0 | G79: =SUM(G77:G78) -> 0 | H79: =SUM(H77:H78) -> 0 | I79: =SUM(I77:I78) -> 0 | J79: =SUM(J77:J78) -> 0 | K79: =SUM(K77:K78) -> 2 | L79: =SUM(L77:L78) -> 2 | M79: =SUM(M77:M78) -> 0 | ... X79: =SUM(X77:X78) -> 0
B80: Others | C80: FTE Empl. | F80: =SUM(D80:E80) -> 0 | I80: =SUM(G80:H80) -> 0 | L80: =SUM(J80:K80) -> 0 | O80: =SUM(M80:N80) -> 0 | R80: =SUM(P80:Q80) -> 0 | U80: =SUM(S80:T80) -> 0 | X80: =SUM(V80:W80) -> 0
C81: FTE Temps | F81: =SUM(D81:E81) -> 0 | I81: =SUM(G81:H81) -> 0 | L81: =SUM(J81:K81) -> 0 | O81: =SUM(M81:N81) -> 0 | R81: =SUM(P81:Q81) -> 0 | U81: =SUM(S81:T81) -> 0 | X81: =SUM(V81:W81) -> 0
C82: Total | F82: =SUM(F80:F81) -> 0 | G82: =SUM(G80:G81) -> 0 | H82: =SUM(H80:H81) -> 0 | I82: =SUM(I80:I81) -> 0 | J82: =SUM(J80:J81) -> 0 | K82: =SUM(K80:K81) -> 0 | L82: =SUM(L80:L81) -> 0 | M82: =SUM(M80:M81) -> 0 | ... X82: =SUM(X80:X81) -> 0
B83: Total | C83: FTE Empl. | D83: =D65+D71+D68+D77+D80+D74 -> 0 | E83: =E65+E71+E68+E77+E80+E74 -> 0 | F83: =F65+F71+F68+F77+F80+F74 -> 0 | G83: =G65+G71+G68+G77+G80+G74 -> 0 | H83: =H65+H71+H68+H77+H80+H74 -> 0 | I83: =I65+I71+I68+I77+I80+I74 -> 0 | J83: =J65+J71+J68+J77+J80+J74 -> 23 | K83: =K65+K71+K68+K77+K80+K74 -> 2 | ... X83: =X65+X71+X68+X77+X80+X74 -> 0
C84: FTE Temps | D84: =D66+D72+D69+D78+D81+D75 -> 0 | E84: =E66+E72+E69+E78+E81+E75 -> 0 | F84: =F66+F72+F69+F78+F81+F75 -> 0 | G84: =G66+G72+G69+G78+G81+G75 -> 0 | H84: =H66+H72+H69+H78+H81+H75 -> 0 | I84: =I66+I72+I69+I78+I81+I75 -> 0 | J84: =J66+J72+J69+J78+J81+J75 -> 0 | K84: =K66+K72+K69+K78+K81+K75 -> 0 | ... X84: =X66+X72+X69+X78+X81+X75 -> 0
C85: Total | D85: =D67+D73+D70+D79+D82+D76 -> 0 | E85: =E67+E73+E70+E79+E82+E76 -> 0 | F85: =F67+F73+F70+F79+F82+F76 -> 0 | G85: =G67+G73+G70+G79+G82+G76 -> 0 | H85: =H67+H73+H70+H79+H82+H76 -> 0 | I85: =I67+I73+I70+I79+I82+I76 -> 0 | J85: =J67+J73+J70+J79+J82+J76 -> 23 | K85: =K67+K73+K70+K79+K82+K76 -> 2 | ... X85: =X67+X73+X70+X79+X82+X76 -> 0

Sheet ReturnCalcBusPlanLoc
A1: Return Calculation based on additonal business
A3: =+BusPlanLocation!C7 -> 166101 Bornova | C3: Business Plan Periods
A4: Currency: | C4: =START!$C$14 -> 2021 | D4: =C4+1 -> 2022 | E4: =D4+1 -> 2023 | F4: =E4+1 -> 2024 | G4: =F4+1 -> 2025 | H4: =G4+1 -> 2026 | J4: =H4+1 -> 2027 | K4: =J4+1 -> 2028 | L4: =J4+1 -> 2028 | M4: =L4+1 -> 2029 | N4: =L4+1 -> 2029 | O4: =N4+1 -> 2030 | P4: =N4+1 -> 2030 | Q4: =P4+1 -> 2031 | R4: =P4+1 -> 2031 | S4: =R4+1 -> 2032 | T4: =R4+1 -> 2032
A5: =+BusPlanLocation!C9 -> EUR | C5: =+BusPlanLocation!I9 -> Business Plan | D5: =+BusPlanLocation!K9 -> Business Plan | E5: =+BusPlanLocation!M9 -> Business Plan | F5: =+BusPlanLocation!O9 -> Business Plan | G5: =+BusPlanLocation!Q9 -> Business Plan | H5: =+BusPlanLocation!S9 -> Business Plan
C6: =+BusPlanLocation!I10 -> in 1.000 EUR | D6: =+BusPlanLocation!K10 -> in 1.000 EUR | E6: =+BusPlanLocation!M10 -> in 1.000 EUR | F6: =+BusPlanLocation!O10 -> in 1.000 EUR | G6: =+BusPlanLocation!Q10 -> in 1.000 EUR | H6: =+BusPlanLocation!S10 -> in 1.000 EUR
A7: Management Summary
A8: EBITDA | C8: =+BusPlanLocation!I92 -> #REF! | D8: =+BusPlanLocation!K92 -> #REF! | E8: =+BusPlanLocation!M92 -> #REF! | F8: =+BusPlanLocation!O92 -> 0 | G8: =+BusPlanLocation!Q92 -> 0 | H8: =+BusPlanLocation!S92 -> 0
A9: EBIT | C9: =+BusPlanLocation!I98 -> #REF! | D9: =+BusPlanLocation!K98 -> #REF! | E9: =+BusPlanLocation!M98 -> #REF! | F9: =+BusPlanLocation!O98 -> 0 | G9: =+BusPlanLocation!Q98 -> 0 | H9: =+BusPlanLocation!S98 -> 0
A10: EBT | C10: =+BusPlanLocation!I127 -> #REF! | D10: =+BusPlanLocation!K127 -> #REF! | E10: =+BusPlanLocation!M127 -> #REF! | F10: =+BusPlanLocation!O129 -> 0 | G10: =+BusPlanLocation!Q127 -> 0 | H10: =+BusPlanLocation!S127 -> 0
A11: Sales in tons
